Workbook
Name Types: Списки!$A$2:$A$7
Name Currencies: Списки!$B$2:$B$7
Name Materials: Списки!$C$2:$C$10
Name Construction: Списки!$D$2:$D$5
Name Commercial: Списки!$E$2:$E$5
Name Purpose: Списки!$F$2:$F$6
Name YesNo: Списки!$G$2:$G$3
Name DebtFormats: Списки!$H$2:$H$3
Name Goals: Списки!$I$2:$I$8

Sheet Сводка
A1: Сбор объектов по вариантам покупки
A2: Одна строка — один объект. Справа на листе видно, чего не хватает для публикации в форме добавления.
A4: Вариант | B4: В таблице | C4: Можно публиковать | D4: Не хватает | E4: Что проверяет лист
A5: Купить сейчас | B5: =COUNTIF('Купить сейчас'!AO3:AO82,"<>") | C5: =COUNTIF('Купить сейчас'!AO3:AO82,"Можно публиковать") | D5: =COUNTIF('Купить сейчас'!AO3:AO82,"Не хватает") | E5: Формат «Аукцион + Продать сейчас»: фиксированная цена, минимальная цена, стартовая ставка, даты и документы.
A6: Аукцион | B6: =COUNTIF('Аукцион'!AO3:AO82,"<>") | C6: =COUNTIF('Аукцион'!AO3:AO82,"Можно публиковать") | D6: =COUNTIF('Аукцион'!AO3:AO82,"Не хватает") | E6: Торги без обязательной цены «Продать сейчас». Минимальная цена, ставка и срок аукциона обязательны.
A7: Доли | B7: =COUNTIF('Доли'!AK3:AK82,"<>") | C7: =COUNTIF('Доли'!AK3:AK82,"Можно публиковать") | D7: =COUNTIF('Доли'!AK3:AK82,"Не хватает") | E7: Общая стоимость и число долей. Цена одной доли считается сама. Тест-драйва в этом формате нет.
A8: Долги | B8: =COUNTIF('Долги'!AQ3:AQ82,"<>") | C8: =COUNTIF('Долги'!AQ3:AQ82,"Можно публиковать") | D8: =COUNTIF('Долги'!AQ3:AQ82,"Не хватает") | E8: Сумма долга. Аукционные поля включаются только если формат — «Долги + Аукцион». Пакет долга желателен, но не блокирует.
A9: Девелопмент | B9: =COUNTIF('Девелопмент'!AV3:AV82,"<>") | C9: =COUNTIF('Девелопмент'!AV3:AV82,"Можно публиковать") | D9: =COUNTIF('Девелопмент'!AV3:AV82,"Не хватает") | E9: Адрес и параметры объекта плюс экономика проекта. Бюджет и прибыль считаются сами.
A11: Как читать таблицу
A12: Поля совпадают с мастером добавления объекта. Обязательность параметров зависит от типа недвижимости.
A13: Квартира и апартаменты: площадь, жилая площадь, комнаты, ванные, этаж, этажность, год и материал.
A14: Дом и вилла: участок, площадь дома, спальни, ванные, этажность, год и материал.
A15: Коммерция: площадь и тип. Земля: участок и назначение.
A16: Для всех вариантов, кроме долгов, нужны документ о праве собственности и справка об отсутствии обременений. Фото — минимум одно.
A17: «Продать сейчас»: минимальная цена не выше самой цены и не выше 90% от неё. Стартовая ставка не выше 30%. Аукцион длится минимум 3 месяца и 15 дней.
A18: «Желательно добрать» не мешает публикации: это описание, кадастр, видео, меньше пяти фото и рекомендованный пакет долга.
A19: Формулы протянуты на 80 строк. Если объектов больше, потяните последнюю заполненную строку вниз.
A20: Комментарий к заголовку колонки объясняет, когда поле обязательно. Лист «Списки» скрыт и питает выпадающие списки.

Sheet Купить сейчас
A1: Сбор | B1: Объект | D1: Адрес | I1: Объект | J1: Параметры | W1: Цена | AB1: Тест-драйв | AE1: Подача | AJ1: Документы | AM1: Проверка
A2: Источник | B2: Название | C2: Тип недвижимости | D2: Страна | E2: Город | F2: Улица | G2: Номер дома | H2: Кадастровый номер | I2: Валюта | J2: Площадь, м² | K2: Жилая, м² | L2: Участок, м² | M2: Комнаты | N2: Спальни | O2: Ванные | P2: Этаж | Q2: Этажей | R2: Год | S2: Материал | T2: Конструкция | U2: Тип коммерции | V2: Назначение земли | W2: Продать сейчас | X2: Минимальная цена | Y2: Стартовая ставка | Z2: Начало аукциона | AA2: Окончание аукциона | AB2: Тест-драйв | AC2: Сутки тест-драйва | AD2: Депозит тест-драйва | AE2: Фото, шт. | AF2: Ссылка на фото | AG2: Ссылка на видео | AH2: Описание | AI2: Удобства | AJ2: Право собственности | AK2: Нет обременений | AL2: Доп. документы | AM2: Не хватает для публикации | AN2: Желательно добрать | AO2: Готовность
AM3: =IF(NOT(COUNTA(A3:AL3)>0),"",IF(TEXTJOIN(", ",TRUE,IF(B3="","Название",""),IF(C3="","Тип недвижимости",""),IF(D3="","Страна",""),IF(E3="","Город",""),IF(F3="","Улица",""),IF(I3="","Валюта",""),IF(OR(AE3="",AE3<1),"Хотя бы 1 фото",""),IF(AND(OR(C3="Квартира",C3="Апартаменты",C3="Дом",C3="Вилла",C3="Коммерческая"),J3=""),"Площадь",""),IF(AND(OR(C3="Квартира",C3="Апартаменты"),K3=""),"Жилая площадь",""),IF(AND(OR(C3="Дом",C3="Вилла",C3="Земля"),L3=""),"Площадь участка",""),IF(AND(OR(C3="Квартира",C3="Апартаменты"),M3=""),"Комнаты",""),IF(AND(OR(C3="Дом",C3="Вилла"),N3=""),"Спальни",""),IF(AND(OR(C3="Квартира",C3="Апартаменты",C3="Дом",C3="Вилла"),O3=""),"Ванные",""),IF(AND(OR(C3="Квартира",C3="Апартаменты"),P3=""),"Этаж",""),IF(AND(OR(OR(C3="Квартира",C3="Апартаменты"),OR(C3="Дом",C3="Вилла")),Q3=""),"Этажей",""),IF(AND(OR(OR(C3="Квартира",C3="Апартаменты"),OR(C3="Дом",C3="Вилла")),OR(R3="",R3>YEAR(TODAY()))),"Год постройки",""),IF(AND(P3<>"",Q3<>"",P3>Q3),"Этаж больше этажности",""),IF(AND(OR(C3="Квартира",C3="Апартаменты",C3="Дом",C3="Вилла"),S3=""),"Материал",""),IF(AND(OR(C3="Коммерческая"),U3=""),"Тип коммерции",""),IF(AND(OR(C3="Земля"),V3=""),"Назначение земли",""),IF(OR(W3="",W3<=0),"Продать сейчас",""),IF(OR(X3="",X3<=0),"Минимальная цена продажи",""),IF(OR(Y3="",Y3<=0),"Стартовая ставка",""),IF(Z3="","Начало аукциона",""),IF(AA3="","Окончание аукциона",""),IF(AND(W3<>"",X3<>"",X3>W3),"Минимальная цена выше «Продать сейчас»",""),IF(AND(W3<>"",X3<>"",X3<=W3,X3>W3*0.9),"Минимальная цена выше 90% от «Продать сейчас»",""),IF(AND(W3<>"",Y3<>"",Y3>W3*0.3),"Стартовая ставка выше 30% от «Продать сейчас»",""),IF(AND(Z3<>"",AA3<>"",AA3<EDATE(Z3,3)+15),"Аукцион короче 3 месяцев и 15 дней",""),IF(AND(AB3="Да",OR(AC3="",AC3<=0)),"Цена тест-драйва за сутки",""),IF(OR(AJ3="",AJ3="Нет"),"Право собственности",""),IF(OR(AK3="",AK3="Нет"),"Справка об отсутствии обременений",""))="","",TEXTJOIN(", ",TRUE,IF(B3="","Название",""),IF(C3="","Тип недвижимости",""),IF(D3="","Страна",""),IF(E3="","Город",""),IF(F3="","Улица",""),IF(I3="","Валюта",""),IF(OR(AE3="",AE3<1),"Хотя бы 1 фото",""),IF(AND(OR(C3="Квартира",C3="Апартаменты",C3="Дом",C3="Вилла",C3="Коммерческая"),J3=""),"Площадь",""),IF(AND(OR(C3="Квартира",C3="Апартаменты"),K3=""),"Жилая площадь",""),IF(AND(OR(C3="Дом",C3="Вилла",C3="Земля"),L3=""),"Площадь участка",""),IF(AND(OR(C3="Квартира",C3="Апартаменты"),M3=""),"Комнаты",""),IF(AND(OR(C3="Дом",C3="Вилла"),N3=""),"Спальни",""),IF(AND(OR(C3="Квартира",C3="Апартаменты",C3="Дом",C3="Вилла"),O3=""),"Ванные",""),IF(AND(OR(C3="Квартира",C3="Апартаменты"),P3=""),"Этаж",""),IF(AND(OR(OR(C3="Квартира",C3="Апартаменты"),OR(C3="Дом",C3="Вилла")),Q3=""),"Этажей",""),IF(AND(OR(OR(C3="Квартира",C3="Апартаменты"),OR(C3="Дом",C3="Вилла")),OR(R3="",R3>YEAR(TODAY()))),"Год постройки",""),IF(AND(P3<>"",Q3<>"",P3>Q3),"Этаж больше этажности",""),IF(AND(OR(C3="Квартира",C3="Апартаменты",C3="Дом",C3="Вилла"),S3=""),"Материал",""),IF(AND(OR(C3="Коммерческая"),U3=""),"Тип коммерции",""),IF(AND(OR(C3="Земля"),V3=""),"Назначение земли",""),IF(OR(W3="",W3<=0),"Продать сейчас",""),IF(OR(X3="",X3<=0),"Минимальная цена продажи",""),IF(OR(Y3="",Y3<=0),"Стартовая ставка",""),IF(Z3="","Начало аукциона",""),IF(AA3="","Окончание аукциона",""),IF(AND(W3<>"",X3<>"",X3>W3),"Минимальная цена выше «Продать сейчас»",""),IF(AND(W3<>"",X3<>"",X3<=W3,X3>W3*0.9),"Минимальная цена выше 90% от «Продать сейчас»",""),IF(AND(W3<>"",Y3<>"",Y3>W3*0.3),"Стартовая ставка выше 30% от «Продать сейчас»",""),IF(AND(Z3<>"",AA3<>"",AA3<EDATE(Z3,3)+15),"Аукцион короче 3 месяцев и 15 дней",""),IF(AND(AB3="Да",OR(AC3="",AC3<=0)),"Цена тест-драйва за сутки",""),IF(OR(AJ3="",AJ3="Нет"),"Право собственности",""),IF(OR(AK3="",AK3="Нет"),"Справка об отсутствии обременений","")))) | AN3: =IF(NOT(COUNTA(A3:AL3)>0),"",IF(TEXTJOIN(", ",TRUE,IF(AH3="","Описание",""),IF(AND(AE3<>"",AE3>=1,AE3<5),"Фото меньше 5",""),IF(AG3="","Видео",""),IF(H3="","Кадастровый номер",""),IF(AF3="","Ссылка на фото",""))="","",TEXTJOIN(", ",TRUE,IF(AH3="","Описание",""),IF(AND(AE3<>"",AE3>=1,AE3<5),"Фото меньше 5",""),IF(AG3="","Видео",""),IF(H3="","Кадастровый номер",""),IF(AF3="","Ссылка на фото","")))) | AO3: =IF(NOT(COUNTA(A3:AL3)>0),"",IF(AM3="","Можно публиковать","Не хватает"))
AM4: =IF(NOT(COUNTA(A4:AL4)>0),"",IF(TEXTJOIN(", ",TRUE,IF(B4="","Название",""),IF(C4="","Тип недвижимости",""),IF(D4="","Страна",""),IF(E4="","Город",""),IF(F4="","Улица",""),IF(I4="","Валюта",""),IF(OR(AE4="",AE4<1),"Хотя бы 1 фото",""),IF(AND(OR(C4="Квартира",C4="Апартаменты",C4="Дом",C4="Вилла",C4="Коммерческая"),J4=""),"Площадь",""),IF(AND(OR(C4="Квартира",C4="Апартаменты"),K4=""),"Жилая площадь",""),IF(AND(OR(C4="Дом",C4="Вилла",C4="Земля"),L4=""),"Площадь участка",""),IF(AND(OR(C4="Квартира",C4="Апартаменты"),M4=""),"Комнаты",""),IF(AND(OR(C4="Дом",C4="Вилла"),N4=""),"Спальни",""),IF(AND(OR(C4="Квартира",C4="Апартаменты",C4="Дом",C4="Вилла"),O4=""),"Ванные",""),IF(AND(OR(C4="Квартира",C4="Апартаменты"),P4=""),"Этаж",""),IF(AND(OR(OR(C4="Квартира",C4="Апартаменты"),OR(C4="Дом",C4="Вилла")),Q4=""),"Этажей",""),IF(AND(OR(OR(C4="Квартира",C4="Апартаменты"),OR(C4="Дом",C4="Вилла")),OR(R4="",R4>YEAR(TODAY()))),"Год постройки",""),IF(AND(P4<>"",Q4<>"",P4>Q4),"Этаж больше этажности",""),IF(AND(OR(C4="Квартира",C4="Апартаменты",C4="Дом",C4="Вилла"),S4=""),"Материал",""),IF(AND(OR(C4="Коммерческая"),U4=""),"Тип коммерции",""),IF(AND(OR(C4="Земля"),V4=""),"Назначение земли",""),IF(OR(W4="",W4<=0),"Продать сейчас",""),IF(OR(X4="",X4<=0),"Минимальная цена продажи",""),IF(OR(Y4="",Y4<=0),"Стартовая ставка",""),IF(Z4="","Начало аукциона",""),IF(AA4="","Окончание аукциона",""),IF(AND(W4<>"",X4<>"",X4>W4),"Минимальная цена выше «Продать сейчас»",""),IF(AND(W4<>"",X4<>"",X4<=W4,X4>W4*0.9),"Минимальная цена выше 90% от «Продать сейчас»",""),IF(AND(W4<>"",Y4<>"",Y4>W4*0.3),"Стартовая ставка выше 30% от «Продать сейчас»",""),IF(AND(Z4<>"",AA4<>"",AA4<EDATE(Z4,3)+15),"Аукцион короче 3 месяцев и 15 дней",""),IF(AND(AB4="Да",OR(AC4="",AC4<=0)),"Цена тест-драйва за сутки",""),IF(OR(AJ4="",AJ4="Нет"),"Право собственности",""),IF(OR(AK4="",AK4="Нет"),"Справка об отсутствии обременений",""))="","",TEXTJOIN(", ",TRUE,IF(B4="","Название",""),IF(C4="","Тип недвижимости",""),IF(D4="","Страна",""),IF(E4="","Город",""),IF(F4="","Улица",""),IF(I4="","Валюта",""),IF(OR(AE4="",AE4<1),"Хотя бы 1 фото",""),IF(AND(OR(C4="Квартира",C4="Апартаменты",C4="Дом",C4="Вилла",C4="Коммерческая"),J4=""),"Площадь",""),IF(AND(OR(C4="Квартира",C4="Апартаменты"),K4=""),"Жилая площадь",""),IF(AND(OR(C4="Дом",C4="Вилла",C4="Земля"),L4=""),"Площадь участка",""),IF(AND(OR(C4="Квартира",C4="Апартаменты"),M4=""),"Комнаты",""),IF(AND(OR(C4="Дом",C4="Вилла"),N4=""),"Спальни",""),IF(AND(OR(C4="Квартира",C4="Апартаменты",C4="Дом",C4="Вилла"),O4=""),"Ванные",""),IF(AND(OR(C4="Квартира",C4="Апартаменты"),P4=""),"Этаж",""),IF(AND(OR(OR(C4="Квартира",C4="Апартаменты"),OR(C4="Дом",C4="Вилла")),Q4=""),"Этажей",""),IF(AND(OR(OR(C4="Квартира",C4="Апартаменты"),OR(C4="Дом",C4="Вилла")),OR(R4="",R4>YEAR(TODAY()))),"Год постройки",""),IF(AND(P4<>"",Q4<>"",P4>Q4),"Этаж больше этажности",""),IF(AND(OR(C4="Квартира",C4="Апартаменты",C4="Дом",C4="Вилла"),S4=""),"Материал",""),IF(AND(OR(C4="Коммерческая"),U4=""),"Тип коммерции",""),IF(AND(OR(C4="Земля"),V4=""),"Назначение земли",""),IF(OR(W4="",W4<=0),"Продать сейчас",""),IF(OR(X4="",X4<=0),"Минимальная цена продажи",""),IF(OR(Y4="",Y4<=0),"Стартовая ставка",""),IF(Z4="","Начало аукциона",""),IF(AA4="","Окончание аукциона",""),IF(AND(W4<>"",X4<>"",X4>W4),"Минимальная цена выше «Продать сейчас»",""),IF(AND(W4<>"",X4<>"",X4<=W4,X4>W4*0.9),"Минимальная цена выше 90% от «Продать сейчас»",""),IF(AND(W4<>"",Y4<>"",Y4>W4*0.3),"Стартовая ставка выше 30% от «Продать сейчас»",""),IF(AND(Z4<>"",AA4<>"",AA4<EDATE(Z4,3)+15),"Аукцион короче 3 месяцев и 15 дней",""),IF(AND(AB4="Да",OR(AC4="",AC4<=0)),"Цена тест-драйва за сутки",""),IF(OR(AJ4="",AJ4="Нет"),"Право собственности",""),IF(OR(AK4="",AK4="Нет"),"Справка об отсутствии обременений","")))) | AN4: =IF(NOT(COUNTA(A4:AL4)>0),"",IF(TEXTJOIN(", ",TRUE,IF(AH4="","Описание",""),IF(AND(AE4<>"",AE4>=1,AE4<5),"Фото меньше 5",""),IF(AG4="","Видео",""),IF(H4="","Кадастровый номер",""),IF(AF4="","Ссылка на фото",""))="","",TEXTJOIN(", ",TRUE,IF(AH4="","Описание",""),IF(AND(AE4<>"",AE4>=1,AE4<5),"Фото меньше 5",""),IF(AG4="","Видео",""),IF(H4="","Кадастровый номер",""),IF(AF4="","Ссылка на фото","")))) | AO4: =IF(NOT(COUNTA(A4:AL4)>0),"",IF(AM4="","Можно публиковать","Не хватает"))
AM5: =IF(NOT(COUNTA(A5:AL5)>0),"",IF(TEXTJOIN(", ",TRUE,IF(B5="","Название",""),IF(C5="","Тип недвижимости",""),IF(D5="","Страна",""),IF(E5="","Город",""),IF(F5="","Улица",""),IF(I5="","Валюта",""),IF(OR(AE5="",AE5<1),"Хотя бы 1 фото",""),IF(AND(OR(C5="Квартира",C5="Апартаменты",C5="Дом",C5="Вилла",C5="Коммерческая"),J5=""),"Площадь",""),IF(AND(OR(C5="Квартира",C5="Апартаменты"),K5=""),"Жилая площадь",""),IF(AND(OR(C5="Дом",C5="Вилла",C5="Земля"),L5=""),"Площадь участка",""),IF(AND(OR(C5="Квартира",C5="Апартаменты"),M5=""),"Комнаты",""),IF(AND(OR(C5="Дом",C5="Вилла"),N5=""),"Спальни",""),IF(AND(OR(C5="Квартира",C5="Апартаменты",C5="Дом",C5="Вилла"),O5=""),"Ванные",""),IF(AND(OR(C5="Квартира",C5="Апартаменты"),P5=""),"Этаж",""),IF(AND(OR(OR(C5="Квартира",C5="Апартаменты"),OR(C5="Дом",C5="Вилла")),Q5=""),"Этажей",""),IF(AND(OR(OR(C5="Квартира",C5="Апартаменты"),OR(C5="Дом",C5="Вилла")),OR(R5="",R5>YEAR(TODAY()))),"Год постройки",""),IF(AND(P5<>"",Q5<>"",P5>Q5),"Этаж больше этажности",""),IF(AND(OR(C5="Квартира",C5="Апартаменты",C5="Дом",C5="Вилла"),S5=""),"Материал",""),IF(AND(OR(C5="Коммерческая"),U5=""),"Тип коммерции",""),IF(AND(OR(C5="Земля"),V5=""),"Назначение земли",""),IF(OR(W5="",W5<=0),"Продать сейчас",""),IF(OR(X5="",X5<=0),"Минимальная цена продажи",""),IF(OR(Y5="",Y5<=0),"Стартовая ставка",""),IF(Z5="","Начало аукциона",""),IF(AA5="","Окончание аукциона",""),IF(AND(W5<>"",X5<>"",X5>W5),"Минимальная цена выше «Продать сейчас»",""),IF(AND(W5<>"",X5<>"",X5<=W5,X5>W5*0.9),"Минимальная цена выше 90% от «Продать сейчас»",""),IF(AND(W5<>"",Y5<>"",Y5>W5*0.3),"Стартовая ставка выше 30% от «Продать сейчас»",""),IF(AND(Z5<>"",AA5<>"",AA5<EDATE(Z5,3)+15),"Аукцион короче 3 месяцев и 15 дней",""),IF(AND(AB5="Да",OR(AC5="",AC5<=0)),"Цена тест-драйва за сутки",""),IF(OR(AJ5="",AJ5="Нет"),"Право собственности",""),IF(OR(AK5="",AK5="Нет"),"Справка об отсутствии обременений",""))="","",TEXTJOIN(", ",TRUE,IF(B5="","Название",""),IF(C5="","Тип недвижимости",""),IF(D5="","Страна",""),IF(E5="","Город",""),IF(F5="","Улица",""),IF(I5="","Валюта",""),IF(OR(AE5="",AE5<1),"Хотя бы 1 фото",""),IF(AND(OR(C5="Квартира",C5="Апартаменты",C5="Дом",C5="Вилла",C5="Коммерческая"),J5=""),"Площадь",""),IF(AND(OR(C5="Квартира",C5="Апартаменты"),K5=""),"Жилая площадь",""),IF(AND(OR(C5="Дом",C5="Вилла",C5="Земля"),L5=""),"Площадь участка",""),IF(AND(OR(C5="Квартира",C5="Апартаменты"),M5=""),"Комнаты",""),IF(AND(OR(C5="Дом",C5="Вилла"),N5=""),"Спальни",""),IF(AND(OR(C5="Квартира",C5="Апартаменты",C5="Дом",C5="Вилла"),O5=""),"Ванные",""),IF(AND(OR(C5="Квартира",C5="Апартаменты"),P5=""),"Этаж",""),IF(AND(OR(OR(C5="Квартира",C5="Апартаменты"),OR(C5="Дом",C5="Вилла")),Q5=""),"Этажей",""),IF(AND(OR(OR(C5="Квартира",C5="Апартаменты"),OR(C5="Дом",C5="Вилла")),OR(R5="",R5>YEAR(TODAY()))),"Год постройки",""),IF(AND(P5<>"",Q5<>"",P5>Q5),"Этаж больше этажности",""),IF(AND(OR(C5="Квартира",C5="Апартаменты",C5="Дом",C5="Вилла"),S5=""),"Материал",""),IF(AND(OR(C5="Коммерческая"),U5=""),"Тип коммерции",""),IF(AND(OR(C5="Земля"),V5=""),"Назначение земли",""),IF(OR(W5="",W5<=0),"Продать сейчас",""),IF(OR(X5="",X5<=0),"Минимальная цена продажи",""),IF(OR(Y5="",Y5<=0),"Стартовая ставка",""),IF(Z5="","Начало аукциона",""),IF(AA5="","Окончание аукциона",""),IF(AND(W5<>"",X5<>"",X5>W5),"Минимальная цена выше «Продать сейчас»",""),IF(AND(W5<>"",X5<>"",X5<=W5,X5>W5*0.9),"Минимальная цена выше 90% от «Продать сейчас»",""),IF(AND(W5<>"",Y5<>"",Y5>W5*0.3),"Стартовая ставка выше 30% от «Продать сейчас»",""),IF(AND(Z5<>"",AA5<>"",AA5<EDATE(Z5,3)+15),"Аукцион короче 3 месяцев и 15 дней",""),IF(AND(AB5="Да",OR(AC5="",AC5<=0)),"Цена тест-драйва за сутки",""),IF(OR(AJ5="",AJ5="Нет"),"Право собственности",""),IF(OR(AK5="",AK5="Нет"),"Справка об отсутствии обременений","")))) | AN5: =IF(NOT(COUNTA(A5:AL5)>0),"",IF(TEXTJOIN(", ",TRUE,IF(AH5="","Описание",""),IF(AND(AE5<>"",AE5>=1,AE5<5),"Фото меньше 5",""),IF(AG5="","Видео",""),IF(H5="","Кадастровый номер",""),IF(AF5="","Ссылка на фото",""))="","",TEXTJOIN(", ",TRUE,IF(AH5="","Описание",""),IF(AND(AE5<>"",AE5>=1,AE5<5),"Фото меньше 5",""),IF(AG5="","Видео",""),IF(H5="","Кадастровый номер",""),IF(AF5="","Ссылка на фото","")))) | AO5: =IF(NOT(COUNTA(A5:AL5)>0),"",IF(AM5="","Можно публиковать","Не хватает"))
AM6: =IF(NOT(COUNTA(A6:AL6)>0),"",IF(TEXTJOIN(", ",TRUE,IF(B6="","Название",""),IF(C6="","Тип недвижимости",""),IF(D6="","Страна",""),IF(E6="","Город",""),IF(F6="","Улица",""),IF(I6="","Валюта",""),IF(OR(AE6="",AE6<1),"Хотя бы 1 фото",""),IF(AND(OR(C6="Квартира",C6="Апартаменты",C6="Дом",C6="Вилла",C6="Коммерческая"),J6=""),"Площадь",""),IF(AND(OR(C6="Квартира",C6="Апартаменты"),K6=""),"Жилая площадь",""),IF(AND(OR(C6="Дом",C6="Вилла",C6="Земля"),L6=""),"Площадь участка",""),IF(AND(OR(C6="Квартира",C6="Апартаменты"),M6=""),"Комнаты",""),IF(AND(OR(C6="Дом",C6="Вилла"),N6=""),"Спальни",""),IF(AND(OR(C6="Квартира",C6="Апартаменты",C6="Дом",C6="Вилла"),O6=""),"Ванные",""),IF(AND(OR(C6="Квартира",C6="Апартаменты"),P6=""),"Этаж",""),IF(AND(OR(OR(C6="Квартира",C6="Апартаменты"),OR(C6="Дом",C6="Вилла")),Q6=""),"Этажей",""),IF(AND(OR(OR(C6="Квартира",C6="Апартаменты"),OR(C6="Дом",C6="Вилла")),OR(R6="",R6>YEAR(TODAY()))),"Год постройки",""),IF(AND(P6<>"",Q6<>"",P6>Q6),"Этаж больше этажности",""),IF(AND(OR(C6="Квартира",C6="Апартаменты",C6="Дом",C6="Вилла"),S6=""),"Материал",""),IF(AND(OR(C6="Коммерческая"),U6=""),"Тип коммерции",""),IF(AND(OR(C6="Земля"),V6=""),"Назначение земли",""),IF(OR(W6="",W6<=0),"Продать сейчас",""),IF(OR(X6="",X6<=0),"Минимальная цена продажи",""),IF(OR(Y6="",Y6<=0),"Стартовая ставка",""),IF(Z6="","Начало аукциона",""),IF(AA6="","Окончание аукциона",""),IF(AND(W6<>"",X6<>"",X6>W6),"Минимальная цена выше «Продать сейчас»",""),IF(AND(W6<>"",X6<>"",X6<=W6,X6>W6*0.9),"Минимальная цена выше 90% от «Продать сейчас»",""),IF(AND(W6<>"",Y6<>"",Y6>W6*0.3),"Стартовая ставка выше 30% от «Продать сейчас»",""),IF(AND(Z6<>"",AA6<>"",AA6<EDATE(Z6,3)+15),"Аукцион короче 3 месяцев и 15 дней",""),IF(AND(AB6="Да",OR(AC6="",AC6<=0)),"Цена тест-драйва за сутки",""),IF(OR(AJ6="",AJ6="Нет"),"Право собственности",""),IF(OR(AK6="",AK6="Нет"),"Справка об отсутствии обременений",""))="","",TEXTJOIN(", ",TRUE,IF(B6="","Название",""),IF(C6="","Тип недвижимости",""),IF(D6="","Страна",""),IF(E6="","Город",""),IF(F6="","Улица",""),IF(I6="","Валюта",""),IF(OR(AE6="",AE6<1),"Хотя бы 1 фото",""),IF(AND(OR(C6="Квартира",C6="Апартаменты",C6="Дом",C6="Вилла",C6="Коммерческая"),J6=""),"Площадь",""),IF(AND(OR(C6="Квартира",C6="Апартаменты"),K6=""),"Жилая площадь",""),IF(AND(OR(C6="Дом",C6="Вилла",C6="Земля"),L6=""),"Площадь участка",""),IF(AND(OR(C6="Квартира",C6="Апартаменты"),M6=""),"Комнаты",""),IF(AND(OR(C6="Дом",C6="Вилла"),N6=""),"Спальни",""),IF(AND(OR(C6="Квартира",C6="Апартаменты",C6="Дом",C6="Вилла"),O6=""),"Ванные",""),IF(AND(OR(C6="Квартира",C6="Апартаменты"),P6=""),"Этаж",""),IF(AND(OR(OR(C6="Квартира",C6="Апартаменты"),OR(C6="Дом",C6="Вилла")),Q6=""),"Этажей",""),IF(AND(OR(OR(C6="Квартира",C6="Апартаменты"),OR(C6="Дом",C6="Вилла")),OR(R6="",R6>YEAR(TODAY()))),"Год постройки",""),IF(AND(P6<>"",Q6<>"",P6>Q6),"Этаж больше этажности",""),IF(AND(OR(C6="Квартира",C6="Апартаменты",C6="Дом",C6="Вилла"),S6=""),"Материал",""),IF(AND(OR(C6="Коммерческая"),U6=""),"Тип коммерции",""),IF(AND(OR(C6="Земля"),V6=""),"Назначение земли",""),IF(OR(W6="",W6<=0),"Продать сейчас",""),IF(OR(X6="",X6<=0),"Минимальная цена продажи",""),IF(OR(Y6="",Y6<=0),"Стартовая ставка",""),IF(Z6="","Начало аукциона",""),IF(AA6="","Окончание аукциона",""),IF(AND(W6<>"",X6<>"",X6>W6),"Минимальная цена выше «Продать сейчас»",""),IF(AND(W6<>"",X6<>"",X6<=W6,X6>W6*0.9),"Минимальная цена выше 90% от «Продать сейчас»",""),IF(AND(W6<>"",Y6<>"",Y6>W6*0.3),"Стартовая ставка выше 30% от «Продать сейчас»",""),IF(AND(Z6<>"",AA6<>"",AA6<EDATE(Z6,3)+15),"Аукцион короче 3 месяцев и 15 дней",""),IF(AND(AB6="Да",OR(AC6="",AC6<=0)),"Цена тест-драйва за сутки",""),IF(OR(AJ6="",AJ6="Нет"),"Право собственности",""),IF(OR(AK6="",AK6="Нет"),"Справка об отсутствии обременений","")))) | AN6: =IF(NOT(COUNTA(A6:AL6)>0),"",IF(TEXTJOIN(", ",TRUE,IF(AH6="","Описание",""),IF(AND(AE6<>"",AE6>=1,AE6<5),"Фото меньше 5",""),IF(AG6="","Видео",""),IF(H6="","Кадастровый номер",""),IF(AF6="","Ссылка на фото",""))="","",TEXTJOIN(", ",TRUE,IF(AH6="","Описание",""),IF(AND(AE6<>"",AE6>=1,AE6<5),"Фото меньше 5",""),IF(AG6="","Видео",""),IF(H6="","Кадастровый номер",""),IF(AF6="","Ссылка на фото","")))) | AO6: =IF(NOT(COUNTA(A6:AL6)>0),"",IF(AM6="","Можно публиковать","Не хватает"))
AM7: =IF(NOT(COUNTA(A7:AL7)>0),"",IF(TEXTJOIN(", ",TRUE,IF(B7="","Название",""),IF(C7="","Тип недвижимости",""),IF(D7="","Страна",""),IF(E7="","Город",""),IF(F7="","Улица",""),IF(I7="","Валюта",""),IF(OR(AE7="",AE7<1),"Хотя бы 1 фото",""),IF(AND(OR(C7="Квартира",C7="Апартаменты",C7="Дом",C7="Вилла",C7="Коммерческая"),J7=""),"Площадь",""),IF(AND(OR(C7="Квартира",C7="Апартаменты"),K7=""),"Жилая площадь",""),IF(AND(OR(C7="Дом",C7="Вилла",C7="Земля"),L7=""),"Площадь участка",""),IF(AND(OR(C7="Квартира",C7="Апартаменты"),M7=""),"Комнаты",""),IF(AND(OR(C7="Дом",C7="Вилла"),N7=""),"Спальни",""),IF(AND(OR(C7="Квартира",C7="Апартаменты",C7="Дом",C7="Вилла"),O7=""),"Ванные",""),IF(AND(OR(C7="Квартира",C7="Апартаменты"),P7=""),"Этаж",""),IF(AND(OR(OR(C7="Квартира",C7="Апартаменты"),OR(C7="Дом",C7="Вилла")),Q7=""),"Этажей",""),IF(AND(OR(OR(C7="Квартира",C7="Апартаменты"),OR(C7="Дом",C7="Вилла")),OR(R7="",R7>YEAR(TODAY()))),"Год постройки",""),IF(AND(P7<>"",Q7<>"",P7>Q7),"Этаж больше этажности",""),IF(AND(OR(C7="Квартира",C7="Апартаменты",C7="Дом",C7="Вилла"),S7=""),"Материал",""),IF(AND(OR(C7="Коммерческая"),U7=""),"Тип коммерции",""),IF(AND(OR(C7="Земля"),V7=""),"Назначение земли",""),IF(OR(W7="",W7<=0),"Продать сейчас",""),IF(OR(X7="",X7<=0),"Минимальная цена продажи",""),IF(OR(Y7="",Y7<=0),"Стартовая ставка",""),IF(Z7="","Начало аукциона",""),IF(AA7="","Окончание аукциона",""),IF(AND(W7<>"",X7<>"",X7>W7),"Минимальная цена выше «Продать сейчас»",""),IF(AND(W7<>"",X7<>"",X7<=W7,X7>W7*0.9),"Минимальная цена выше 90% от «Продать сейчас»",""),IF(AND(W7<>"",Y7<>"",Y7>W7*0.3),"Стартовая ставка выше 30% от «Продать сейчас»",""),IF(AND(Z7<>"",AA7<>"",AA7<EDATE(Z7,3)+15),"Аукцион короче 3 месяцев и 15 дней",""),IF(AND(AB7="Да",OR(AC7="",AC7<=0)),"Цена тест-драйва за сутки",""),IF(OR(AJ7="",AJ7="Нет"),"Право собственности",""),IF(OR(AK7="",AK7="Нет"),"Справка об отсутствии обременений",""))="","",TEXTJOIN(", ",TRUE,IF(B7="","Название",""),IF(C7="","Тип недвижимости",""),IF(D7="","Страна",""),IF(E7="","Город",""),IF(F7="","Улица",""),IF(I7="","Валюта",""),IF(OR(AE7="",AE7<1),"Хотя бы 1 фото",""),IF(AND(OR(C7="Квартира",C7="Апартаменты",C7="Дом",C7="Вилла",C7="Коммерческая"),J7=""),"Площадь",""),IF(AND(OR(C7="Квартира",C7="Апартаменты"),K7=""),"Жилая площадь",""),IF(AND(OR(C7="Дом",C7="Вилла",C7="Земля"),L7=""),"Площадь участка",""),IF(AND(OR(C7="Квартира",C7="Апартаменты"),M7=""),"Комнаты",""),IF(AND(OR(C7="Дом",C7="Вилла"),N7=""),"Спальни",""),IF(AND(OR(C7="Квартира",C7="Апартаменты",C7="Дом",C7="Вилла"),O7=""),"Ванные",""),IF(AND(OR(C7="Квартира",C7="Апартаменты"),P7=""),"Этаж",""),IF(AND(OR(OR(C7="Квартира",C7="Апартаменты"),OR(C7="Дом",C7="Вилла")),Q7=""),"Этажей",""),IF(AND(OR(OR(C7="Квартира",C7="Апартаменты"),OR(C7="Дом",C7="Вилла")),OR(R7="",R7>YEAR(TODAY()))),"Год постройки",""),IF(AND(P7<>"",Q7<>"",P7>Q7),"Этаж больше этажности",""),IF(AND(OR(C7="Квартира",C7="Апартаменты",C7="Дом",C7="Вилла"),S7=""),"Материал",""),IF(AND(OR(C7="Коммерческая"),U7=""),"Тип коммерции",""),IF(AND(OR(C7="Земля"),V7=""),"Назначение земли",""),IF(OR(W7="",W7<=0),"Продать сейчас",""),IF(OR(X7="",X7<=0),"Минимальная цена продажи",""),IF(OR(Y7="",Y7<=0),"Стартовая ставка",""),IF(Z7="","Начало аукциона",""),IF(AA7="","Окончание аукциона",""),IF(AND(W7<>"",X7<>"",X7>W7),"Минимальная цена выше «Продать сейчас»",""),IF(AND(W7<>"",X7<>"",X7<=W7,X7>W7*0.9),"Минимальная цена выше 90% от «Продать сейчас»",""),IF(AND(W7<>"",Y7<>"",Y7>W7*0.3),"Стартовая ставка выше 30% от «Продать сейчас»",""),IF(AND(Z7<>"",AA7<>"",AA7<EDATE(Z7,3)+15),"Аукцион короче 3 месяцев и 15 дней",""),IF(AND(AB7="Да",OR(AC7="",AC7<=0)),"Цена тест-драйва за сутки",""),IF(OR(AJ7="",AJ7="Нет"),"Право собственности",""),IF(OR(AK7="",AK7="Нет"),"Справка об отсутствии обременений","")))) | AN7: =IF(NOT(COUNTA(A7:AL7)>0),"",IF(TEXTJOIN(", ",TRUE,IF(AH7="","Описание",""),IF(AND(AE7<>"",AE7>=1,AE7<5),"Фото меньше 5",""),IF(AG7="","Видео",""),IF(H7="","Кадастровый номер",""),IF(AF7="","Ссылка на фото",""))="","",TEXTJOIN(", ",TRUE,IF(AH7="","Описание",""),IF(AND(AE7<>"",AE7>=1,AE7<5),"Фото меньше 5",""),IF(AG7="","Видео",""),IF(H7="","Кадастровый номер",""),IF(AF7="","Ссылка на фото","")))) | AO7: =IF(NOT(COUNTA(A7:AL7)>0),"",IF(AM7="","Можно публиковать","Не хватает"))
AM8: =IF(NOT(COUNTA(A8:AL8)>0),"",IF(TEXTJOIN(", ",TRUE,IF(B8="","Название",""),IF(C8="","Тип недвижимости",""),IF(D8="","Страна",""),IF(E8="","Город",""),IF(F8="","Улица",""),IF(I8="","Валюта",""),IF(OR(AE8="",AE8<1),"Хотя бы 1 фото",""),IF(AND(OR(C8="Квартира",C8="Апартаменты",C8="Дом",C8="Вилла",C8="Коммерческая"),J8=""),"Площадь",""),IF(AND(OR(C8="Квартира",C8="Апартаменты"),K8=""),"Жилая площадь",""),IF(AND(OR(C8="Дом",C8="Вилла",C8="Земля"),L8=""),"Площадь участка",""),IF(AND(OR(C8="Квартира",C8="Апартаменты"),M8=""),"Комнаты",""),IF(AND(OR(C8="Дом",C8="Вилла"),N8=""),"Спальни",""),IF(AND(OR(C8="Квартира",C8="Апартаменты",C8="Дом",C8="Вилла"),O8=""),"Ванные",""),IF(AND(OR(C8="Квартира",C8="Апартаменты"),P8=""),"Этаж",""),IF(AND(OR(OR(C8="Квартира",C8="Апартаменты"),OR(C8="Дом",C8="Вилла")),Q8=""),"Этажей",""),IF(AND(OR(OR(C8="Квартира",C8="Апартаменты"),OR(C8="Дом",C8="Вилла")),OR(R8="",R8>YEAR(TODAY()))),"Год постройки",""),IF(AND(P8<>"",Q8<>"",P8>Q8),"Этаж больше этажности",""),IF(AND(OR(C8="Квартира",C8="Апартаменты",C8="Дом",C8="Вилла"),S8=""),"Материал",""),IF(AND(OR(C8="Коммерческая"),U8=""),"Тип коммерции",""),IF(AND(OR(C8="Земля"),V8=""),"Назначение земли",""),IF(OR(W8="",W8<=0),"Продать сейчас",""),IF(OR(X8="",X8<=0),"Минимальная цена продажи",""),IF(OR(Y8="",Y8<=0),"Стартовая ставка",""),IF(Z8="","Начало аукциона",""),IF(AA8="","Окончание аукциона",""),IF(AND(W8<>"",X8<>"",X8>W8),"Минимальная цена выше «Продать сейчас»",""),IF(AND(W8<>"",X8<>"",X8<=W8,X8>W8*0.9),"Минимальная цена выше 90% от «Продать сейчас»",""),IF(AND(W8<>"",Y8<>"",Y8>W8*0.3),"Стартовая ставка выше 30% от «Продать сейчас»",""),IF(AND(Z8<>"",AA8<>"",AA8<EDATE(Z8,3)+15),"Аукцион короче 3 месяцев и 15 дней",""),IF(AND(AB8="Да",OR(AC8="",AC8<=0)),"Цена тест-драйва за сутки",""),IF(OR(AJ8="",AJ8="Нет"),"Право собственности",""),IF(OR(AK8="",AK8="Нет"),"Справка об отсутствии обременений",""))="","",TEXTJOIN(", ",TRUE,IF(B8="","Название",""),IF(C8="","Тип недвижимости",""),IF(D8="","Страна",""),IF(E8="","Город",""),IF(F8="","Улица",""),IF(I8="","Валюта",""),IF(OR(AE8="",AE8<1),"Хотя бы 1 фото",""),IF(AND(OR(C8="Квартира",C8="Апартаменты",C8="Дом",C8="Вилла",C8="Коммерческая"),J8=""),"Площадь",""),IF(AND(OR(C8="Квартира",C8="Апартаменты"),K8=""),"Жилая площадь",""),IF(AND(OR(C8="Дом",C8="Вилла",C8="Земля"),L8=""),"Площадь участка",""),IF(AND(OR(C8="Квартира",C8="Апартаменты"),M8=""),"Комнаты",""),IF(AND(OR(C8="Дом",C8="Вилла"),N8=""),"Спальни",""),IF(AND(OR(C8="Квартира",C8="Апартаменты",C8="Дом",C8="Вилла"),O8=""),"Ванные",""),IF(AND(OR(C8="Квартира",C8="Апартаменты"),P8=""),"Этаж",""),IF(AND(OR(OR(C8="Квартира",C8="Апартаменты"),OR(C8="Дом",C8="Вилла")),Q8=""),"Этажей",""),IF(AND(OR(OR(C8="Квартира",C8="Апартаменты"),OR(C8="Дом",C8="Вилла")),OR(R8="",R8>YEAR(TODAY()))),"Год постройки",""),IF(AND(P8<>"",Q8<>"",P8>Q8),"Этаж больше этажности",""),IF(AND(OR(C8="Квартира",C8="Апартаменты",C8="Дом",C8="Вилла"),S8=""),"Материал",""),IF(AND(OR(C8="Коммерческая"),U8=""),"Тип коммерции",""),IF(AND(OR(C8="Земля"),V8=""),"Назначение земли",""),IF(OR(W8="",W8<=0),"Продать сейчас",""),IF(OR(X8="",X8<=0),"Минимальная цена продажи",""),IF(OR(Y8="",Y8<=0),"Стартовая ставка",""),IF(Z8="","Начало аукциона",""),IF(AA8="","Окончание аукциона",""),IF(AND(W8<>"",X8<>"",X8>W8),"Минимальная цена выше «Продать сейчас»",""),IF(AND(W8<>"",X8<>"",X8<=W8,X8>W8*0.9),"Минимальная цена выше 90% от «Продать сейчас»",""),IF(AND(W8<>"",Y8<>"",Y8>W8*0.3),"Стартовая ставка выше 30% от «Продать сейчас»",""),IF(AND(Z8<>"",AA8<>"",AA8<EDATE(Z8,3)+15),"Аукцион короче 3 месяцев и 15 дней",""),IF(AND(AB8="Да",OR(AC8="",AC8<=0)),"Цена тест-драйва за сутки",""),IF(OR(AJ8="",AJ8="Нет"),"Право собственности",""),IF(OR(AK8="",AK8="Нет"),"Справка об отсутствии обременений","")))) | AN8: =IF(NOT(COUNTA(A8:AL8)>0),"",IF(TEXTJOIN(", ",TRUE,IF(AH8="","Описание",""),IF(AND(AE8<>"",AE8>=1,AE8<5),"Фото меньше 5",""),IF(AG8="","Видео",""),IF(H8="","Кадастровый номер",""),IF(AF8="","Ссылка на фото",""))="","",TEXTJOIN(", ",TRUE,IF(AH8="","Описание",""),IF(AND(AE8<>"",AE8>=1,AE8<5),"Фото меньше 5",""),IF(AG8="","Видео",""),IF(H8="","Кадастровый номер",""),IF(AF8="","Ссылка на фото","")))) | AO8: =IF(NOT(COUNTA(A8:AL8)>0),"",IF(AM8="","Можно публиковать","Не хватает"))
AM9: =IF(NOT(COUNTA(A9:AL9)>0),"",IF(TEXTJOIN(", ",TRUE,IF(B9="","Название",""),IF(C9="","Тип недвижимости",""),IF(D9="","Страна",""),IF(E9="","Город",""),IF(F9="","Улица",""),IF(I9="","Валюта",""),IF(OR(AE9="",AE9<1),"Хотя бы 1 фото",""),IF(AND(OR(C9="Квартира",C9="Апартаменты",C9="Дом",C9="Вилла",C9="Коммерческая"),J9=""),"Площадь",""),IF(AND(OR(C9="Квартира",C9="Апартаменты"),K9=""),"Жилая площадь",""),IF(AND(OR(C9="Дом",C9="Вилла",C9="Земля"),L9=""),"Площадь участка",""),IF(AND(OR(C9="Квартира",C9="Апартаменты"),M9=""),"Комнаты",""),IF(AND(OR(C9="Дом",C9="Вилла"),N9=""),"Спальни",""),IF(AND(OR(C9="Квартира",C9="Апартаменты",C9="Дом",C9="Вилла"),O9=""),"Ванные",""),IF(AND(OR(C9="Квартира",C9="Апартаменты"),P9=""),"Этаж",""),IF(AND(OR(OR(C9="Квартира",C9="Апартаменты"),OR(C9="Дом",C9="Вилла")),Q9=""),"Этажей",""),IF(AND(OR(OR(C9="Квартира",C9="Апартаменты"),OR(C9="Дом",C9="Вилла")),OR(R9="",R9>YEAR(TODAY()))),"Год постройки",""),IF(AND(P9<>"",Q9<>"",P9>Q9),"Этаж больше этажности",""),IF(AND(OR(C9="Квартира",C9="Апартаменты",C9="Дом",C9="Вилла"),S9=""),"Материал",""),IF(AND(OR(C9="Коммерческая"),U9=""),"Тип коммерции",""),IF(AND(OR(C9="Земля"),V9=""),"Назначение земли",""),IF(OR(W9="",W9<=0),"Продать сейчас",""),IF(OR(X9="",X9<=0),"Минимальная цена продажи",""),IF(OR(Y9="",Y9<=0),"Стартовая ставка",""),IF(Z9="","Начало аукциона",""),IF(AA9="","Окончание аукциона",""),IF(AND(W9<>"",X9<>"",X9>W9),"Минимальная цена выше «Продать сейчас»",""),IF(AND(W9<>"",X9<>"",X9<=W9,X9>W9*0.9),"Минимальная цена выше 90% от «Продать сейчас»",""),IF(AND(W9<>"",Y9<>"",Y9>W9*0.3),"Стартовая ставка выше 30% от «Продать сейчас»",""),IF(AND(Z9<>"",AA9<>"",AA9<EDATE(Z9,3)+15),"Аукцион короче 3 месяцев и 15 дней",""),IF(AND(AB9="Да",OR(AC9="",AC9<=0)),"Цена тест-драйва за сутки",""),IF(OR(AJ9="",AJ9="Нет"),"Право собственности",""),IF(OR(AK9="",AK9="Нет"),"Справка об отсутствии обременений",""))="","",TEXTJOIN(", ",TRUE,IF(B9="","Название",""),IF(C9="","Тип недвижимости",""),IF(D9="","Страна",""),IF(E9="","Город",""),IF(F9="","Улица",""),IF(I9="","Валюта",""),IF(OR(AE9="",AE9<1),"Хотя бы 1 фото",""),IF(AND(OR(C9="Квартира",C9="Апартаменты",C9="Дом",C9="Вилла",C9="Коммерческая"),J9=""),"Площадь",""),IF(AND(OR(C9="Квартира",C9="Апартаменты"),K9=""),"Жилая площадь",""),IF(AND(OR(C9="Дом",C9="Вилла",C9="Земля"),L9=""),"Площадь участка",""),IF(AND(OR(C9="Квартира",C9="Апартаменты"),M9=""),"Комнаты",""),IF(AND(OR(C9="Дом",C9="Вилла"),N9=""),"Спальни",""),IF(AND(OR(C9="Квартира",C9="Апартаменты",C9="Дом",C9="Вилла"),O9=""),"Ванные",""),IF(AND(OR(C9="Квартира",C9="Апартаменты"),P9=""),"Этаж",""),IF(AND(OR(OR(C9="Квартира",C9="Апартаменты"),OR(C9="Дом",C9="Вилла")),Q9=""),"Этажей",""),IF(AND(OR(OR(C9="Квартира",C9="Апартаменты"),OR(C9="Дом",C9="Вилла")),OR(R9="",R9>YEAR(TODAY()))),"Год постройки",""),IF(AND(P9<>"",Q9<>"",P9>Q9),"Этаж больше этажности",""),IF(AND(OR(C9="Квартира",C9="Апартаменты",C9="Дом",C9="Вилла"),S9=""),"Материал",""),IF(AND(OR(C9="Коммерческая"),U9=""),"Тип коммерции",""),IF(AND(OR(C9="Земля"),V9=""),"Назначение земли",""),IF(OR(W9="",W9<=0),"Продать сейчас",""),IF(OR(X9="",X9<=0),"Минимальная цена продажи",""),IF(OR(Y9="",Y9<=0),"Стартовая ставка",""),IF(Z9="","Начало аукциона",""),IF(AA9="","Окончание аукциона",""),IF(AND(W9<>"",X9<>"",X9>W9),"Минимальная цена выше «Продать сейчас»",""),IF(AND(W9<>"",X9<>"",X9<=W9,X9>W9*0.9),"Минимальная цена выше 90% от «Продать сейчас»",""),IF(AND(W9<>"",Y9<>"",Y9>W9*0.3),"Стартовая ставка выше 30% от «Продать сейчас»",""),IF(AND(Z9<>"",AA9<>"",AA9<EDATE(Z9,3)+15),"Аукцион короче 3 месяцев и 15 дней",""),IF(AND(AB9="Да",OR(AC9="",AC9<=0)),"Цена тест-драйва за сутки",""),IF(OR(AJ9="",AJ9="Нет"),"Право собственности",""),IF(OR(AK9="",AK9="Нет"),"Справка об отсутствии обременений","")))) | AN9: =IF(NOT(COUNTA(A9:AL9)>0),"",IF(TEXTJOIN(", ",TRUE,IF(AH9="","Описание",""),IF(AND(AE9<>"",AE9>=1,AE9<5),"Фото меньше 5",""),IF(AG9="","Видео",""),IF(H9="","Кадастровый номер",""),IF(AF9="","Ссылка на фото",""))="","",TEXTJOIN(", ",TRUE,IF(AH9="","Описание",""),IF(AND(AE9<>"",AE9>=1,AE9<5),"Фото меньше 5",""),IF(AG9="","Видео",""),IF(H9="","Кадастровый номер",""),IF(AF9="","Ссылка на фото","")))) | AO9: =IF(NOT(COUNTA(A9:AL9)>0),"",IF(AM9="","Можно публиковать","Не хватает"))
AM10: =IF(NOT(COUNTA(A10:AL10)>0),"",IF(TEXTJOIN(", ",TRUE,IF(B10="","Название",""),IF(C10="","Тип недвижимости",""),IF(D10="","Страна",""),IF(E10="","Город",""),IF(F10="","Улица",""),IF(I10="","Валюта",""),IF(OR(AE10="",AE10<1),"Хотя бы 1 фото",""),IF(AND(OR(C10="Квартира",C10="Апартаменты",C10="Дом",C10="Вилла",C10="Коммерческая"),J10=""),"Площадь",""),IF(AND(OR(C10="Квартира",C10="Апартаменты"),K10=""),"Жилая площадь",""),IF(AND(OR(C10="Дом",C10="Вилла",C10="Земля"),L10=""),"Площадь участка",""),IF(AND(OR(C10="Квартира",C10="Апартаменты"),M10=""),"Комнаты",""),IF(AND(OR(C10="Дом",C10="Вилла"),N10=""),"Спальни",""),IF(AND(OR(C10="Квартира",C10="Апартаменты",C10="Дом",C10="Вилла"),O10=""),"Ванные",""),IF(AND(OR(C10="Квартира",C10="Апартаменты"),P10=""),"Этаж",""),IF(AND(OR(OR(C10="Квартира",C10="Апартаменты"),OR(C10="Дом",C10="Вилла")),Q10=""),"Этажей",""),IF(AND(OR(OR(C10="Квартира",C10="Апартаменты"),OR(C10="Дом",C10="Вилла")),OR(R10="",R10>YEAR(TODAY()))),"Год постройки",""),IF(AND(P10<>"",Q10<>"",P10>Q10),"Этаж больше этажности",""),IF(AND(OR(C10="Квартира",C10="Апартаменты",C10="Дом",C10="Вилла"),S10=""),"Материал",""),IF(AND(OR(C10="Коммерческая"),U10=""),"Тип коммерции",""),IF(AND(OR(C10="Земля"),V10=""),"Назначение земли",""),IF(OR(W10="",W10<=0),"Продать сейчас",""),IF(OR(X10="",X10<=0),"Минимальная цена продажи",""),IF(OR(Y10="",Y10<=0),"Стартовая ставка",""),IF(Z10="","Начало аукциона",""),IF(AA10="","Окончание аукциона",""),IF(AND(W10<>"",X10<>"",X10>W10),"Минимальная цена выше «Продать сейчас»",""),IF(AND(W10<>"",X10<>"",X10<=W10,X10>W10*0.9),"Минимальная цена выше 90% от «Продать сейчас»",""),IF(AND(W10<>"",Y10<>"",Y10>W10*0.3),"Стартовая ставка выше 30% от «Продать сейчас»",""),IF(AND(Z10<>"",AA10<>"",AA10<EDATE(Z10,3)+15),"Аукцион короче 3 месяцев и 15 дней",""),IF(AND(AB10="Да",OR(AC10="",AC10<=0)),"Цена тест-драйва за сутки",""),IF(OR(AJ10="",AJ10="Нет"),"Право собственности",""),IF(OR(AK10="",AK10="Нет"),"Справка об отсутствии обременений",""))="","",TEXTJOIN(", ",TRUE,IF(B10="","Название",""),IF(C10="","Тип недвижимости",""),IF(D10="","Страна",""),IF(E10="","Город",""),IF(F10="","Улица",""),IF(I10="","Валюта",""),IF(OR(AE10="",AE10<1),"Хотя бы 1 фото",""),IF(AND(OR(C10="Квартира",C10="Апартаменты",C10="Дом",C10="Вилла",C10="Коммерческая"),J10=""),"Площадь",""),IF(AND(OR(C10="Квартира",C10="Апартаменты"),K10=""),"Жилая площадь",""),IF(AND(OR(C10="Дом",C10="Вилла",C10="Земля"),L10=""),"Площадь участка",""),IF(AND(OR(C10="Квартира",C10="Апартаменты"),M10=""),"Комнаты",""),IF(AND(OR(C10="Дом",C10="Вилла"),N10=""),"Спальни",""),IF(AND(OR(C10="Квартира",C10="Апартаменты",C10="Дом",C10="Вилла"),O10=""),"Ванные",""),IF(AND(OR(C10="Квартира",C10="Апартаменты"),P10=""),"Этаж",""),IF(AND(OR(OR(C10="Квартира",C10="Апартаменты"),OR(C10="Дом",C10="Вилла")),Q10=""),"Этажей",""),IF(AND(OR(OR(C10="Квартира",C10="Апартаменты"),OR(C10="Дом",C10="Вилла")),OR(R10="",R10>YEAR(TODAY()))),"Год постройки",""),IF(AND(P10<>"",Q10<>"",P10>Q10),"Этаж больше этажности",""),IF(AND(OR(C10="Квартира",C10="Апартаменты",C10="Дом",C10="Вилла"),S10=""),"Материал",""),IF(AND(OR(C10="Коммерческая"),U10=""),"Тип коммерции",""),IF(AND(OR(C10="Земля"),V10=""),"Назначение земли",""),IF(OR(W10="",W10<=0),"Продать сейчас",""),IF(OR(X10="",X10<=0),"Минимальная цена продажи",""),IF(OR(Y10="",Y10<=0),"Стартовая ставка",""),IF(Z10="","Начало аукциона",""),IF(AA10="","Окончание аукциона",""),IF(AND(W10<>"",X10<>"",X10>W10),"Минимальная цена выше «Продать сейчас»",""),IF(AND(W10<>"",X10<>"",X10<=W10,X10>W10*0.9),"Минимальная цена выше 90% от «Продать сейчас»",""),IF(AND(W10<>"",Y10<>"",Y10>W10*0.3),"Стартовая ставка выше 30% от «Продать сейчас»",""),IF(AND(Z10<>"",AA10<>"",AA10<EDATE(Z10,3)+15),"Аукцион короче 3 месяцев и 15 дней",""),IF(AND(AB10="Да",OR(AC10="",AC10<=0)),"Цена тест-драйва за сутки",""),IF(OR(AJ10="",AJ10="Нет"),"Право собственности",""),IF(OR(AK10="",AK10="Нет"),"Справка об отсутствии обременений","")))) | AN10: =IF(NOT(COUNTA(A10:AL10)>0),"",IF(TEXTJOIN(", ",TRUE,IF(AH10="","Описание",""),IF(AND(AE10<>"",AE10>=1,AE10<5),"Фото меньше 5",""),IF(AG10="","Видео",""),IF(H10="","Кадастровый номер",""),IF(AF10="","Ссылка на фото",""))="","",TEXTJOIN(", ",TRUE,IF(AH10="","Описание",""),IF(AND(AE10<>"",AE10>=1,AE10<5),"Фото меньше 5",""),IF(AG10="","Видео",""),IF(H10="","Кадастровый номер",""),IF(AF10="","Ссылка на фото","")))) | AO10: =IF(NOT(COUNTA(A10:AL10)>0),"",IF(AM10="","Можно публиковать","Не хватает"))
AM11: =IF(NOT(COUNTA(A11:AL11)>0),"",IF(TEXTJOIN(", ",TRUE,IF(B11="","Название",""),IF(C11="","Тип недвижимости",""),IF(D11="","Страна",""),IF(E11="","Город",""),IF(F11="","Улица",""),IF(I11="","Валюта",""),IF(OR(AE11="",AE11<1),"Хотя бы 1 фото",""),IF(AND(OR(C11="Квартира",C11="Апартаменты",C11="Дом",C11="Вилла",C11="Коммерческая"),J11=""),"Площадь",""),IF(AND(OR(C11="Квартира",C11="Апартаменты"),K11=""),"Жилая площадь",""),IF(AND(OR(C11="Дом",C11="Вилла",C11="Земля"),L11=""),"Площадь участка",""),IF(AND(OR(C11="Квартира",C11="Апартаменты"),M11=""),"Комнаты",""),IF(AND(OR(C11="Дом",C11="Вилла"),N11=""),"Спальни",""),IF(AND(OR(C11="Квартира",C11="Апартаменты",C11="Дом",C11="Вилла"),O11=""),"Ванные",""),IF(AND(OR(C11="Квартира",C11="Апартаменты"),P11=""),"Этаж",""),IF(AND(OR(OR(C11="Квартира",C11="Апартаменты"),OR(C11="Дом",C11="Вилла")),Q11=""),"Этажей",""),IF(AND(OR(OR(C11="Квартира",C11="Апартаменты"),OR(C11="Дом",C11="Вилла")),OR(R11="",R11>YEAR(TODAY()))),"Год постройки",""),IF(AND(P11<>"",Q11<>"",P11>Q11),"Этаж больше этажности",""),IF(AND(OR(C11="Квартира",C11="Апартаменты",C11="Дом",C11="Вилла"),S11=""),"Материал",""),IF(AND(OR(C11="Коммерческая"),U11=""),"Тип коммерции",""),IF(AND(OR(C11="Земля"),V11=""),"Назначение земли",""),IF(OR(W11="",W11<=0),"Продать сейчас",""),IF(OR(X11="",X11<=0),"Минимальная цена продажи",""),IF(OR(Y11="",Y11<=0),"Стартовая ставка",""),IF(Z11="","Начало аукциона",""),IF(AA11="","Окончание аукциона",""),IF(AND(W11<>"",X11<>"",X11>W11),"Минимальная цена выше «Продать сейчас»",""),IF(AND(W11<>"",X11<>"",X11<=W11,X11>W11*0.9),"Минимальная цена выше 90% от «Продать сейчас»",""),IF(AND(W11<>"",Y11<>"",Y11>W11*0.3),"Стартовая ставка выше 30% от «Продать сейчас»",""),IF(AND(Z11<>"",AA11<>"",AA11<EDATE(Z11,3)+15),"Аукцион короче 3 месяцев и 15 дней",""),IF(AND(AB11="Да",OR(AC11="",AC11<=0)),"Цена тест-драйва за сутки",""),IF(OR(AJ11="",AJ11="Нет"),"Право собственности",""),IF(OR(AK11="",AK11="Нет"),"Справка об отсутствии обременений",""))="","",TEXTJOIN(", ",TRUE,IF(B11="","Название",""),IF(C11="","Тип недвижимости",""),IF(D11="","Страна",""),IF(E11="","Город",""),IF(F11="","Улица",""),IF(I11="","Валюта",""),IF(OR(AE11="",AE11<1),"Хотя бы 1 фото",""),IF(AND(OR(C11="Квартира",C11="Апартаменты",C11="Дом",C11="Вилла",C11="Коммерческая"),J11=""),"Площадь",""),IF(AND(OR(C11="Квартира",C11="Апартаменты"),K11=""),"Жилая площадь",""),IF(AND(OR(C11="Дом",C11="Вилла",C11="Земля"),L11=""),"Площадь участка",""),IF(AND(OR(C11="Квартира",C11="Апартаменты"),M11=""),"Комнаты",""),IF(AND(OR(C11="Дом",C11="Вилла"),N11=""),"Спальни",""),IF(AND(OR(C11="Квартира",C11="Апартаменты",C11="Дом",C11="Вилла"),O11=""),"Ванные",""),IF(AND(OR(C11="Квартира",C11="Апартаменты"),P11=""),"Этаж",""),IF(AND(OR(OR(C11="Квартира",C11="Апартаменты"),OR(C11="Дом",C11="Вилла")),Q11=""),"Этажей",""),IF(AND(OR(OR(C11="Квартира",C11="Апартаменты"),OR(C11="Дом",C11="Вилла")),OR(R11="",R11>YEAR(TODAY()))),"Год постройки",""),IF(AND(P11<>"",Q11<>"",P11>Q11),"Этаж больше этажности",""),IF(AND(OR(C11="Квартира",C11="Апартаменты",C11="Дом",C11="Вилла"),S11=""),"Материал",""),IF(AND(OR(C11="Коммерческая"),U11=""),"Тип коммерции",""),IF(AND(OR(C11="Земля"),V11=""),"Назначение земли",""),IF(OR(W11="",W11<=0),"Продать сейчас",""),IF(OR(X11="",X11<=0),"Минимальная цена продажи",""),IF(OR(Y11="",Y11<=0),"Стартовая ставка",""),IF(Z11="","Начало аукциона",""),IF(AA11="","Окончание аукциона",""),IF(AND(W11<>"",X11<>"",X11>W11),"Минимальная цена выше «Продать сейчас»",""),IF(AND(W11<>"",X11<>"",X11<=W11,X11>W11*0.9),"Минимальная цена выше 90% от «Продать сейчас»",""),IF(AND(W11<>"",Y11<>"",Y11>W11*0.3),"Стартовая ставка выше 30% от «Продать сейчас»",""),IF(AND(Z11<>"",AA11<>"",AA11<EDATE(Z11,3)+15),"Аукцион короче 3 месяцев и 15 дней",""),IF(AND(AB11="Да",OR(AC11="",AC11<=0)),"Цена тест-драйва за сутки",""),IF(OR(AJ11="",AJ11="Нет"),"Право собственности",""),IF(OR(AK11="",AK11="Нет"),"Справка об отсутствии обременений","")))) | AN11: =IF(NOT(COUNTA(A11:AL11)>0),"",IF(TEXTJOIN(", ",TRUE,IF(AH11="","Описание",""),IF(AND(AE11<>"",AE11>=1,AE11<5),"Фото меньше 5",""),IF(AG11="","Видео",""),IF(H11="","Кадастровый номер",""),IF(AF11="","Ссылка на фото",""))="","",TEXTJOIN(", ",TRUE,IF(AH11="","Описание",""),IF(AND(AE11<>"",AE11>=1,AE11<5),"Фото меньше 5",""),IF(AG11="","Видео",""),IF(H11="","Кадастровый номер",""),IF(AF11="","Ссылка на фото","")))) | AO11: =IF(NOT(COUNTA(A11:AL11)>0),"",IF(AM11="","Можно публиковать","Не хватает"))
AM12: =IF(NOT(COUNTA(A12:AL12)>0),"",IF(TEXTJOIN(", ",TRUE,IF(B12="","Название",""),IF(C12="","Тип недвижимости",""),IF(D12="","Страна",""),IF(E12="","Город",""),IF(F12="","Улица",""),IF(I12="","Валюта",""),IF(OR(AE12="",AE12<1),"Хотя бы 1 фото",""),IF(AND(OR(C12="Квартира",C12="Апартаменты",C12="Дом",C12="Вилла",C12="Коммерческая"),J12=""),"Площадь",""),IF(AND(OR(C12="Квартира",C12="Апартаменты"),K12=""),"Жилая площадь",""),IF(AND(OR(C12="Дом",C12="Вилла",C12="Земля"),L12=""),"Площадь участка",""),IF(AND(OR(C12="Квартира",C12="Апартаменты"),M12=""),"Комнаты",""),IF(AND(OR(C12="Дом",C12="Вилла"),N12=""),"Спальни",""),IF(AND(OR(C12="Квартира",C12="Апартаменты",C12="Дом",C12="Вилла"),O12=""),"Ванные",""),IF(AND(OR(C12="Квартира",C12="Апартаменты"),P12=""),"Этаж",""),IF(AND(OR(OR(C12="Квартира",C12="Апартаменты"),OR(C12="Дом",C12="Вилла")),Q12=""),"Этажей",""),IF(AND(OR(OR(C12="Квартира",C12="Апартаменты"),OR(C12="Дом",C12="Вилла")),OR(R12="",R12>YEAR(TODAY()))),"Год постройки",""),IF(AND(P12<>"",Q12<>"",P12>Q12),"Этаж больше этажности",""),IF(AND(OR(C12="Квартира",C12="Апартаменты",C12="Дом",C12="Вилла"),S12=""),"Материал",""),IF(AND(OR(C12="Коммерческая"),U12=""),"Тип коммерции",""),IF(AND(OR(C12="Земля"),V12=""),"Назначение земли",""),IF(OR(W12="",W12<=0),"Продать сейчас",""),IF(OR(X12="",X12<=0),"Минимальная цена продажи",""),IF(OR(Y12="",Y12<=0),"Стартовая ставка",""),IF(Z12="","Начало аукциона",""),IF(AA12="","Окончание аукциона",""),IF(AND(W12<>"",X12<>"",X12>W12),"Минимальная цена выше «Продать сейчас»",""),IF(AND(W12<>"",X12<>"",X12<=W12,X12>W12*0.9),"Минимальная цена выше 90% от «Продать сейчас»",""),IF(AND(W12<>"",Y12<>"",Y12>W12*0.3),"Стартовая ставка выше 30% от «Продать сейчас»",""),IF(AND(Z12<>"",AA12<>"",AA12<EDATE(Z12,3)+15),"Аукцион короче 3 месяцев и 15 дней",""),IF(AND(AB12="Да",OR(AC12="",AC12<=0)),"Цена тест-драйва за сутки",""),IF(OR(AJ12="",AJ12="Нет"),"Право собственности",""),IF(OR(AK12="",AK12="Нет"),"Справка об отсутствии обременений",""))="","",TEXTJOIN(", ",TRUE,IF(B12="","Название",""),IF(C12="","Тип недвижимости",""),IF(D12="","Страна",""),IF(E12="","Город",""),IF(F12="","Улица",""),IF(I12="","Валюта",""),IF(OR(AE12="",AE12<1),"Хотя бы 1 фото",""),IF(AND(OR(C12="Квартира",C12="Апартаменты",C12="Дом",C12="Вилла",C12="Коммерческая"),J12=""),"Площадь",""),IF(AND(OR(C12="Квартира",C12="Апартаменты"),K12=""),"Жилая площадь",""),IF(AND(OR(C12="Дом",C12="Вилла",C12="Земля"),L12=""),"Площадь участка",""),IF(AND(OR(C12="Квартира",C12="Апартаменты"),M12=""),"Комнаты",""),IF(AND(OR(C12="Дом",C12="Вилла"),N12=""),"Спальни",""),IF(AND(OR(C12="Квартира",C12="Апартаменты",C12="Дом",C12="Вилла"),O12=""),"Ванные",""),IF(AND(OR(C12="Квартира",C12="Апартаменты"),P12=""),"Этаж",""),IF(AND(OR(OR(C12="Квартира",C12="Апартаменты"),OR(C12="Дом",C12="Вилла")),Q12=""),"Этажей",""),IF(AND(OR(OR(C12="Квартира",C12="Апартаменты"),OR(C12="Дом",C12="Вилла")),OR(R12="",R12>YEAR(TODAY()))),"Год постройки",""),IF(AND(P12<>"",Q12<>"",P12>Q12),"Этаж больше этажности",""),IF(AND(OR(C12="Квартира",C12="Апартаменты",C12="Дом",C12="Вилла"),S12=""),"Материал",""),IF(AND(OR(C12="Коммерческая"),U12=""),"Тип коммерции",""),IF(AND(OR(C12="Земля"),V12=""),"Назначение земли",""),IF(OR(W12="",W12<=0),"Продать сейчас",""),IF(OR(X12="",X12<=0),"Минимальная цена продажи",""),IF(OR(Y12="",Y12<=0),"Стартовая ставка",""),IF(Z12="","Начало аукциона",""),IF(AA12="","Окончание аукциона",""),IF(AND(W12<>"",X12<>"",X12>W12),"Минимальная цена выше «Продать сейчас»",""),IF(AND(W12<>"",X12<>"",X12<=W12,X12>W12*0.9),"Минимальная цена выше 90% от «Продать сейчас»",""),IF(AND(W12<>"",Y12<>"",Y12>W12*0.3),"Стартовая ставка выше 30% от «Продать сейчас»",""),IF(AND(Z12<>"",AA12<>"",AA12<EDATE(Z12,3)+15),"Аукцион короче 3 месяцев и 15 дней",""),IF(AND(AB12="Да",OR(AC12="",AC12<=0)),"Цена тест-драйва за сутки",""),IF(OR(AJ12="",AJ12="Нет"),"Право собственности",""),IF(OR(AK12="",AK12="Нет"),"Справка об отсутствии обременений","")))) | AN12: =IF(NOT(COUNTA(A12:AL12)>0),"",IF(TEXTJOIN(", ",TRUE,IF(AH12="","Описание",""),IF(AND(AE12<>"",AE12>=1,AE12<5),"Фото меньше 5",""),IF(AG12="","Видео",""),IF(H12="","Кадастровый номер",""),IF(AF12="","Ссылка на фото",""))="","",TEXTJOIN(", ",TRUE,IF(AH12="","Описание",""),IF(AND(AE12<>"",AE12>=1,AE12<5),"Фото меньше 5",""),IF(AG12="","Видео",""),IF(H12="","Кадастровый номер",""),IF(AF12="","Ссылка на фото","")))) | AO12: =IF(NOT(COUNTA(A12:AL12)>0),"",IF(AM12="","Можно публиковать","Не хватает"))
AM13: =IF(NOT(COUNTA(A13:AL13)>0),"",IF(TEXTJOIN(", ",TRUE,IF(B13="","Название",""),IF(C13="","Тип недвижимости",""),IF(D13="","Страна",""),IF(E13="","Город",""),IF(F13="","Улица",""),IF(I13="","Валюта",""),IF(OR(AE13="",AE13<1),"Хотя бы 1 фото",""),IF(AND(OR(C13="Квартира",C13="Апартаменты",C13="Дом",C13="Вилла",C13="Коммерческая"),J13=""),"Площадь",""),IF(AND(OR(C13="Квартира",C13="Апартаменты"),K13=""),"Жилая площадь",""),IF(AND(OR(C13="Дом",C13="Вилла",C13="Земля"),L13=""),"Площадь участка",""),IF(AND(OR(C13="Квартира",C13="Апартаменты"),M13=""),"Комнаты",""),IF(AND(OR(C13="Дом",C13="Вилла"),N13=""),"Спальни",""),IF(AND(OR(C13="Квартира",C13="Апартаменты",C13="Дом",C13="Вилла"),O13=""),"Ванные",""),IF(AND(OR(C13="Квартира",C13="Апартаменты"),P13=""),"Этаж",""),IF(AND(OR(OR(C13="Квартира",C13="Апартаменты"),OR(C13="Дом",C13="Вилла")),Q13=""),"Этажей",""),IF(AND(OR(OR(C13="Квартира",C13="Апартаменты"),OR(C13="Дом",C13="Вилла")),OR(R13="",R13>YEAR(TODAY()))),"Год постройки",""),IF(AND(P13<>"",Q13<>"",P13>Q13),"Этаж больше этажности",""),IF(AND(OR(C13="Квартира",C13="Апартаменты",C13="Дом",C13="Вилла"),S13=""),"Материал",""),IF(AND(OR(C13="Коммерческая"),U13=""),"Тип коммерции",""),IF(AND(OR(C13="Земля"),V13=""),"Назначение земли",""),IF(OR(W13="",W13<=0),"Продать сейчас",""),IF(OR(X13="",X13<=0),"Минимальная цена продажи",""),IF(OR(Y13="",Y13<=0),"Стартовая ставка",""),IF(Z13="","Начало аукциона",""),IF(AA13="","Окончание аукциона",""),IF(AND(W13<>"",X13<>"",X13>W13),"Минимальная цена выше «Продать сейчас»",""),IF(AND(W13<>"",X13<>"",X13<=W13,X13>W13*0.9),"Минимальная цена выше 90% от «Продать сейчас»",""),IF(AND(W13<>"",Y13<>"",Y13>W13*0.3),"Стартовая ставка выше 30% от «Продать сейчас»",""),IF(AND(Z13<>"",AA13<>"",AA13<EDATE(Z13,3)+15),"Аукцион короче 3 месяцев и 15 дней",""),IF(AND(AB13="Да",OR(AC13="",AC13<=0)),"Цена тест-драйва за сутки",""),IF(OR(AJ13="",AJ13="Нет"),"Право собственности",""),IF(OR(AK13="",AK13="Нет"),"Справка об отсутствии обременений",""))="","",TEXTJOIN(", ",TRUE,IF(B13="","Название",""),IF(C13="","Тип недвижимости",""),IF(D13="","Страна",""),IF(E13="","Город",""),IF(F13="","Улица",""),IF(I13="","Валюта",""),IF(OR(AE13="",AE13<1),"Хотя бы 1 фото",""),IF(AND(OR(C13="Квартира",C13="Апартаменты",C13="Дом",C13="Вилла",C13="Коммерческая"),J13=""),"Площадь",""),IF(AND(OR(C13="Квартира",C13="Апартаменты"),K13=""),"Жилая площадь",""),IF(AND(OR(C13="Дом",C13="Вилла",C13="Земля"),L13=""),"Площадь участка",""),IF(AND(OR(C13="Квартира",C13="Апартаменты"),M13=""),"Комнаты",""),IF(AND(OR(C13="Дом",C13="Вилла"),N13=""),"Спальни",""),IF(AND(OR(C13="Квартира",C13="Апартаменты",C13="Дом",C13="Вилла"),O13=""),"Ванные",""),IF(AND(OR(C13="Квартира",C13="Апартаменты"),P13=""),"Этаж",""),IF(AND(OR(OR(C13="Квартира",C13="Апартаменты"),OR(C13="Дом",C13="Вилла")),Q13=""),"Этажей",""),IF(AND(OR(OR(C13="Квартира",C13="Апартаменты"),OR(C13="Дом",C13="Вилла")),OR(R13="",R13>YEAR(TODAY()))),"Год постройки",""),IF(AND(P13<>"",Q13<>"",P13>Q13),"Этаж больше этажности",""),IF(AND(OR(C13="Квартира",C13="Апартаменты",C13="Дом",C13="Вилла"),S13=""),"Материал",""),IF(AND(OR(C13="Коммерческая"),U13=""),"Тип коммерции",""),IF(AND(OR(C13="Земля"),V13=""),"Назначение земли",""),IF(OR(W13="",W13<=0),"Продать сейчас",""),IF(OR(X13="",X13<=0),"Минимальная цена продажи",""),IF(OR(Y13="",Y13<=0),"Стартовая ставка",""),IF(Z13="","Начало аукциона",""),IF(AA13="","Окончание аукциона",""),IF(AND(W13<>"",X13<>"",X13>W13),"Минимальная цена выше «Продать сейчас»",""),IF(AND(W13<>"",X13<>"",X13<=W13,X13>W13*0.9),"Минимальная цена выше 90% от «Продать сейчас»",""),IF(AND(W13<>"",Y13<>"",Y13>W13*0.3),"Стартовая ставка выше 30% от «Продать сейчас»",""),IF(AND(Z13<>"",AA13<>"",AA13<EDATE(Z13,3)+15),"Аукцион короче 3 месяцев и 15 дней",""),IF(AND(AB13="Да",OR(AC13="",AC13<=0)),"Цена тест-драйва за сутки",""),IF(OR(AJ13="",AJ13="Нет"),"Право собственности",""),IF(OR(AK13="",AK13="Нет"),"Справка об отсутствии обременений","")))) | AN13: =IF(NOT(COUNTA(A13:AL13)>0),"",IF(TEXTJOIN(", ",TRUE,IF(AH13="","Описание",""),IF(AND(AE13<>"",AE13>=1,AE13<5),"Фото меньше 5",""),IF(AG13="","Видео",""),IF(H13="","Кадастровый номер",""),IF(AF13="","Ссылка на фото",""))="","",TEXTJOIN(", ",TRUE,IF(AH13="","Описание",""),IF(AND(AE13<>"",AE13>=1,AE13<5),"Фото меньше 5",""),IF(AG13="","Видео",""),IF(H13="","Кадастровый номер",""),IF(AF13="","Ссылка на фото","")))) | AO13: =IF(NOT(COUNTA(A13:AL13)>0),"",IF(AM13="","Можно публиковать","Не хватает"))
AM14: =IF(NOT(COUNTA(A14:AL14)>0),"",IF(TEXTJOIN(", ",TRUE,IF(B14="","Название",""),IF(C14="","Тип недвижимости",""),IF(D14="","Страна",""),IF(E14="","Город",""),IF(F14="","Улица",""),IF(I14="","Валюта",""),IF(OR(AE14="",AE14<1),"Хотя бы 1 фото",""),IF(AND(OR(C14="Квартира",C14="Апартаменты",C14="Дом",C14="Вилла",C14="Коммерческая"),J14=""),"Площадь",""),IF(AND(OR(C14="Квартира",C14="Апартаменты"),K14=""),"Жилая площадь",""),IF(AND(OR(C14="Дом",C14="Вилла",C14="Земля"),L14=""),"Площадь участка",""),IF(AND(OR(C14="Квартира",C14="Апартаменты"),M14=""),"Комнаты",""),IF(AND(OR(C14="Дом",C14="Вилла"),N14=""),"Спальни",""),IF(AND(OR(C14="Квартира",C14="Апартаменты",C14="Дом",C14="Вилла"),O14=""),"Ванные",""),IF(AND(OR(C14="Квартира",C14="Апартаменты"),P14=""),"Этаж",""),IF(AND(OR(OR(C14="Квартира",C14="Апартаменты"),OR(C14="Дом",C14="Вилла")),Q14=""),"Этажей",""),IF(AND(OR(OR(C14="Квартира",C14="Апартаменты"),OR(C14="Дом",C14="Вилла")),OR(R14="",R14>YEAR(TODAY()))),"Год постройки",""),IF(AND(P14<>"",Q14<>"",P14>Q14),"Этаж больше этажности",""),IF(AND(OR(C14="Квартира",C14="Апартаменты",C14="Дом",C14="Вилла"),S14=""),"Материал",""),IF(AND(OR(C14="Коммерческая"),U14=""),"Тип коммерции",""),IF(AND(OR(C14="Земля"),V14=""),"Назначение земли",""),IF(OR(W14="",W14<=0),"Продать сейчас",""),IF(OR(X14="",X14<=0),"Минимальная цена продажи",""),IF(OR(Y14="",Y14<=0),"Стартовая ставка",""),IF(Z14="","Начало аукциона",""),IF(AA14="","Окончание аукциона",""),IF(AND(W14<>"",X14<>"",X14>W14),"Минимальная цена выше «Продать сейчас»",""),IF(AND(W14<>"",X14<>"",X14<=W14,X14>W14*0.9),"Минимальная цена выше 90% от «Продать сейчас»",""),IF(AND(W14<>"",Y14<>"",Y14>W14*0.3),"Стартовая ставка выше 30% от «Продать сейчас»",""),IF(AND(Z14<>"",AA14<>"",AA14<EDATE(Z14,3)+15),"Аукцион короче 3 месяцев и 15 дней",""),IF(AND(AB14="Да",OR(AC14="",AC14<=0)),"Цена тест-драйва за сутки",""),IF(OR(AJ14="",AJ14="Нет"),"Право собственности",""),IF(OR(AK14="",AK14="Нет"),"Справка об отсутствии обременений",""))="","",TEXTJOIN(", ",TRUE,IF(B14="","Название",""),IF(C14="","Тип недвижимости",""),IF(D14="","Страна",""),IF(E14="","Город",""),IF(F14="","Улица",""),IF(I14="","Валюта",""),IF(OR(AE14="",AE14<1),"Хотя бы 1 фото",""),IF(AND(OR(C14="Квартира",C14="Апартаменты",C14="Дом",C14="Вилла",C14="Коммерческая"),J14=""),"Площадь",""),IF(AND(OR(C14="Квартира",C14="Апартаменты"),K14=""),"Жилая площадь",""),IF(AND(OR(C14="Дом",C14="Вилла",C14="Земля"),L14=""),"Площадь участка",""),IF(AND(OR(C14="Квартира",C14="Апартаменты"),M14=""),"Комнаты",""),IF(AND(OR(C14="Дом",C14="Вилла"),N14=""),"Спальни",""),IF(AND(OR(C14="Квартира",C14="Апартаменты",C14="Дом",C14="Вилла"),O14=""),"Ванные",""),IF(AND(OR(C14="Квартира",C14="Апартаменты"),P14=""),"Этаж",""),IF(AND(OR(OR(C14="Квартира",C14="Апартаменты"),OR(C14="Дом",C14="Вилла")),Q14=""),"Этажей",""),IF(AND(OR(OR(C14="Квартира",C14="Апартаменты"),OR(C14="Дом",C14="Вилла")),OR(R14="",R14>YEAR(TODAY()))),"Год постройки",""),IF(AND(P14<>"",Q14<>"",P14>Q14),"Этаж больше этажности",""),IF(AND(OR(C14="Квартира",C14="Апартаменты",C14="Дом",C14="Вилла"),S14=""),"Материал",""),IF(AND(OR(C14="Коммерческая"),U14=""),"Тип коммерции",""),IF(AND(OR(C14="Земля"),V14=""),"Назначение земли",""),IF(OR(W14="",W14<=0),"Продать сейчас",""),IF(OR(X14="",X14<=0),"Минимальная цена продажи",""),IF(OR(Y14="",Y14<=0),"Стартовая ставка",""),IF(Z14="","Начало аукциона",""),IF(AA14="","Окончание аукциона",""),IF(AND(W14<>"",X14<>"",X14>W14),"Минимальная цена выше «Продать сейчас»",""),IF(AND(W14<>"",X14<>"",X14<=W14,X14>W14*0.9),"Минимальная цена выше 90% от «Продать сейчас»",""),IF(AND(W14<>"",Y14<>"",Y14>W14*0.3),"Стартовая ставка выше 30% от «Продать сейчас»",""),IF(AND(Z14<>"",AA14<>"",AA14<EDATE(Z14,3)+15),"Аукцион короче 3 месяцев и 15 дней",""),IF(AND(AB14="Да",OR(AC14="",AC14<=0)),"Цена тест-драйва за сутки",""),IF(OR(AJ14="",AJ14="Нет"),"Право собственности",""),IF(OR(AK14="",AK14="Нет"),"Справка об отсутствии обременений","")))) | AN14: =IF(NOT(COUNTA(A14:AL14)>0),"",IF(TEXTJOIN(", ",TRUE,IF(AH14="","Описание",""),IF(AND(AE14<>"",AE14>=1,AE14<5),"Фото меньше 5",""),IF(AG14="","Видео",""),IF(H14="","Кадастровый номер",""),IF(AF14="","Ссылка на фото",""))="","",TEXTJOIN(", ",TRUE,IF(AH14="","Описание",""),IF(AND(AE14<>"",AE14>=1,AE14<5),"Фото меньше 5",""),IF(AG14="","Видео",""),IF(H14="","Кадастровый номер",""),IF(AF14="","Ссылка на фото","")))) | AO14: =IF(NOT(COUNTA(A14:AL14)>0),"",IF(AM14="","Можно публиковать","Не хватает"))
... AM82: =IF(NOT(COUNTA(A82:AL82)>0),"",IF(TEXTJOIN(", ",TRUE,IF(B82="","Название",""),IF(C82="","Тип недвижимости",""),IF(D82="","Страна",""),IF(E82="","Город",""),IF(F82="","Улица",""),IF(I82="","Валюта",""),IF(OR(AE82="",AE82<1),"Хотя бы 1 фото",""),IF(AND(OR(C82="Квартира",C82="Апартаменты",C82="Дом",C82="Вилла",C82="Коммерческая"),J82=""),"Площадь",""),IF(AND(OR(C82="Квартира",C82="Апартаменты"),K82=""),"Жилая площадь",""),IF(AND(OR(C82="Дом",C82="Вилла",C82="Земля"),L82=""),"Площадь участка",""),IF(AND(OR(C82="Квартира",C82="Апартаменты"),M82=""),"Комнаты",""),IF(AND(OR(C82="Дом",C82="Вилла"),N82=""),"Спальни",""),IF(AND(OR(C82="Квартира",C82="Апартаменты",C82="Дом",C82="Вилла"),O82=""),"Ванные",""),IF(AND(OR(C82="Квартира",C82="Апартаменты"),P82=""),"Этаж",""),IF(AND(OR(OR(C82="Квартира",C82="Апартаменты"),OR(C82="Дом",C82="Вилла")),Q82=""),"Этажей",""),IF(AND(OR(OR(C82="Квартира",C82="Апартаменты"),OR(C82="Дом",C82="Вилла")),OR(R82="",R82>YEAR(TODAY()))),"Год постройки",""),IF(AND(P82<>"",Q82<>"",P82>Q82),"Этаж больше этажности",""),IF(AND(OR(C82="Квартира",C82="Апартаменты",C82="Дом",C82="Вилла"),S82=""),"Материал",""),IF(AND(OR(C82="Коммерческая"),U82=""),"Тип коммерции",""),IF(AND(OR(C82="Земля"),V82=""),"Назначение земли",""),IF(OR(W82="",W82<=0),"Продать сейчас",""),IF(OR(X82="",X82<=0),"Минимальная цена продажи",""),IF(OR(Y82="",Y82<=0),"Стартовая ставка",""),IF(Z82="","Начало аукциона",""),IF(AA82="","Окончание аукциона",""),IF(AND(W82<>"",X82<>"",X82>W82),"Минимальная цена выше «Продать сейчас»",""),IF(AND(W82<>"",X82<>"",X82<=W82,X82>W82*0.9),"Минимальная цена выше 90% от «Продать сейчас»",""),IF(AND(W82<>"",Y82<>"",Y82>W82*0.3),"Стартовая ставка выше 30% от «Продать сейчас»",""),IF(AND(Z82<>"",AA82<>"",AA82<EDATE(Z82,3)+15),"Аукцион короче 3 месяцев и 15 дней",""),IF(AND(AB82="Да",OR(AC82="",AC82<=0)),"Цена тест-драйва за сутки",""),IF(OR(AJ82="",AJ82="Нет"),"Право собственности",""),IF(OR(AK82="",AK82="Нет"),"Справка об отсутствии обременений",""))="","",TEXTJOIN(", ",TRUE,IF(B82="","Название",""),IF(C82="","Тип недвижимости",""),IF(D82="","Страна",""),IF(E82="","Город",""),IF(F82="","Улица",""),IF(I82="","Валюта",""),IF(OR(AE82="",AE82<1),"Хотя бы 1 фото",""),IF(AND(OR(C82="Квартира",C82="Апартаменты",C82="Дом",C82="Вилла",C82="Коммерческая"),J82=""),"Площадь",""),IF(AND(OR(C82="Квартира",C82="Апартаменты"),K82=""),"Жилая площадь",""),IF(AND(OR(C82="Дом",C82="Вилла",C82="Земля"),L82=""),"Площадь участка",""),IF(AND(OR(C82="Квартира",C82="Апартаменты"),M82=""),"Комнаты",""),IF(AND(OR(C82="Дом",C82="Вилла"),N82=""),"Спальни",""),IF(AND(OR(C82="Квартира",C82="Апартаменты",C82="Дом",C82="Вилла"),O82=""),"Ванные",""),IF(AND(OR(C82="Квартира",C82="Апартаменты"),P82=""),"Этаж",""),IF(AND(OR(OR(C82="Квартира",C82="Апартаменты"),OR(C82="Дом",C82="Вилла")),Q82=""),"Этажей",""),IF(AND(OR(OR(C82="Квартира",C82="Апартаменты"),OR(C82="Дом",C82="Вилла")),OR(R82="",R82>YEAR(TODAY()))),"Год постройки",""),IF(AND(P82<>"",Q82<>"",P82>Q82),"Этаж больше этажности",""),IF(AND(OR(C82="Квартира",C82="Апартаменты",C82="Дом",C82="Вилла"),S82=""),"Материал",""),IF(AND(OR(C82="Коммерческая"),U82=""),"Тип коммерции",""),IF(AND(OR(C82="Земля"),V82=""),"Назначение земли",""),IF(OR(W82="",W82<=0),"Продать сейчас",""),IF(OR(X82="",X82<=0),"Минимальная цена продажи",""),IF(OR(Y82="",Y82<=0),"Стартовая ставка",""),IF(Z82="","Начало аукциона",""),IF(AA82="","Окончание аукциона",""),IF(AND(W82<>"",X82<>"",X82>W82),"Минимальная цена выше «Продать сейчас»",""),IF(AND(W82<>"",X82<>"",X82<=W82,X82>W82*0.9),"Минимальная цена выше 90% от «Продать сейчас»",""),IF(AND(W82<>"",Y82<>"",Y82>W82*0.3),"Стартовая ставка выше 30% от «Продать сейчас»",""),IF(AND(Z82<>"",AA82<>"",AA82<EDATE(Z82,3)+15),"Аукцион короче 3 месяцев и 15 дней",""),IF(AND(AB82="Да",OR(AC82="",AC82<=0)),"Цена тест-драйва за сутки",""),IF(OR(AJ82="",AJ82="Нет"),"Право собственности",""),IF(OR(AK82="",AK82="Нет"),"Справка об отсутствии обременений","")))) | AN82: =IF(NOT(COUNTA(A82:AL82)>0),"",IF(TEXTJOIN(", ",TRUE,IF(AH82="","Описание",""),IF(AND(AE82<>"",AE82>=1,AE82<5),"Фото меньше 5",""),IF(AG82="","Видео",""),IF(H82="","Кадастровый номер",""),IF(AF82="","Ссылка на фото",""))="","",TEXTJOIN(", ",TRUE,IF(AH82="","Описание",""),IF(AND(AE82<>"",AE82>=1,AE82<5),"Фото меньше 5",""),IF(AG82="","Видео",""),IF(H82="","Кадастровый номер",""),IF(AF82="","Ссылка на фото","")))) | AO82: =IF(NOT(COUNTA(A82:AL82)>0),"",IF(AM82="","Можно публиковать","Не хватает"))

Sheet Аукцион
A1: Сбор | B1: Объект | D1: Адрес | I1: Объект | J1: Параметры | W1: Цена | AB1: Тест-драйв | AE1: Подача | AJ1: Документы | AM1: Проверка
A2: Источник | B2: Название | C2: Тип недвижимости | D2: Страна | E2: Город | F2: Улица | G2: Номер дома | H2: Кадастровый номер | I2: Валюта | J2: Площадь, м² | K2: Жилая, м² | L2: Участок, м² | M2: Комнаты | N2: Спальни | O2: Ванные | P2: Этаж | Q2: Этажей | R2: Год | S2: Материал | T2: Конструкция | U2: Тип коммерции | V2: Назначение земли | W2: Продать сейчас | X2: Минимальная цена | Y2: Стартовая ставка | Z2: Начало аукциона | AA2: Окончание аукциона | AB2: Тест-драйв | AC2: Сутки тест-драйва | AD2: Депозит тест-драйва | AE2: Фото, шт. | AF2: Ссылка на фото | AG2: Ссылка на видео | AH2: Описание | AI2: Удобства | AJ2: Право собственности | AK2: Нет обременений | AL2: Доп. документы | AM2: Не хватает для публикации | AN2: Желательно добрать | AO2: Готовность
AM3: =IF(NOT(COUNTA(A3:AL3)>0),"",IF(TEXTJOIN(", ",TRUE,IF(B3="","Название",""),IF(C3="","Тип недвижимости",""),IF(D3="","Страна",""),IF(E3="","Город",""),IF(F3="","Улица",""),IF(I3="","Валюта",""),IF(OR(AE3="",AE3<1),"Хотя бы 1 фото",""),IF(AND(OR(C3="Квартира",C3="Апартаменты",C3="Дом",C3="Вилла",C3="Коммерческая"),J3=""),"Площадь",""),IF(AND(OR(C3="Квартира",C3="Апартаменты"),K3=""),"Жилая площадь",""),IF(AND(OR(C3="Дом",C3="Вилла",C3="Земля"),L3=""),"Площадь участка",""),IF(AND(OR(C3="Квартира",C3="Апартаменты"),M3=""),"Комнаты",""),IF(AND(OR(C3="Дом",C3="Вилла"),N3=""),"Спальни",""),IF(AND(OR(C3="Квартира",C3="Апартаменты",C3="Дом",C3="Вилла"),O3=""),"Ванные",""),IF(AND(OR(C3="Квартира",C3="Апартаменты"),P3=""),"Этаж",""),IF(AND(OR(OR(C3="Квартира",C3="Апартаменты"),OR(C3="Дом",C3="Вилла")),Q3=""),"Этажей",""),IF(AND(OR(OR(C3="Квартира",C3="Апартаменты"),OR(C3="Дом",C3="Вилла")),OR(R3="",R3>YEAR(TODAY()))),"Год постройки",""),IF(AND(P3<>"",Q3<>"",P3>Q3),"Этаж больше этажности",""),IF(AND(OR(C3="Квартира",C3="Апартаменты",C3="Дом",C3="Вилла"),S3=""),"Материал",""),IF(AND(OR(C3="Коммерческая"),U3=""),"Тип коммерции",""),IF(AND(OR(C3="Земля"),V3=""),"Назначение земли",""),IF(OR(X3="",X3<=0),"Минимальная цена продажи",""),IF(OR(Y3="",Y3<=0),"Стартовая ставка",""),IF(Z3="","Начало аукциона",""),IF(AA3="","Окончание аукциона",""),IF(AND(W3<>"",X3<>"",X3>W3),"Минимальная цена выше «Продать сейчас»",""),IF(AND(W3<>"",X3<>"",X3<=W3,X3>W3*0.9),"Минимальная цена выше 90% от «Продать сейчас»",""),IF(AND(W3<>"",Y3<>"",Y3>W3*0.3),"Стартовая ставка выше 30% от «Продать сейчас»",""),IF(AND(Z3<>"",AA3<>"",AA3<EDATE(Z3,3)+15),"Аукцион короче 3 месяцев и 15 дней",""),IF(AND(AB3="Да",OR(AC3="",AC3<=0)),"Цена тест-драйва за сутки",""),IF(OR(AJ3="",AJ3="Нет"),"Право собственности",""),IF(OR(AK3="",AK3="Нет"),"Справка об отсутствии обременений",""))="","",TEXTJOIN(", ",TRUE,IF(B3="","Название",""),IF(C3="","Тип недвижимости",""),IF(D3="","Страна",""),IF(E3="","Город",""),IF(F3="","Улица",""),IF(I3="","Валюта",""),IF(OR(AE3="",AE3<1),"Хотя бы 1 фото",""),IF(AND(OR(C3="Квартира",C3="Апартаменты",C3="Дом",C3="Вилла",C3="Коммерческая"),J3=""),"Площадь",""),IF(AND(OR(C3="Квартира",C3="Апартаменты"),K3=""),"Жилая площадь",""),IF(AND(OR(C3="Дом",C3="Вилла",C3="Земля"),L3=""),"Площадь участка",""),IF(AND(OR(C3="Квартира",C3="Апартаменты"),M3=""),"Комнаты",""),IF(AND(OR(C3="Дом",C3="Вилла"),N3=""),"Спальни",""),IF(AND(OR(C3="Квартира",C3="Апартаменты",C3="Дом",C3="Вилла"),O3=""),"Ванные",""),IF(AND(OR(C3="Квартира",C3="Апартаменты"),P3=""),"Этаж",""),IF(AND(OR(OR(C3="Квартира",C3="Апартаменты"),OR(C3="Дом",C3="Вилла")),Q3=""),"Этажей",""),IF(AND(OR(OR(C3="Квартира",C3="Апартаменты"),OR(C3="Дом",C3="Вилла")),OR(R3="",R3>YEAR(TODAY()))),"Год постройки",""),IF(AND(P3<>"",Q3<>"",P3>Q3),"Этаж больше этажности",""),IF(AND(OR(C3="Квартира",C3="Апартаменты",C3="Дом",C3="Вилла"),S3=""),"Материал",""),IF(AND(OR(C3="Коммерческая"),U3=""),"Тип коммерции",""),IF(AND(OR(C3="Земля"),V3=""),"Назначение земли",""),IF(OR(X3="",X3<=0),"Минимальная цена продажи",""),IF(OR(Y3="",Y3<=0),"Стартовая ставка",""),IF(Z3="","Начало аукциона",""),IF(AA3="","Окончание аукциона",""),IF(AND(W3<>"",X3<>"",X3>W3),"Минимальная цена выше «Продать сейчас»",""),IF(AND(W3<>"",X3<>"",X3<=W3,X3>W3*0.9),"Минимальная цена выше 90% от «Продать сейчас»",""),IF(AND(W3<>"",Y3<>"",Y3>W3*0.3),"Стартовая ставка выше 30% от «Продать сейчас»",""),IF(AND(Z3<>"",AA3<>"",AA3<EDATE(Z3,3)+15),"Аукцион короче 3 месяцев и 15 дней",""),IF(AND(AB3="Да",OR(AC3="",AC3<=0)),"Цена тест-драйва за сутки",""),IF(OR(AJ3="",AJ3="Нет"),"Право собственности",""),IF(OR(AK3="",AK3="Нет"),"Справка об отсутствии обременений","")))) | AN3: =IF(NOT(COUNTA(A3:AL3)>0),"",IF(TEXTJOIN(", ",TRUE,IF(AH3="","Описание",""),IF(AND(AE3<>"",AE3>=1,AE3<5),"Фото меньше 5",""),IF(AG3="","Видео",""),IF(H3="","Кадастровый номер",""),IF(AF3="","Ссылка на фото",""))="","",TEXTJOIN(", ",TRUE,IF(AH3="","Описание",""),IF(AND(AE3<>"",AE3>=1,AE3<5),"Фото меньше 5",""),IF(AG3="","Видео",""),IF(H3="","Кадастровый номер",""),IF(AF3="","Ссылка на фото","")))) | AO3: =IF(NOT(COUNTA(A3:AL3)>0),"",IF(AM3="","Можно публиковать","Не хватает"))
AM4: =IF(NOT(COUNTA(A4:AL4)>0),"",IF(TEXTJOIN(", ",TRUE,IF(B4="","Название",""),IF(C4="","Тип недвижимости",""),IF(D4="","Страна",""),IF(E4="","Город",""),IF(F4="","Улица",""),IF(I4="","Валюта",""),IF(OR(AE4="",AE4<1),"Хотя бы 1 фото",""),IF(AND(OR(C4="Квартира",C4="Апартаменты",C4="Дом",C4="Вилла",C4="Коммерческая"),J4=""),"Площадь",""),IF(AND(OR(C4="Квартира",C4="Апартаменты"),K4=""),"Жилая площадь",""),IF(AND(OR(C4="Дом",C4="Вилла",C4="Земля"),L4=""),"Площадь участка",""),IF(AND(OR(C4="Квартира",C4="Апартаменты"),M4=""),"Комнаты",""),IF(AND(OR(C4="Дом",C4="Вилла"),N4=""),"Спальни",""),IF(AND(OR(C4="Квартира",C4="Апартаменты",C4="Дом",C4="Вилла"),O4=""),"Ванные",""),IF(AND(OR(C4="Квартира",C4="Апартаменты"),P4=""),"Этаж",""),IF(AND(OR(OR(C4="Квартира",C4="Апартаменты"),OR(C4="Дом",C4="Вилла")),Q4=""),"Этажей",""),IF(AND(OR(OR(C4="Квартира",C4="Апартаменты"),OR(C4="Дом",C4="Вилла")),OR(R4="",R4>YEAR(TODAY()))),"Год постройки",""),IF(AND(P4<>"",Q4<>"",P4>Q4),"Этаж больше этажности",""),IF(AND(OR(C4="Квартира",C4="Апартаменты",C4="Дом",C4="Вилла"),S4=""),"Материал",""),IF(AND(OR(C4="Коммерческая"),U4=""),"Тип коммерции",""),IF(AND(OR(C4="Земля"),V4=""),"Назначение земли",""),IF(OR(X4="",X4<=0),"Минимальная цена продажи",""),IF(OR(Y4="",Y4<=0),"Стартовая ставка",""),IF(Z4="","Начало аукциона",""),IF(AA4="","Окончание аукциона",""),IF(AND(W4<>"",X4<>"",X4>W4),"Минимальная цена выше «Продать сейчас»",""),IF(AND(W4<>"",X4<>"",X4<=W4,X4>W4*0.9),"Минимальная цена выше 90% от «Продать сейчас»",""),IF(AND(W4<>"",Y4<>"",Y4>W4*0.3),"Стартовая ставка выше 30% от «Продать сейчас»",""),IF(AND(Z4<>"",AA4<>"",AA4<EDATE(Z4,3)+15),"Аукцион короче 3 месяцев и 15 дней",""),IF(AND(AB4="Да",OR(AC4="",AC4<=0)),"Цена тест-драйва за сутки",""),IF(OR(AJ4="",AJ4="Нет"),"Право собственности",""),IF(OR(AK4="",AK4="Нет"),"Справка об отсутствии обременений",""))="","",TEXTJOIN(", ",TRUE,IF(B4="","Название",""),IF(C4="","Тип недвижимости",""),IF(D4="","Страна",""),IF(E4="","Город",""),IF(F4="","Улица",""),IF(I4="","Валюта",""),IF(OR(AE4="",AE4<1),"Хотя бы 1 фото",""),IF(AND(OR(C4="Квартира",C4="Апартаменты",C4="Дом",C4="Вилла",C4="Коммерческая"),J4=""),"Площадь",""),IF(AND(OR(C4="Квартира",C4="Апартаменты"),K4=""),"Жилая площадь",""),IF(AND(OR(C4="Дом",C4="Вилла",C4="Земля"),L4=""),"Площадь участка",""),IF(AND(OR(C4="Квартира",C4="Апартаменты"),M4=""),"Комнаты",""),IF(AND(OR(C4="Дом",C4="Вилла"),N4=""),"Спальни",""),IF(AND(OR(C4="Квартира",C4="Апартаменты",C4="Дом",C4="Вилла"),O4=""),"Ванные",""),IF(AND(OR(C4="Квартира",C4="Апартаменты"),P4=""),"Этаж",""),IF(AND(OR(OR(C4="Квартира",C4="Апартаменты"),OR(C4="Дом",C4="Вилла")),Q4=""),"Этажей",""),IF(AND(OR(OR(C4="Квартира",C4="Апартаменты"),OR(C4="Дом",C4="Вилла")),OR(R4="",R4>YEAR(TODAY()))),"Год постройки",""),IF(AND(P4<>"",Q4<>"",P4>Q4),"Этаж больше этажности",""),IF(AND(OR(C4="Квартира",C4="Апартаменты",C4="Дом",C4="Вилла"),S4=""),"Материал",""),IF(AND(OR(C4="Коммерческая"),U4=""),"Тип коммерции",""),IF(AND(OR(C4="Земля"),V4=""),"Назначение земли",""),IF(OR(X4="",X4<=0),"Минимальная цена продажи",""),IF(OR(Y4="",Y4<=0),"Стартовая ставка",""),IF(Z4="","Начало аукциона",""),IF(AA4="","Окончание аукциона",""),IF(AND(W4<>"",X4<>"",X4>W4),"Минимальная цена выше «Продать сейчас»",""),IF(AND(W4<>"",X4<>"",X4<=W4,X4>W4*0.9),"Минимальная цена выше 90% от «Продать сейчас»",""),IF(AND(W4<>"",Y4<>"",Y4>W4*0.3),"Стартовая ставка выше 30% от «Продать сейчас»",""),IF(AND(Z4<>"",AA4<>"",AA4<EDATE(Z4,3)+15),"Аукцион короче 3 месяцев и 15 дней",""),IF(AND(AB4="Да",OR(AC4="",AC4<=0)),"Цена тест-драйва за сутки",""),IF(OR(AJ4="",AJ4="Нет"),"Право собственности",""),IF(OR(AK4="",AK4="Нет"),"Справка об отсутствии обременений","")))) | AN4: =IF(NOT(COUNTA(A4:AL4)>0),"",IF(TEXTJOIN(", ",TRUE,IF(AH4="","Описание",""),IF(AND(AE4<>"",AE4>=1,AE4<5),"Фото меньше 5",""),IF(AG4="","Видео",""),IF(H4="","Кадастровый номер",""),IF(AF4="","Ссылка на фото",""))="","",TEXTJOIN(", ",TRUE,IF(AH4="","Описание",""),IF(AND(AE4<>"",AE4>=1,AE4<5),"Фото меньше 5",""),IF(AG4="","Видео",""),IF(H4="","Кадастровый номер",""),IF(AF4="","Ссылка на фото","")))) | AO4: =IF(NOT(COUNTA(A4:AL4)>0),"",IF(AM4="","Можно публиковать","Не хватает"))
AM5: =IF(NOT(COUNTA(A5:AL5)>0),"",IF(TEXTJOIN(", ",TRUE,IF(B5="","Название",""),IF(C5="","Тип недвижимости",""),IF(D5="","Страна",""),IF(E5="","Город",""),IF(F5="","Улица",""),IF(I5="","Валюта",""),IF(OR(AE5="",AE5<1),"Хотя бы 1 фото",""),IF(AND(OR(C5="Квартира",C5="Апартаменты",C5="Дом",C5="Вилла",C5="Коммерческая"),J5=""),"Площадь",""),IF(AND(OR(C5="Квартира",C5="Апартаменты"),K5=""),"Жилая площадь",""),IF(AND(OR(C5="Дом",C5="Вилла",C5="Земля"),L5=""),"Площадь участка",""),IF(AND(OR(C5="Квартира",C5="Апартаменты"),M5=""),"Комнаты",""),IF(AND(OR(C5="Дом",C5="Вилла"),N5=""),"Спальни",""),IF(AND(OR(C5="Квартира",C5="Апартаменты",C5="Дом",C5="Вилла"),O5=""),"Ванные",""),IF(AND(OR(C5="Квартира",C5="Апартаменты"),P5=""),"Этаж",""),IF(AND(OR(OR(C5="Квартира",C5="Апартаменты"),OR(C5="Дом",C5="Вилла")),Q5=""),"Этажей",""),IF(AND(OR(OR(C5="Квартира",C5="Апартаменты"),OR(C5="Дом",C5="Вилла")),OR(R5="",R5>YEAR(TODAY()))),"Год постройки",""),IF(AND(P5<>"",Q5<>"",P5>Q5),"Этаж больше этажности",""),IF(AND(OR(C5="Квартира",C5="Апартаменты",C5="Дом",C5="Вилла"),S5=""),"Материал",""),IF(AND(OR(C5="Коммерческая"),U5=""),"Тип коммерции",""),IF(AND(OR(C5="Земля"),V5=""),"Назначение земли",""),IF(OR(X5="",X5<=0),"Минимальная цена продажи",""),IF(OR(Y5="",Y5<=0),"Стартовая ставка",""),IF(Z5="","Начало аукциона",""),IF(AA5="","Окончание аукциона",""),IF(AND(W5<>"",X5<>"",X5>W5),"Минимальная цена выше «Продать сейчас»",""),IF(AND(W5<>"",X5<>"",X5<=W5,X5>W5*0.9),"Минимальная цена выше 90% от «Продать сейчас»",""),IF(AND(W5<>"",Y5<>"",Y5>W5*0.3),"Стартовая ставка выше 30% от «Продать сейчас»",""),IF(AND(Z5<>"",AA5<>"",AA5<EDATE(Z5,3)+15),"Аукцион короче 3 месяцев и 15 дней",""),IF(AND(AB5="Да",OR(AC5="",AC5<=0)),"Цена тест-драйва за сутки",""),IF(OR(AJ5="",AJ5="Нет"),"Право собственности",""),IF(OR(AK5="",AK5="Нет"),"Справка об отсутствии обременений",""))="","",TEXTJOIN(", ",TRUE,IF(B5="","Название",""),IF(C5="","Тип недвижимости",""),IF(D5="","Страна",""),IF(E5="","Город",""),IF(F5="","Улица",""),IF(I5="","Валюта",""),IF(OR(AE5="",AE5<1),"Хотя бы 1 фото",""),IF(AND(OR(C5="Квартира",C5="Апартаменты",C5="Дом",C5="Вилла",C5="Коммерческая"),J5=""),"Площадь",""),IF(AND(OR(C5="Квартира",C5="Апартаменты"),K5=""),"Жилая площадь",""),IF(AND(OR(C5="Дом",C5="Вилла",C5="Земля"),L5=""),"Площадь участка",""),IF(AND(OR(C5="Квартира",C5="Апартаменты"),M5=""),"Комнаты",""),IF(AND(OR(C5="Дом",C5="Вилла"),N5=""),"Спальни",""),IF(AND(OR(C5="Квартира",C5="Апартаменты",C5="Дом",C5="Вилла"),O5=""),"Ванные",""),IF(AND(OR(C5="Квартира",C5="Апартаменты"),P5=""),"Этаж",""),IF(AND(OR(OR(C5="Квартира",C5="Апартаменты"),OR(C5="Дом",C5="Вилла")),Q5=""),"Этажей",""),IF(AND(OR(OR(C5="Квартира",C5="Апартаменты"),OR(C5="Дом",C5="Вилла")),OR(R5="",R5>YEAR(TODAY()))),"Год постройки",""),IF(AND(P5<>"",Q5<>"",P5>Q5),"Этаж больше этажности",""),IF(AND(OR(C5="Квартира",C5="Апартаменты",C5="Дом",C5="Вилла"),S5=""),"Материал",""),IF(AND(OR(C5="Коммерческая"),U5=""),"Тип коммерции",""),IF(AND(OR(C5="Земля"),V5=""),"Назначение земли",""),IF(OR(X5="",X5<=0),"Минимальная цена продажи",""),IF(OR(Y5="",Y5<=0),"Стартовая ставка",""),IF(Z5="","Начало аукциона",""),IF(AA5="","Окончание аукциона",""),IF(AND(W5<>"",X5<>"",X5>W5),"Минимальная цена выше «Продать сейчас»",""),IF(AND(W5<>"",X5<>"",X5<=W5,X5>W5*0.9),"Минимальная цена выше 90% от «Продать сейчас»",""),IF(AND(W5<>"",Y5<>"",Y5>W5*0.3),"Стартовая ставка выше 30% от «Продать сейчас»",""),IF(AND(Z5<>"",AA5<>"",AA5<EDATE(Z5,3)+15),"Аукцион короче 3 месяцев и 15 дней",""),IF(AND(AB5="Да",OR(AC5="",AC5<=0)),"Цена тест-драйва за сутки",""),IF(OR(AJ5="",AJ5="Нет"),"Право собственности",""),IF(OR(AK5="",AK5="Нет"),"Справка об отсутствии обременений","")))) | AN5: =IF(NOT(COUNTA(A5:AL5)>0),"",IF(TEXTJOIN(", ",TRUE,IF(AH5="","Описание",""),IF(AND(AE5<>"",AE5>=1,AE5<5),"Фото меньше 5",""),IF(AG5="","Видео",""),IF(H5="","Кадастровый номер",""),IF(AF5="","Ссылка на фото",""))="","",TEXTJOIN(", ",TRUE,IF(AH5="","Описание",""),IF(AND(AE5<>"",AE5>=1,AE5<5),"Фото меньше 5",""),IF(AG5="","Видео",""),IF(H5="","Кадастровый номер",""),IF(AF5="","Ссылка на фото","")))) | AO5: =IF(NOT(COUNTA(A5:AL5)>0),"",IF(AM5="","Можно публиковать","Не хватает"))
AM6: =IF(NOT(COUNTA(A6:AL6)>0),"",IF(TEXTJOIN(", ",TRUE,IF(B6="","Название",""),IF(C6="","Тип недвижимости",""),IF(D6="","Страна",""),IF(E6="","Город",""),IF(F6="","Улица",""),IF(I6="","Валюта",""),IF(OR(AE6="",AE6<1),"Хотя бы 1 фото",""),IF(AND(OR(C6="Квартира",C6="Апартаменты",C6="Дом",C6="Вилла",C6="Коммерческая"),J6=""),"Площадь",""),IF(AND(OR(C6="Квартира",C6="Апартаменты"),K6=""),"Жилая площадь",""),IF(AND(OR(C6="Дом",C6="Вилла",C6="Земля"),L6=""),"Площадь участка",""),IF(AND(OR(C6="Квартира",C6="Апартаменты"),M6=""),"Комнаты",""),IF(AND(OR(C6="Дом",C6="Вилла"),N6=""),"Спальни",""),IF(AND(OR(C6="Квартира",C6="Апартаменты",C6="Дом",C6="Вилла"),O6=""),"Ванные",""),IF(AND(OR(C6="Квартира",C6="Апартаменты"),P6=""),"Этаж",""),IF(AND(OR(OR(C6="Квартира",C6="Апартаменты"),OR(C6="Дом",C6="Вилла")),Q6=""),"Этажей",""),IF(AND(OR(OR(C6="Квартира",C6="Апартаменты"),OR(C6="Дом",C6="Вилла")),OR(R6="",R6>YEAR(TODAY()))),"Год постройки",""),IF(AND(P6<>"",Q6<>"",P6>Q6),"Этаж больше этажности",""),IF(AND(OR(C6="Квартира",C6="Апартаменты",C6="Дом",C6="Вилла"),S6=""),"Материал",""),IF(AND(OR(C6="Коммерческая"),U6=""),"Тип коммерции",""),IF(AND(OR(C6="Земля"),V6=""),"Назначение земли",""),IF(OR(X6="",X6<=0),"Минимальная цена продажи",""),IF(OR(Y6="",Y6<=0),"Стартовая ставка",""),IF(Z6="","Начало аукциона",""),IF(AA6="","Окончание аукциона",""),IF(AND(W6<>"",X6<>"",X6>W6),"Минимальная цена выше «Продать сейчас»",""),IF(AND(W6<>"",X6<>"",X6<=W6,X6>W6*0.9),"Минимальная цена выше 90% от «Продать сейчас»",""),IF(AND(W6<>"",Y6<>"",Y6>W6*0.3),"Стартовая ставка выше 30% от «Продать сейчас»",""),IF(AND(Z6<>"",AA6<>"",AA6<EDATE(Z6,3)+15),"Аукцион короче 3 месяцев и 15 дней",""),IF(AND(AB6="Да",OR(AC6="",AC6<=0)),"Цена тест-драйва за сутки",""),IF(OR(AJ6="",AJ6="Нет"),"Право собственности",""),IF(OR(AK6="",AK6="Нет"),"Справка об отсутствии обременений",""))="","",TEXTJOIN(", ",TRUE,IF(B6="","Название",""),IF(C6="","Тип недвижимости",""),IF(D6="","Страна",""),IF(E6="","Город",""),IF(F6="","Улица",""),IF(I6="","Валюта",""),IF(OR(AE6="",AE6<1),"Хотя бы 1 фото",""),IF(AND(OR(C6="Квартира",C6="Апартаменты",C6="Дом",C6="Вилла",C6="Коммерческая"),J6=""),"Площадь",""),IF(AND(OR(C6="Квартира",C6="Апартаменты"),K6=""),"Жилая площадь",""),IF(AND(OR(C6="Дом",C6="Вилла",C6="Земля"),L6=""),"Площадь участка",""),IF(AND(OR(C6="Квартира",C6="Апартаменты"),M6=""),"Комнаты",""),IF(AND(OR(C6="Дом",C6="Вилла"),N6=""),"Спальни",""),IF(AND(OR(C6="Квартира",C6="Апартаменты",C6="Дом",C6="Вилла"),O6=""),"Ванные",""),IF(AND(OR(C6="Квартира",C6="Апартаменты"),P6=""),"Этаж",""),IF(AND(OR(OR(C6="Квартира",C6="Апартаменты"),OR(C6="Дом",C6="Вилла")),Q6=""),"Этажей",""),IF(AND(OR(OR(C6="Квартира",C6="Апартаменты"),OR(C6="Дом",C6="Вилла")),OR(R6="",R6>YEAR(TODAY()))),"Год постройки",""),IF(AND(P6<>"",Q6<>"",P6>Q6),"Этаж больше этажности",""),IF(AND(OR(C6="Квартира",C6="Апартаменты",C6="Дом",C6="Вилла"),S6=""),"Материал",""),IF(AND(OR(C6="Коммерческая"),U6=""),"Тип коммерции",""),IF(AND(OR(C6="Земля"),V6=""),"Назначение земли",""),IF(OR(X6="",X6<=0),"Минимальная цена продажи",""),IF(OR(Y6="",Y6<=0),"Стартовая ставка",""),IF(Z6="","Начало аукциона",""),IF(AA6="","Окончание аукциона",""),IF(AND(W6<>"",X6<>"",X6>W6),"Минимальная цена выше «Продать сейчас»",""),IF(AND(W6<>"",X6<>"",X6<=W6,X6>W6*0.9),"Минимальная цена выше 90% от «Продать сейчас»",""),IF(AND(W6<>"",Y6<>"",Y6>W6*0.3),"Стартовая ставка выше 30% от «Продать сейчас»",""),IF(AND(Z6<>"",AA6<>"",AA6<EDATE(Z6,3)+15),"Аукцион короче 3 месяцев и 15 дней",""),IF(AND(AB6="Да",OR(AC6="",AC6<=0)),"Цена тест-драйва за сутки",""),IF(OR(AJ6="",AJ6="Нет"),"Право собственности",""),IF(OR(AK6="",AK6="Нет"),"Справка об отсутствии обременений","")))) | AN6: =IF(NOT(COUNTA(A6:AL6)>0),"",IF(TEXTJOIN(", ",TRUE,IF(AH6="","Описание",""),IF(AND(AE6<>"",AE6>=1,AE6<5),"Фото меньше 5",""),IF(AG6="","Видео",""),IF(H6="","Кадастровый номер",""),IF(AF6="","Ссылка на фото",""))="","",TEXTJOIN(", ",TRUE,IF(AH6="","Описание",""),IF(AND(AE6<>"",AE6>=1,AE6<5),"Фото меньше 5",""),IF(AG6="","Видео",""),IF(H6="","Кадастровый номер",""),IF(AF6="","Ссылка на фото","")))) | AO6: =IF(NOT(COUNTA(A6:AL6)>0),"",IF(AM6="","Можно публиковать","Не хватает"))
AM7: =IF(NOT(COUNTA(A7:AL7)>0),"",IF(TEXTJOIN(", ",TRUE,IF(B7="","Название",""),IF(C7="","Тип недвижимости",""),IF(D7="","Страна",""),IF(E7="","Город",""),IF(F7="","Улица",""),IF(I7="","Валюта",""),IF(OR(AE7="",AE7<1),"Хотя бы 1 фото",""),IF(AND(OR(C7="Квартира",C7="Апартаменты",C7="Дом",C7="Вилла",C7="Коммерческая"),J7=""),"Площадь",""),IF(AND(OR(C7="Квартира",C7="Апартаменты"),K7=""),"Жилая площадь",""),IF(AND(OR(C7="Дом",C7="Вилла",C7="Земля"),L7=""),"Площадь участка",""),IF(AND(OR(C7="Квартира",C7="Апартаменты"),M7=""),"Комнаты",""),IF(AND(OR(C7="Дом",C7="Вилла"),N7=""),"Спальни",""),IF(AND(OR(C7="Квартира",C7="Апартаменты",C7="Дом",C7="Вилла"),O7=""),"Ванные",""),IF(AND(OR(C7="Квартира",C7="Апартаменты"),P7=""),"Этаж",""),IF(AND(OR(OR(C7="Квартира",C7="Апартаменты"),OR(C7="Дом",C7="Вилла")),Q7=""),"Этажей",""),IF(AND(OR(OR(C7="Квартира",C7="Апартаменты"),OR(C7="Дом",C7="Вилла")),OR(R7="",R7>YEAR(TODAY()))),"Год постройки",""),IF(AND(P7<>"",Q7<>"",P7>Q7),"Этаж больше этажности",""),IF(AND(OR(C7="Квартира",C7="Апартаменты",C7="Дом",C7="Вилла"),S7=""),"Материал",""),IF(AND(OR(C7="Коммерческая"),U7=""),"Тип коммерции",""),IF(AND(OR(C7="Земля"),V7=""),"Назначение земли",""),IF(OR(X7="",X7<=0),"Минимальная цена продажи",""),IF(OR(Y7="",Y7<=0),"Стартовая ставка",""),IF(Z7="","Начало аукциона",""),IF(AA7="","Окончание аукциона",""),IF(AND(W7<>"",X7<>"",X7>W7),"Минимальная цена выше «Продать сейчас»",""),IF(AND(W7<>"",X7<>"",X7<=W7,X7>W7*0.9),"Минимальная цена выше 90% от «Продать сейчас»",""),IF(AND(W7<>"",Y7<>"",Y7>W7*0.3),"Стартовая ставка выше 30% от «Продать сейчас»",""),IF(AND(Z7<>"",AA7<>"",AA7<EDATE(Z7,3)+15),"Аукцион короче 3 месяцев и 15 дней",""),IF(AND(AB7="Да",OR(AC7="",AC7<=0)),"Цена тест-драйва за сутки",""),IF(OR(AJ7="",AJ7="Нет"),"Право собственности",""),IF(OR(AK7="",AK7="Нет"),"Справка об отсутствии обременений",""))="","",TEXTJOIN(", ",TRUE,IF(B7="","Название",""),IF(C7="","Тип недвижимости",""),IF(D7="","Страна",""),IF(E7="","Город",""),IF(F7="","Улица",""),IF(I7="","Валюта",""),IF(OR(AE7="",AE7<1),"Хотя бы 1 фото",""),IF(AND(OR(C7="Квартира",C7="Апартаменты",C7="Дом",C7="Вилла",C7="Коммерческая"),J7=""),"Площадь",""),IF(AND(OR(C7="Квартира",C7="Апартаменты"),K7=""),"Жилая площадь",""),IF(AND(OR(C7="Дом",C7="Вилла",C7="Земля"),L7=""),"Площадь участка",""),IF(AND(OR(C7="Квартира",C7="Апартаменты"),M7=""),"Комнаты",""),IF(AND(OR(C7="Дом",C7="Вилла"),N7=""),"Спальни",""),IF(AND(OR(C7="Квартира",C7="Апартаменты",C7="Дом",C7="Вилла"),O7=""),"Ванные",""),IF(AND(OR(C7="Квартира",C7="Апартаменты"),P7=""),"Этаж",""),IF(AND(OR(OR(C7="Квартира",C7="Апартаменты"),OR(C7="Дом",C7="Вилла")),Q7=""),"Этажей",""),IF(AND(OR(OR(C7="Квартира",C7="Апартаменты"),OR(C7="Дом",C7="Вилла")),OR(R7="",R7>YEAR(TODAY()))),"Год постройки",""),IF(AND(P7<>"",Q7<>"",P7>Q7),"Этаж больше этажности",""),IF(AND(OR(C7="Квартира",C7="Апартаменты",C7="Дом",C7="Вилла"),S7=""),"Материал",""),IF(AND(OR(C7="Коммерческая"),U7=""),"Тип коммерции",""),IF(AND(OR(C7="Земля"),V7=""),"Назначение земли",""),IF(OR(X7="",X7<=0),"Минимальная цена продажи",""),IF(OR(Y7="",Y7<=0),"Стартовая ставка",""),IF(Z7="","Начало аукциона",""),IF(AA7="","Окончание аукциона",""),IF(AND(W7<>"",X7<>"",X7>W7),"Минимальная цена выше «Продать сейчас»",""),IF(AND(W7<>"",X7<>"",X7<=W7,X7>W7*0.9),"Минимальная цена выше 90% от «Продать сейчас»",""),IF(AND(W7<>"",Y7<>"",Y7>W7*0.3),"Стартовая ставка выше 30% от «Продать сейчас»",""),IF(AND(Z7<>"",AA7<>"",AA7<EDATE(Z7,3)+15),"Аукцион короче 3 месяцев и 15 дней",""),IF(AND(AB7="Да",OR(AC7="",AC7<=0)),"Цена тест-драйва за сутки",""),IF(OR(AJ7="",AJ7="Нет"),"Право собственности",""),IF(OR(AK7="",AK7="Нет"),"Справка об отсутствии обременений","")))) | AN7: =IF(NOT(COUNTA(A7:AL7)>0),"",IF(TEXTJOIN(", ",TRUE,IF(AH7="","Описание",""),IF(AND(AE7<>"",AE7>=1,AE7<5),"Фото меньше 5",""),IF(AG7="","Видео",""),IF(H7="","Кадастровый номер",""),IF(AF7="","Ссылка на фото",""))="","",TEXTJOIN(", ",TRUE,IF(AH7="","Описание",""),IF(AND(AE7<>"",AE7>=1,AE7<5),"Фото меньше 5",""),IF(AG7="","Видео",""),IF(H7="","Кадастровый номер",""),IF(AF7="","Ссылка на фото","")))) | AO7: =IF(NOT(COUNTA(A7:AL7)>0),"",IF(AM7="","Можно публиковать","Не хватает"))
AM8: =IF(NOT(COUNTA(A8:AL8)>0),"",IF(TEXTJOIN(", ",TRUE,IF(B8="","Название",""),IF(C8="","Тип недвижимости",""),IF(D8="","Страна",""),IF(E8="","Город",""),IF(F8="","Улица",""),IF(I8="","Валюта",""),IF(OR(AE8="",AE8<1),"Хотя бы 1 фото",""),IF(AND(OR(C8="Квартира",C8="Апартаменты",C8="Дом",C8="Вилла",C8="Коммерческая"),J8=""),"Площадь",""),IF(AND(OR(C8="Квартира",C8="Апартаменты"),K8=""),"Жилая площадь",""),IF(AND(OR(C8="Дом",C8="Вилла",C8="Земля"),L8=""),"Площадь участка",""),IF(AND(OR(C8="Квартира",C8="Апартаменты"),M8=""),"Комнаты",""),IF(AND(OR(C8="Дом",C8="Вилла"),N8=""),"Спальни",""),IF(AND(OR(C8="Квартира",C8="Апартаменты",C8="Дом",C8="Вилла"),O8=""),"Ванные",""),IF(AND(OR(C8="Квартира",C8="Апартаменты"),P8=""),"Этаж",""),IF(AND(OR(OR(C8="Квартира",C8="Апартаменты"),OR(C8="Дом",C8="Вилла")),Q8=""),"Этажей",""),IF(AND(OR(OR(C8="Квартира",C8="Апартаменты"),OR(C8="Дом",C8="Вилла")),OR(R8="",R8>YEAR(TODAY()))),"Год постройки",""),IF(AND(P8<>"",Q8<>"",P8>Q8),"Этаж больше этажности",""),IF(AND(OR(C8="Квартира",C8="Апартаменты",C8="Дом",C8="Вилла"),S8=""),"Материал",""),IF(AND(OR(C8="Коммерческая"),U8=""),"Тип коммерции",""),IF(AND(OR(C8="Земля"),V8=""),"Назначение земли",""),IF(OR(X8="",X8<=0),"Минимальная цена продажи",""),IF(OR(Y8="",Y8<=0),"Стартовая ставка",""),IF(Z8="","Начало аукциона",""),IF(AA8="","Окончание аукциона",""),IF(AND(W8<>"",X8<>"",X8>W8),"Минимальная цена выше «Продать сейчас»",""),IF(AND(W8<>"",X8<>"",X8<=W8,X8>W8*0.9),"Минимальная цена выше 90% от «Продать сейчас»",""),IF(AND(W8<>"",Y8<>"",Y8>W8*0.3),"Стартовая ставка выше 30% от «Продать сейчас»",""),IF(AND(Z8<>"",AA8<>"",AA8<EDATE(Z8,3)+15),"Аукцион короче 3 месяцев и 15 дней",""),IF(AND(AB8="Да",OR(AC8="",AC8<=0)),"Цена тест-драйва за сутки",""),IF(OR(AJ8="",AJ8="Нет"),"Право собственности",""),IF(OR(AK8="",AK8="Нет"),"Справка об отсутствии обременений",""))="","",TEXTJOIN(", ",TRUE,IF(B8="","Название",""),IF(C8="","Тип недвижимости",""),IF(D8="","Страна",""),IF(E8="","Город",""),IF(F8="","Улица",""),IF(I8="","Валюта",""),IF(OR(AE8="",AE8<1),"Хотя бы 1 фото",""),IF(AND(OR(C8="Квартира",C8="Апартаменты",C8="Дом",C8="Вилла",C8="Коммерческая"),J8=""),"Площадь",""),IF(AND(OR(C8="Квартира",C8="Апартаменты"),K8=""),"Жилая площадь",""),IF(AND(OR(C8="Дом",C8="Вилла",C8="Земля"),L8=""),"Площадь участка",""),IF(AND(OR(C8="Квартира",C8="Апартаменты"),M8=""),"Комнаты",""),IF(AND(OR(C8="Дом",C8="Вилла"),N8=""),"Спальни",""),IF(AND(OR(C8="Квартира",C8="Апартаменты",C8="Дом",C8="Вилла"),O8=""),"Ванные",""),IF(AND(OR(C8="Квартира",C8="Апартаменты"),P8=""),"Этаж",""),IF(AND(OR(OR(C8="Квартира",C8="Апартаменты"),OR(C8="Дом",C8="Вилла")),Q8=""),"Этажей",""),IF(AND(OR(OR(C8="Квартира",C8="Апартаменты"),OR(C8="Дом",C8="Вилла")),OR(R8="",R8>YEAR(TODAY()))),"Год постройки",""),IF(AND(P8<>"",Q8<>"",P8>Q8),"Этаж больше этажности",""),IF(AND(OR(C8="Квартира",C8="Апартаменты",C8="Дом",C8="Вилла"),S8=""),"Материал",""),IF(AND(OR(C8="Коммерческая"),U8=""),"Тип коммерции",""),IF(AND(OR(C8="Земля"),V8=""),"Назначение земли",""),IF(OR(X8="",X8<=0),"Минимальная цена продажи",""),IF(OR(Y8="",Y8<=0),"Стартовая ставка",""),IF(Z8="","Начало аукциона",""),IF(AA8="","Окончание аукциона",""),IF(AND(W8<>"",X8<>"",X8>W8),"Минимальная цена выше «Продать сейчас»",""),IF(AND(W8<>"",X8<>"",X8<=W8,X8>W8*0.9),"Минимальная цена выше 90% от «Продать сейчас»",""),IF(AND(W8<>"",Y8<>"",Y8>W8*0.3),"Стартовая ставка выше 30% от «Продать сейчас»",""),IF(AND(Z8<>"",AA8<>"",AA8<EDATE(Z8,3)+15),"Аукцион короче 3 месяцев и 15 дней",""),IF(AND(AB8="Да",OR(AC8="",AC8<=0)),"Цена тест-драйва за сутки",""),IF(OR(AJ8="",AJ8="Нет"),"Право собственности",""),IF(OR(AK8="",AK8="Нет"),"Справка об отсутствии обременений","")))) | AN8: =IF(NOT(COUNTA(A8:AL8)>0),"",IF(TEXTJOIN(", ",TRUE,IF(AH8="","Описание",""),IF(AND(AE8<>"",AE8>=1,AE8<5),"Фото меньше 5",""),IF(AG8="","Видео",""),IF(H8="","Кадастровый номер",""),IF(AF8="","Ссылка на фото",""))="","",TEXTJOIN(", ",TRUE,IF(AH8="","Описание",""),IF(AND(AE8<>"",AE8>=1,AE8<5),"Фото меньше 5",""),IF(AG8="","Видео",""),IF(H8="","Кадастровый номер",""),IF(AF8="","Ссылка на фото","")))) | AO8: =IF(NOT(COUNTA(A8:AL8)>0),"",IF(AM8="","Можно публиковать","Не хватает"))
AM9: =IF(NOT(COUNTA(A9:AL9)>0),"",IF(TEXTJOIN(", ",TRUE,IF(B9="","Название",""),IF(C9="","Тип недвижимости",""),IF(D9="","Страна",""),IF(E9="","Город",""),IF(F9="","Улица",""),IF(I9="","Валюта",""),IF(OR(AE9="",AE9<1),"Хотя бы 1 фото",""),IF(AND(OR(C9="Квартира",C9="Апартаменты",C9="Дом",C9="Вилла",C9="Коммерческая"),J9=""),"Площадь",""),IF(AND(OR(C9="Квартира",C9="Апартаменты"),K9=""),"Жилая площадь",""),IF(AND(OR(C9="Дом",C9="Вилла",C9="Земля"),L9=""),"Площадь участка",""),IF(AND(OR(C9="Квартира",C9="Апартаменты"),M9=""),"Комнаты",""),IF(AND(OR(C9="Дом",C9="Вилла"),N9=""),"Спальни",""),IF(AND(OR(C9="Квартира",C9="Апартаменты",C9="Дом",C9="Вилла"),O9=""),"Ванные",""),IF(AND(OR(C9="Квартира",C9="Апартаменты"),P9=""),"Этаж",""),IF(AND(OR(OR(C9="Квартира",C9="Апартаменты"),OR(C9="Дом",C9="Вилла")),Q9=""),"Этажей",""),IF(AND(OR(OR(C9="Квартира",C9="Апартаменты"),OR(C9="Дом",C9="Вилла")),OR(R9="",R9>YEAR(TODAY()))),"Год постройки",""),IF(AND(P9<>"",Q9<>"",P9>Q9),"Этаж больше этажности",""),IF(AND(OR(C9="Квартира",C9="Апартаменты",C9="Дом",C9="Вилла"),S9=""),"Материал",""),IF(AND(OR(C9="Коммерческая"),U9=""),"Тип коммерции",""),IF(AND(OR(C9="Земля"),V9=""),"Назначение земли",""),IF(OR(X9="",X9<=0),"Минимальная цена продажи",""),IF(OR(Y9="",Y9<=0),"Стартовая ставка",""),IF(Z9="","Начало аукциона",""),IF(AA9="","Окончание аукциона",""),IF(AND(W9<>"",X9<>"",X9>W9),"Минимальная цена выше «Продать сейчас»",""),IF(AND(W9<>"",X9<>"",X9<=W9,X9>W9*0.9),"Минимальная цена выше 90% от «Продать сейчас»",""),IF(AND(W9<>"",Y9<>"",Y9>W9*0.3),"Стартовая ставка выше 30% от «Продать сейчас»",""),IF(AND(Z9<>"",AA9<>"",AA9<EDATE(Z9,3)+15),"Аукцион короче 3 месяцев и 15 дней",""),IF(AND(AB9="Да",OR(AC9="",AC9<=0)),"Цена тест-драйва за сутки",""),IF(OR(AJ9="",AJ9="Нет"),"Право собственности",""),IF(OR(AK9="",AK9="Нет"),"Справка об отсутствии обременений",""))="","",TEXTJOIN(", ",TRUE,IF(B9="","Название",""),IF(C9="","Тип недвижимости",""),IF(D9="","Страна",""),IF(E9="","Город",""),IF(F9="","Улица",""),IF(I9="","Валюта",""),IF(OR(AE9="",AE9<1),"Хотя бы 1 фото",""),IF(AND(OR(C9="Квартира",C9="Апартаменты",C9="Дом",C9="Вилла",C9="Коммерческая"),J9=""),"Площадь",""),IF(AND(OR(C9="Квартира",C9="Апартаменты"),K9=""),"Жилая площадь",""),IF(AND(OR(C9="Дом",C9="Вилла",C9="Земля"),L9=""),"Площадь участка",""),IF(AND(OR(C9="Квартира",C9="Апартаменты"),M9=""),"Комнаты",""),IF(AND(OR(C9="Дом",C9="Вилла"),N9=""),"Спальни",""),IF(AND(OR(C9="Квартира",C9="Апартаменты",C9="Дом",C9="Вилла"),O9=""),"Ванные",""),IF(AND(OR(C9="Квартира",C9="Апартаменты"),P9=""),"Этаж",""),IF(AND(OR(OR(C9="Квартира",C9="Апартаменты"),OR(C9="Дом",C9="Вилла")),Q9=""),"Этажей",""),IF(AND(OR(OR(C9="Квартира",C9="Апартаменты"),OR(C9="Дом",C9="Вилла")),OR(R9="",R9>YEAR(TODAY()))),"Год постройки",""),IF(AND(P9<>"",Q9<>"",P9>Q9),"Этаж больше этажности",""),IF(AND(OR(C9="Квартира",C9="Апартаменты",C9="Дом",C9="Вилла"),S9=""),"Материал",""),IF(AND(OR(C9="Коммерческая"),U9=""),"Тип коммерции",""),IF(AND(OR(C9="Земля"),V9=""),"Назначение земли",""),IF(OR(X9="",X9<=0),"Минимальная цена продажи",""),IF(OR(Y9="",Y9<=0),"Стартовая ставка",""),IF(Z9="","Начало аукциона",""),IF(AA9="","Окончание аукциона",""),IF(AND(W9<>"",X9<>"",X9>W9),"Минимальная цена выше «Продать сейчас»",""),IF(AND(W9<>"",X9<>"",X9<=W9,X9>W9*0.9),"Минимальная цена выше 90% от «Продать сейчас»",""),IF(AND(W9<>"",Y9<>"",Y9>W9*0.3),"Стартовая ставка выше 30% от «Продать сейчас»",""),IF(AND(Z9<>"",AA9<>"",AA9<EDATE(Z9,3)+15),"Аукцион короче 3 месяцев и 15 дней",""),IF(AND(AB9="Да",OR(AC9="",AC9<=0)),"Цена тест-драйва за сутки",""),IF(OR(AJ9="",AJ9="Нет"),"Право собственности",""),IF(OR(AK9="",AK9="Нет"),"Справка об отсутствии обременений","")))) | AN9: =IF(NOT(COUNTA(A9:AL9)>0),"",IF(TEXTJOIN(", ",TRUE,IF(AH9="","Описание",""),IF(AND(AE9<>"",AE9>=1,AE9<5),"Фото меньше 5",""),IF(AG9="","Видео",""),IF(H9="","Кадастровый номер",""),IF(AF9="","Ссылка на фото",""))="","",TEXTJOIN(", ",TRUE,IF(AH9="","Описание",""),IF(AND(AE9<>"",AE9>=1,AE9<5),"Фото меньше 5",""),IF(AG9="","Видео",""),IF(H9="","Кадастровый номер",""),IF(AF9="","Ссылка на фото","")))) | AO9: =IF(NOT(COUNTA(A9:AL9)>0),"",IF(AM9="","Можно публиковать","Не хватает"))
AM10: =IF(NOT(COUNTA(A10:AL10)>0),"",IF(TEXTJOIN(", ",TRUE,IF(B10="","Название",""),IF(C10="","Тип недвижимости",""),IF(D10="","Страна",""),IF(E10="","Город",""),IF(F10="","Улица",""),IF(I10="","Валюта",""),IF(OR(AE10="",AE10<1),"Хотя бы 1 фото",""),IF(AND(OR(C10="Квартира",C10="Апартаменты",C10="Дом",C10="Вилла",C10="Коммерческая"),J10=""),"Площадь",""),IF(AND(OR(C10="Квартира",C10="Апартаменты"),K10=""),"Жилая площадь",""),IF(AND(OR(C10="Дом",C10="Вилла",C10="Земля"),L10=""),"Площадь участка",""),IF(AND(OR(C10="Квартира",C10="Апартаменты"),M10=""),"Комнаты",""),IF(AND(OR(C10="Дом",C10="Вилла"),N10=""),"Спальни",""),IF(AND(OR(C10="Квартира",C10="Апартаменты",C10="Дом",C10="Вилла"),O10=""),"Ванные",""),IF(AND(OR(C10="Квартира",C10="Апартаменты"),P10=""),"Этаж",""),IF(AND(OR(OR(C10="Квартира",C10="Апартаменты"),OR(C10="Дом",C10="Вилла")),Q10=""),"Этажей",""),IF(AND(OR(OR(C10="Квартира",C10="Апартаменты"),OR(C10="Дом",C10="Вилла")),OR(R10="",R10>YEAR(TODAY()))),"Год постройки",""),IF(AND(P10<>"",Q10<>"",P10>Q10),"Этаж больше этажности",""),IF(AND(OR(C10="Квартира",C10="Апартаменты",C10="Дом",C10="Вилла"),S10=""),"Материал",""),IF(AND(OR(C10="Коммерческая"),U10=""),"Тип коммерции",""),IF(AND(OR(C10="Земля"),V10=""),"Назначение земли",""),IF(OR(X10="",X10<=0),"Минимальная цена продажи",""),IF(OR(Y10="",Y10<=0),"Стартовая ставка",""),IF(Z10="","Начало аукциона",""),IF(AA10="","Окончание аукциона",""),IF(AND(W10<>"",X10<>"",X10>W10),"Минимальная цена выше «Продать сейчас»",""),IF(AND(W10<>"",X10<>"",X10<=W10,X10>W10*0.9),"Минимальная цена выше 90% от «Продать сейчас»",""),IF(AND(W10<>"",Y10<>"",Y10>W10*0.3),"Стартовая ставка выше 30% от «Продать сейчас»",""),IF(AND(Z10<>"",AA10<>"",AA10<EDATE(Z10,3)+15),"Аукцион короче 3 месяцев и 15 дней",""),IF(AND(AB10="Да",OR(AC10="",AC10<=0)),"Цена тест-драйва за сутки",""),IF(OR(AJ10="",AJ10="Нет"),"Право собственности",""),IF(OR(AK10="",AK10="Нет"),"Справка об отсутствии обременений",""))="","",TEXTJOIN(", ",TRUE,IF(B10="","Название",""),IF(C10="","Тип недвижимости",""),IF(D10="","Страна",""),IF(E10="","Город",""),IF(F10="","Улица",""),IF(I10="","Валюта",""),IF(OR(AE10="",AE10<1),"Хотя бы 1 фото",""),IF(AND(OR(C10="Квартира",C10="Апартаменты",C10="Дом",C10="Вилла",C10="Коммерческая"),J10=""),"Площадь",""),IF(AND(OR(C10="Квартира",C10="Апартаменты"),K10=""),"Жилая площадь",""),IF(AND(OR(C10="Дом",C10="Вилла",C10="Земля"),L10=""),"Площадь участка",""),IF(AND(OR(C10="Квартира",C10="Апартаменты"),M10=""),"Комнаты",""),IF(AND(OR(C10="Дом",C10="Вилла"),N10=""),"Спальни",""),IF(AND(OR(C10="Квартира",C10="Апартаменты",C10="Дом",C10="Вилла"),O10=""),"Ванные",""),IF(AND(OR(C10="Квартира",C10="Апартаменты"),P10=""),"Этаж",""),IF(AND(OR(OR(C10="Квартира",C10="Апартаменты"),OR(C10="Дом",C10="Вилла")),Q10=""),"Этажей",""),IF(AND(OR(OR(C10="Квартира",C10="Апартаменты"),OR(C10="Дом",C10="Вилла")),OR(R10="",R10>YEAR(TODAY()))),"Год постройки",""),IF(AND(P10<>"",Q10<>"",P10>Q10),"Этаж больше этажности",""),IF(AND(OR(C10="Квартира",C10="Апартаменты",C10="Дом",C10="Вилла"),S10=""),"Материал",""),IF(AND(OR(C10="Коммерческая"),U10=""),"Тип коммерции",""),IF(AND(OR(C10="Земля"),V10=""),"Назначение земли",""),IF(OR(X10="",X10<=0),"Минимальная цена продажи",""),IF(OR(Y10="",Y10<=0),"Стартовая ставка",""),IF(Z10="","Начало аукциона",""),IF(AA10="","Окончание аукциона",""),IF(AND(W10<>"",X10<>"",X10>W10),"Минимальная цена выше «Продать сейчас»",""),IF(AND(W10<>"",X10<>"",X10<=W10,X10>W10*0.9),"Минимальная цена выше 90% от «Продать сейчас»",""),IF(AND(W10<>"",Y10<>"",Y10>W10*0.3),"Стартовая ставка выше 30% от «Продать сейчас»",""),IF(AND(Z10<>"",AA10<>"",AA10<EDATE(Z10,3)+15),"Аукцион короче 3 месяцев и 15 дней",""),IF(AND(AB10="Да",OR(AC10="",AC10<=0)),"Цена тест-драйва за сутки",""),IF(OR(AJ10="",AJ10="Нет"),"Право собственности",""),IF(OR(AK10="",AK10="Нет"),"Справка об отсутствии обременений","")))) | AN10: =IF(NOT(COUNTA(A10:AL10)>0),"",IF(TEXTJOIN(", ",TRUE,IF(AH10="","Описание",""),IF(AND(AE10<>"",AE10>=1,AE10<5),"Фото меньше 5",""),IF(AG10="","Видео",""),IF(H10="","Кадастровый номер",""),IF(AF10="","Ссылка на фото",""))="","",TEXTJOIN(", ",TRUE,IF(AH10="","Описание",""),IF(AND(AE10<>"",AE10>=1,AE10<5),"Фото меньше 5",""),IF(AG10="","Видео",""),IF(H10="","Кадастровый номер",""),IF(AF10="","Ссылка на фото","")))) | AO10: =IF(NOT(COUNTA(A10:AL10)>0),"",IF(AM10="","Можно публиковать","Не хватает"))
AM11: =IF(NOT(COUNTA(A11:AL11)>0),"",IF(TEXTJOIN(", ",TRUE,IF(B11="","Название",""),IF(C11="","Тип недвижимости",""),IF(D11="","Страна",""),IF(E11="","Город",""),IF(F11="","Улица",""),IF(I11="","Валюта",""),IF(OR(AE11="",AE11<1),"Хотя бы 1 фото",""),IF(AND(OR(C11="Квартира",C11="Апартаменты",C11="Дом",C11="Вилла",C11="Коммерческая"),J11=""),"Площадь",""),IF(AND(OR(C11="Квартира",C11="Апартаменты"),K11=""),"Жилая площадь",""),IF(AND(OR(C11="Дом",C11="Вилла",C11="Земля"),L11=""),"Площадь участка",""),IF(AND(OR(C11="Квартира",C11="Апартаменты"),M11=""),"Комнаты",""),IF(AND(OR(C11="Дом",C11="Вилла"),N11=""),"Спальни",""),IF(AND(OR(C11="Квартира",C11="Апартаменты",C11="Дом",C11="Вилла"),O11=""),"Ванные",""),IF(AND(OR(C11="Квартира",C11="Апартаменты"),P11=""),"Этаж",""),IF(AND(OR(OR(C11="Квартира",C11="Апартаменты"),OR(C11="Дом",C11="Вилла")),Q11=""),"Этажей",""),IF(AND(OR(OR(C11="Квартира",C11="Апартаменты"),OR(C11="Дом",C11="Вилла")),OR(R11="",R11>YEAR(TODAY()))),"Год постройки",""),IF(AND(P11<>"",Q11<>"",P11>Q11),"Этаж больше этажности",""),IF(AND(OR(C11="Квартира",C11="Апартаменты",C11="Дом",C11="Вилла"),S11=""),"Материал",""),IF(AND(OR(C11="Коммерческая"),U11=""),"Тип коммерции",""),IF(AND(OR(C11="Земля"),V11=""),"Назначение земли",""),IF(OR(X11="",X11<=0),"Минимальная цена продажи",""),IF(OR(Y11="",Y11<=0),"Стартовая ставка",""),IF(Z11="","Начало аукциона",""),IF(AA11="","Окончание аукциона",""),IF(AND(W11<>"",X11<>"",X11>W11),"Минимальная цена выше «Продать сейчас»",""),IF(AND(W11<>"",X11<>"",X11<=W11,X11>W11*0.9),"Минимальная цена выше 90% от «Продать сейчас»",""),IF(AND(W11<>"",Y11<>"",Y11>W11*0.3),"Стартовая ставка выше 30% от «Продать сейчас»",""),IF(AND(Z11<>"",AA11<>"",AA11<EDATE(Z11,3)+15),"Аукцион короче 3 месяцев и 15 дней",""),IF(AND(AB11="Да",OR(AC11="",AC11<=0)),"Цена тест-драйва за сутки",""),IF(OR(AJ11="",AJ11="Нет"),"Право собственности",""),IF(OR(AK11="",AK11="Нет"),"Справка об отсутствии обременений",""))="","",TEXTJOIN(", ",TRUE,IF(B11="","Название",""),IF(C11="","Тип недвижимости",""),IF(D11="","Страна",""),IF(E11="","Город",""),IF(F11="","Улица",""),IF(I11="","Валюта",""),IF(OR(AE11="",AE11<1),"Хотя бы 1 фото",""),IF(AND(OR(C11="Квартира",C11="Апартаменты",C11="Дом",C11="Вилла",C11="Коммерческая"),J11=""),"Площадь",""),IF(AND(OR(C11="Квартира",C11="Апартаменты"),K11=""),"Жилая площадь",""),IF(AND(OR(C11="Дом",C11="Вилла",C11="Земля"),L11=""),"Площадь участка",""),IF(AND(OR(C11="Квартира",C11="Апартаменты"),M11=""),"Комнаты",""),IF(AND(OR(C11="Дом",C11="Вилла"),N11=""),"Спальни",""),IF(AND(OR(C11="Квартира",C11="Апартаменты",C11="Дом",C11="Вилла"),O11=""),"Ванные",""),IF(AND(OR(C11="Квартира",C11="Апартаменты"),P11=""),"Этаж",""),IF(AND(OR(OR(C11="Квартира",C11="Апартаменты"),OR(C11="Дом",C11="Вилла")),Q11=""),"Этажей",""),IF(AND(OR(OR(C11="Квартира",C11="Апартаменты"),OR(C11="Дом",C11="Вилла")),OR(R11="",R11>YEAR(TODAY()))),"Год постройки",""),IF(AND(P11<>"",Q11<>"",P11>Q11),"Этаж больше этажности",""),IF(AND(OR(C11="Квартира",C11="Апартаменты",C11="Дом",C11="Вилла"),S11=""),"Материал",""),IF(AND(OR(C11="Коммерческая"),U11=""),"Тип коммерции",""),IF(AND(OR(C11="Земля"),V11=""),"Назначение земли",""),IF(OR(X11="",X11<=0),"Минимальная цена продажи",""),IF(OR(Y11="",Y11<=0),"Стартовая ставка",""),IF(Z11="","Начало аукциона",""),IF(AA11="","Окончание аукциона",""),IF(AND(W11<>"",X11<>"",X11>W11),"Минимальная цена выше «Продать сейчас»",""),IF(AND(W11<>"",X11<>"",X11<=W11,X11>W11*0.9),"Минимальная цена выше 90% от «Продать сейчас»",""),IF(AND(W11<>"",Y11<>"",Y11>W11*0.3),"Стартовая ставка выше 30% от «Продать сейчас»",""),IF(AND(Z11<>"",AA11<>"",AA11<EDATE(Z11,3)+15),"Аукцион короче 3 месяцев и 15 дней",""),IF(AND(AB11="Да",OR(AC11="",AC11<=0)),"Цена тест-драйва за сутки",""),IF(OR(AJ11="",AJ11="Нет"),"Право собственности",""),IF(OR(AK11="",AK11="Нет"),"Справка об отсутствии обременений","")))) | AN11: =IF(NOT(COUNTA(A11:AL11)>0),"",IF(TEXTJOIN(", ",TRUE,IF(AH11="","Описание",""),IF(AND(AE11<>"",AE11>=1,AE11<5),"Фото меньше 5",""),IF(AG11="","Видео",""),IF(H11="","Кадастровый номер",""),IF(AF11="","Ссылка на фото",""))="","",TEXTJOIN(", ",TRUE,IF(AH11="","Описание",""),IF(AND(AE11<>"",AE11>=1,AE11<5),"Фото меньше 5",""),IF(AG11="","Видео",""),IF(H11="","Кадастровый номер",""),IF(AF11="","Ссылка на фото","")))) | AO11: =IF(NOT(COUNTA(A11:AL11)>0),"",IF(AM11="","Можно публиковать","Не хватает"))
AM12: =IF(NOT(COUNTA(A12:AL12)>0),"",IF(TEXTJOIN(", ",TRUE,IF(B12="","Название",""),IF(C12="","Тип недвижимости",""),IF(D12="","Страна",""),IF(E12="","Город",""),IF(F12="","Улица",""),IF(I12="","Валюта",""),IF(OR(AE12="",AE12<1),"Хотя бы 1 фото",""),IF(AND(OR(C12="Квартира",C12="Апартаменты",C12="Дом",C12="Вилла",C12="Коммерческая"),J12=""),"Площадь",""),IF(AND(OR(C12="Квартира",C12="Апартаменты"),K12=""),"Жилая площадь",""),IF(AND(OR(C12="Дом",C12="Вилла",C12="Земля"),L12=""),"Площадь участка",""),IF(AND(OR(C12="Квартира",C12="Апартаменты"),M12=""),"Комнаты",""),IF(AND(OR(C12="Дом",C12="Вилла"),N12=""),"Спальни",""),IF(AND(OR(C12="Квартира",C12="Апартаменты",C12="Дом",C12="Вилла"),O12=""),"Ванные",""),IF(AND(OR(C12="Квартира",C12="Апартаменты"),P12=""),"Этаж",""),IF(AND(OR(OR(C12="Квартира",C12="Апартаменты"),OR(C12="Дом",C12="Вилла")),Q12=""),"Этажей",""),IF(AND(OR(OR(C12="Квартира",C12="Апартаменты"),OR(C12="Дом",C12="Вилла")),OR(R12="",R12>YEAR(TODAY()))),"Год постройки",""),IF(AND(P12<>"",Q12<>"",P12>Q12),"Этаж больше этажности",""),IF(AND(OR(C12="Квартира",C12="Апартаменты",C12="Дом",C12="Вилла"),S12=""),"Материал",""),IF(AND(OR(C12="Коммерческая"),U12=""),"Тип коммерции",""),IF(AND(OR(C12="Земля"),V12=""),"Назначение земли",""),IF(OR(X12="",X12<=0),"Минимальная цена продажи",""),IF(OR(Y12="",Y12<=0),"Стартовая ставка",""),IF(Z12="","Начало аукциона",""),IF(AA12="","Окончание аукциона",""),IF(AND(W12<>"",X12<>"",X12>W12),"Минимальная цена выше «Продать сейчас»",""),IF(AND(W12<>"",X12<>"",X12<=W12,X12>W12*0.9),"Минимальная цена выше 90% от «Продать сейчас»",""),IF(AND(W12<>"",Y12<>"",Y12>W12*0.3),"Стартовая ставка выше 30% от «Продать сейчас»",""),IF(AND(Z12<>"",AA12<>"",AA12<EDATE(Z12,3)+15),"Аукцион короче 3 месяцев и 15 дней",""),IF(AND(AB12="Да",OR(AC12="",AC12<=0)),"Цена тест-драйва за сутки",""),IF(OR(AJ12="",AJ12="Нет"),"Право собственности",""),IF(OR(AK12="",AK12="Нет"),"Справка об отсутствии обременений",""))="","",TEXTJOIN(", ",TRUE,IF(B12="","Название",""),IF(C12="","Тип недвижимости",""),IF(D12="","Страна",""),IF(E12="","Город",""),IF(F12="","Улица",""),IF(I12="","Валюта",""),IF(OR(AE12="",AE12<1),"Хотя бы 1 фото",""),IF(AND(OR(C12="Квартира",C12="Апартаменты",C12="Дом",C12="Вилла",C12="Коммерческая"),J12=""),"Площадь",""),IF(AND(OR(C12="Квартира",C12="Апартаменты"),K12=""),"Жилая площадь",""),IF(AND(OR(C12="Дом",C12="Вилла",C12="Земля"),L12=""),"Площадь участка",""),IF(AND(OR(C12="Квартира",C12="Апартаменты"),M12=""),"Комнаты",""),IF(AND(OR(C12="Дом",C12="Вилла"),N12=""),"Спальни",""),IF(AND(OR(C12="Квартира",C12="Апартаменты",C12="Дом",C12="Вилла"),O12=""),"Ванные",""),IF(AND(OR(C12="Квартира",C12="Апартаменты"),P12=""),"Этаж",""),IF(AND(OR(OR(C12="Квартира",C12="Апартаменты"),OR(C12="Дом",C12="Вилла")),Q12=""),"Этажей",""),IF(AND(OR(OR(C12="Квартира",C12="Апартаменты"),OR(C12="Дом",C12="Вилла")),OR(R12="",R12>YEAR(TODAY()))),"Год постройки",""),IF(AND(P12<>"",Q12<>"",P12>Q12),"Этаж больше этажности",""),IF(AND(OR(C12="Квартира",C12="Апартаменты",C12="Дом",C12="Вилла"),S12=""),"Материал",""),IF(AND(OR(C12="Коммерческая"),U12=""),"Тип коммерции",""),IF(AND(OR(C12="Земля"),V12=""),"Назначение земли",""),IF(OR(X12="",X12<=0),"Минимальная цена продажи",""),IF(OR(Y12="",Y12<=0),"Стартовая ставка",""),IF(Z12="","Начало аукциона",""),IF(AA12="","Окончание аукциона",""),IF(AND(W12<>"",X12<>"",X12>W12),"Минимальная цена выше «Продать сейчас»",""),IF(AND(W12<>"",X12<>"",X12<=W12,X12>W12*0.9),"Минимальная цена выше 90% от «Продать сейчас»",""),IF(AND(W12<>"",Y12<>"",Y12>W12*0.3),"Стартовая ставка выше 30% от «Продать сейчас»",""),IF(AND(Z12<>"",AA12<>"",AA12<EDATE(Z12,3)+15),"Аукцион короче 3 месяцев и 15 дней",""),IF(AND(AB12="Да",OR(AC12="",AC12<=0)),"Цена тест-драйва за сутки",""),IF(OR(AJ12="",AJ12="Нет"),"Право собственности",""),IF(OR(AK12="",AK12="Нет"),"Справка об отсутствии обременений","")))) | AN12: =IF(NOT(COUNTA(A12:AL12)>0),"",IF(TEXTJOIN(", ",TRUE,IF(AH12="","Описание",""),IF(AND(AE12<>"",AE12>=1,AE12<5),"Фото меньше 5",""),IF(AG12="","Видео",""),IF(H12="","Кадастровый номер",""),IF(AF12="","Ссылка на фото",""))="","",TEXTJOIN(", ",TRUE,IF(AH12="","Описание",""),IF(AND(AE12<>"",AE12>=1,AE12<5),"Фото меньше 5",""),IF(AG12="","Видео",""),IF(H12="","Кадастровый номер",""),IF(AF12="","Ссылка на фото","")))) | AO12: =IF(NOT(COUNTA(A12:AL12)>0),"",IF(AM12="","Можно публиковать","Не хватает"))
AM13: =IF(NOT(COUNTA(A13:AL13)>0),"",IF(TEXTJOIN(", ",TRUE,IF(B13="","Название",""),IF(C13="","Тип недвижимости",""),IF(D13="","Страна",""),IF(E13="","Город",""),IF(F13="","Улица",""),IF(I13="","Валюта",""),IF(OR(AE13="",AE13<1),"Хотя бы 1 фото",""),IF(AND(OR(C13="Квартира",C13="Апартаменты",C13="Дом",C13="Вилла",C13="Коммерческая"),J13=""),"Площадь",""),IF(AND(OR(C13="Квартира",C13="Апартаменты"),K13=""),"Жилая площадь",""),IF(AND(OR(C13="Дом",C13="Вилла",C13="Земля"),L13=""),"Площадь участка",""),IF(AND(OR(C13="Квартира",C13="Апартаменты"),M13=""),"Комнаты",""),IF(AND(OR(C13="Дом",C13="Вилла"),N13=""),"Спальни",""),IF(AND(OR(C13="Квартира",C13="Апартаменты",C13="Дом",C13="Вилла"),O13=""),"Ванные",""),IF(AND(OR(C13="Квартира",C13="Апартаменты"),P13=""),"Этаж",""),IF(AND(OR(OR(C13="Квартира",C13="Апартаменты"),OR(C13="Дом",C13="Вилла")),Q13=""),"Этажей",""),IF(AND(OR(OR(C13="Квартира",C13="Апартаменты"),OR(C13="Дом",C13="Вилла")),OR(R13="",R13>YEAR(TODAY()))),"Год постройки",""),IF(AND(P13<>"",Q13<>"",P13>Q13),"Этаж больше этажности",""),IF(AND(OR(C13="Квартира",C13="Апартаменты",C13="Дом",C13="Вилла"),S13=""),"Материал",""),IF(AND(OR(C13="Коммерческая"),U13=""),"Тип коммерции",""),IF(AND(OR(C13="Земля"),V13=""),"Назначение земли",""),IF(OR(X13="",X13<=0),"Минимальная цена продажи",""),IF(OR(Y13="",Y13<=0),"Стартовая ставка",""),IF(Z13="","Начало аукциона",""),IF(AA13="","Окончание аукциона",""),IF(AND(W13<>"",X13<>"",X13>W13),"Минимальная цена выше «Продать сейчас»",""),IF(AND(W13<>"",X13<>"",X13<=W13,X13>W13*0.9),"Минимальная цена выше 90% от «Продать сейчас»",""),IF(AND(W13<>"",Y13<>"",Y13>W13*0.3),"Стартовая ставка выше 30% от «Продать сейчас»",""),IF(AND(Z13<>"",AA13<>"",AA13<EDATE(Z13,3)+15),"Аукцион короче 3 месяцев и 15 дней",""),IF(AND(AB13="Да",OR(AC13="",AC13<=0)),"Цена тест-драйва за сутки",""),IF(OR(AJ13="",AJ13="Нет"),"Право собственности",""),IF(OR(AK13="",AK13="Нет"),"Справка об отсутствии обременений",""))="","",TEXTJOIN(", ",TRUE,IF(B13="","Название",""),IF(C13="","Тип недвижимости",""),IF(D13="","Страна",""),IF(E13="","Город",""),IF(F13="","Улица",""),IF(I13="","Валюта",""),IF(OR(AE13="",AE13<1),"Хотя бы 1 фото",""),IF(AND(OR(C13="Квартира",C13="Апартаменты",C13="Дом",C13="Вилла",C13="Коммерческая"),J13=""),"Площадь",""),IF(AND(OR(C13="Квартира",C13="Апартаменты"),K13=""),"Жилая площадь",""),IF(AND(OR(C13="Дом",C13="Вилла",C13="Земля"),L13=""),"Площадь участка",""),IF(AND(OR(C13="Квартира",C13="Апартаменты"),M13=""),"Комнаты",""),IF(AND(OR(C13="Дом",C13="Вилла"),N13=""),"Спальни",""),IF(AND(OR(C13="Квартира",C13="Апартаменты",C13="Дом",C13="Вилла"),O13=""),"Ванные",""),IF(AND(OR(C13="Квартира",C13="Апартаменты"),P13=""),"Этаж",""),IF(AND(OR(OR(C13="Квартира",C13="Апартаменты"),OR(C13="Дом",C13="Вилла")),Q13=""),"Этажей",""),IF(AND(OR(OR(C13="Квартира",C13="Апартаменты"),OR(C13="Дом",C13="Вилла")),OR(R13="",R13>YEAR(TODAY()))),"Год постройки",""),IF(AND(P13<>"",Q13<>"",P13>Q13),"Этаж больше этажности",""),IF(AND(OR(C13="Квартира",C13="Апартаменты",C13="Дом",C13="Вилла"),S13=""),"Материал",""),IF(AND(OR(C13="Коммерческая"),U13=""),"Тип коммерции",""),IF(AND(OR(C13="Земля"),V13=""),"Назначение земли",""),IF(OR(X13="",X13<=0),"Минимальная цена продажи",""),IF(OR(Y13="",Y13<=0),"Стартовая ставка",""),IF(Z13="","Начало аукциона",""),IF(AA13="","Окончание аукциона",""),IF(AND(W13<>"",X13<>"",X13>W13),"Минимальная цена выше «Продать сейчас»",""),IF(AND(W13<>"",X13<>"",X13<=W13,X13>W13*0.9),"Минимальная цена выше 90% от «Продать сейчас»",""),IF(AND(W13<>"",Y13<>"",Y13>W13*0.3),"Стартовая ставка выше 30% от «Продать сейчас»",""),IF(AND(Z13<>"",AA13<>"",AA13<EDATE(Z13,3)+15),"Аукцион короче 3 месяцев и 15 дней",""),IF(AND(AB13="Да",OR(AC13="",AC13<=0)),"Цена тест-драйва за сутки",""),IF(OR(AJ13="",AJ13="Нет"),"Право собственности",""),IF(OR(AK13="",AK13="Нет"),"Справка об отсутствии обременений","")))) | AN13: =IF(NOT(COUNTA(A13:AL13)>0),"",IF(TEXTJOIN(", ",TRUE,IF(AH13="","Описание",""),IF(AND(AE13<>"",AE13>=1,AE13<5),"Фото меньше 5",""),IF(AG13="","Видео",""),IF(H13="","Кадастровый номер",""),IF(AF13="","Ссылка на фото",""))="","",TEXTJOIN(", ",TRUE,IF(AH13="","Описание",""),IF(AND(AE13<>"",AE13>=1,AE13<5),"Фото меньше 5",""),IF(AG13="","Видео",""),IF(H13="","Кадастровый номер",""),IF(AF13="","Ссылка на фото","")))) | AO13: =IF(NOT(COUNTA(A13:AL13)>0),"",IF(AM13="","Можно публиковать","Не хватает"))
AM14: =IF(NOT(COUNTA(A14:AL14)>0),"",IF(TEXTJOIN(", ",TRUE,IF(B14="","Название",""),IF(C14="","Тип недвижимости",""),IF(D14="","Страна",""),IF(E14="","Город",""),IF(F14="","Улица",""),IF(I14="","Валюта",""),IF(OR(AE14="",AE14<1),"Хотя бы 1 фото",""),IF(AND(OR(C14="Квартира",C14="Апартаменты",C14="Дом",C14="Вилла",C14="Коммерческая"),J14=""),"Площадь",""),IF(AND(OR(C14="Квартира",C14="Апартаменты"),K14=""),"Жилая площадь",""),IF(AND(OR(C14="Дом",C14="Вилла",C14="Земля"),L14=""),"Площадь участка",""),IF(AND(OR(C14="Квартира",C14="Апартаменты"),M14=""),"Комнаты",""),IF(AND(OR(C14="Дом",C14="Вилла"),N14=""),"Спальни",""),IF(AND(OR(C14="Квартира",C14="Апартаменты",C14="Дом",C14="Вилла"),O14=""),"Ванные",""),IF(AND(OR(C14="Квартира",C14="Апартаменты"),P14=""),"Этаж",""),IF(AND(OR(OR(C14="Квартира",C14="Апартаменты"),OR(C14="Дом",C14="Вилла")),Q14=""),"Этажей",""),IF(AND(OR(OR(C14="Квартира",C14="Апартаменты"),OR(C14="Дом",C14="Вилла")),OR(R14="",R14>YEAR(TODAY()))),"Год постройки",""),IF(AND(P14<>"",Q14<>"",P14>Q14),"Этаж больше этажности",""),IF(AND(OR(C14="Квартира",C14="Апартаменты",C14="Дом",C14="Вилла"),S14=""),"Материал",""),IF(AND(OR(C14="Коммерческая"),U14=""),"Тип коммерции",""),IF(AND(OR(C14="Земля"),V14=""),"Назначение земли",""),IF(OR(X14="",X14<=0),"Минимальная цена продажи",""),IF(OR(Y14="",Y14<=0),"Стартовая ставка",""),IF(Z14="","Начало аукциона",""),IF(AA14="","Окончание аукциона",""),IF(AND(W14<>"",X14<>"",X14>W14),"Минимальная цена выше «Продать сейчас»",""),IF(AND(W14<>"",X14<>"",X14<=W14,X14>W14*0.9),"Минимальная цена выше 90% от «Продать сейчас»",""),IF(AND(W14<>"",Y14<>"",Y14>W14*0.3),"Стартовая ставка выше 30% от «Продать сейчас»",""),IF(AND(Z14<>"",AA14<>"",AA14<EDATE(Z14,3)+15),"Аукцион короче 3 месяцев и 15 дней",""),IF(AND(AB14="Да",OR(AC14="",AC14<=0)),"Цена тест-драйва за сутки",""),IF(OR(AJ14="",AJ14="Нет"),"Право собственности",""),IF(OR(AK14="",AK14="Нет"),"Справка об отсутствии обременений",""))="","",TEXTJOIN(", ",TRUE,IF(B14="","Название",""),IF(C14="","Тип недвижимости",""),IF(D14="","Страна",""),IF(E14="","Город",""),IF(F14="","Улица",""),IF(I14="","Валюта",""),IF(OR(AE14="",AE14<1),"Хотя бы 1 фото",""),IF(AND(OR(C14="Квартира",C14="Апартаменты",C14="Дом",C14="Вилла",C14="Коммерческая"),J14=""),"Площадь",""),IF(AND(OR(C14="Квартира",C14="Апартаменты"),K14=""),"Жилая площадь",""),IF(AND(OR(C14="Дом",C14="Вилла",C14="Земля"),L14=""),"Площадь участка",""),IF(AND(OR(C14="Квартира",C14="Апартаменты"),M14=""),"Комнаты",""),IF(AND(OR(C14="Дом",C14="Вилла"),N14=""),"Спальни",""),IF(AND(OR(C14="Квартира",C14="Апартаменты",C14="Дом",C14="Вилла"),O14=""),"Ванные",""),IF(AND(OR(C14="Квартира",C14="Апартаменты"),P14=""),"Этаж",""),IF(AND(OR(OR(C14="Квартира",C14="Апартаменты"),OR(C14="Дом",C14="Вилла")),Q14=""),"Этажей",""),IF(AND(OR(OR(C14="Квартира",C14="Апартаменты"),OR(C14="Дом",C14="Вилла")),OR(R14="",R14>YEAR(TODAY()))),"Год постройки",""),IF(AND(P14<>"",Q14<>"",P14>Q14),"Этаж больше этажности",""),IF(AND(OR(C14="Квартира",C14="Апартаменты",C14="Дом",C14="Вилла"),S14=""),"Материал",""),IF(AND(OR(C14="Коммерческая"),U14=""),"Тип коммерции",""),IF(AND(OR(C14="Земля"),V14=""),"Назначение земли",""),IF(OR(X14="",X14<=0),"Минимальная цена продажи",""),IF(OR(Y14="",Y14<=0),"Стартовая ставка",""),IF(Z14="","Начало аукциона",""),IF(AA14="","Окончание аукциона",""),IF(AND(W14<>"",X14<>"",X14>W14),"Минимальная цена выше «Продать сейчас»",""),IF(AND(W14<>"",X14<>"",X14<=W14,X14>W14*0.9),"Минимальная цена выше 90% от «Продать сейчас»",""),IF(AND(W14<>"",Y14<>"",Y14>W14*0.3),"Стартовая ставка выше 30% от «Продать сейчас»",""),IF(AND(Z14<>"",AA14<>"",AA14<EDATE(Z14,3)+15),"Аукцион короче 3 месяцев и 15 дней",""),IF(AND(AB14="Да",OR(AC14="",AC14<=0)),"Цена тест-драйва за сутки",""),IF(OR(AJ14="",AJ14="Нет"),"Право собственности",""),IF(OR(AK14="",AK14="Нет"),"Справка об отсутствии обременений","")))) | AN14: =IF(NOT(COUNTA(A14:AL14)>0),"",IF(TEXTJOIN(", ",TRUE,IF(AH14="","Описание",""),IF(AND(AE14<>"",AE14>=1,AE14<5),"Фото меньше 5",""),IF(AG14="","Видео",""),IF(H14="","Кадастровый номер",""),IF(AF14="","Ссылка на фото",""))="","",TEXTJOIN(", ",TRUE,IF(AH14="","Описание",""),IF(AND(AE14<>"",AE14>=1,AE14<5),"Фото меньше 5",""),IF(AG14="","Видео",""),IF(H14="","Кадастровый номер",""),IF(AF14="","Ссылка на фото","")))) | AO14: =IF(NOT(COUNTA(A14:AL14)>0),"",IF(AM14="","Можно публиковать","Не хватает"))
... AM82: =IF(NOT(COUNTA(A82:AL82)>0),"",IF(TEXTJOIN(", ",TRUE,IF(B82="","Название",""),IF(C82="","Тип недвижимости",""),IF(D82="","Страна",""),IF(E82="","Город",""),IF(F82="","Улица",""),IF(I82="","Валюта",""),IF(OR(AE82="",AE82<1),"Хотя бы 1 фото",""),IF(AND(OR(C82="Квартира",C82="Апартаменты",C82="Дом",C82="Вилла",C82="Коммерческая"),J82=""),"Площадь",""),IF(AND(OR(C82="Квартира",C82="Апартаменты"),K82=""),"Жилая площадь",""),IF(AND(OR(C82="Дом",C82="Вилла",C82="Земля"),L82=""),"Площадь участка",""),IF(AND(OR(C82="Квартира",C82="Апартаменты"),M82=""),"Комнаты",""),IF(AND(OR(C82="Дом",C82="Вилла"),N82=""),"Спальни",""),IF(AND(OR(C82="Квартира",C82="Апартаменты",C82="Дом",C82="Вилла"),O82=""),"Ванные",""),IF(AND(OR(C82="Квартира",C82="Апартаменты"),P82=""),"Этаж",""),IF(AND(OR(OR(C82="Квартира",C82="Апартаменты"),OR(C82="Дом",C82="Вилла")),Q82=""),"Этажей",""),IF(AND(OR(OR(C82="Квартира",C82="Апартаменты"),OR(C82="Дом",C82="Вилла")),OR(R82="",R82>YEAR(TODAY()))),"Год постройки",""),IF(AND(P82<>"",Q82<>"",P82>Q82),"Этаж больше этажности",""),IF(AND(OR(C82="Квартира",C82="Апартаменты",C82="Дом",C82="Вилла"),S82=""),"Материал",""),IF(AND(OR(C82="Коммерческая"),U82=""),"Тип коммерции",""),IF(AND(OR(C82="Земля"),V82=""),"Назначение земли",""),IF(OR(X82="",X82<=0),"Минимальная цена продажи",""),IF(OR(Y82="",Y82<=0),"Стартовая ставка",""),IF(Z82="","Начало аукциона",""),IF(AA82="","Окончание аукциона",""),IF(AND(W82<>"",X82<>"",X82>W82),"Минимальная цена выше «Продать сейчас»",""),IF(AND(W82<>"",X82<>"",X82<=W82,X82>W82*0.9),"Минимальная цена выше 90% от «Продать сейчас»",""),IF(AND(W82<>"",Y82<>"",Y82>W82*0.3),"Стартовая ставка выше 30% от «Продать сейчас»",""),IF(AND(Z82<>"",AA82<>"",AA82<EDATE(Z82,3)+15),"Аукцион короче 3 месяцев и 15 дней",""),IF(AND(AB82="Да",OR(AC82="",AC82<=0)),"Цена тест-драйва за сутки",""),IF(OR(AJ82="",AJ82="Нет"),"Право собственности",""),IF(OR(AK82="",AK82="Нет"),"Справка об отсутствии обременений",""))="","",TEXTJOIN(", ",TRUE,IF(B82="","Название",""),IF(C82="","Тип недвижимости",""),IF(D82="","Страна",""),IF(E82="","Город",""),IF(F82="","Улица",""),IF(I82="","Валюта",""),IF(OR(AE82="",AE82<1),"Хотя бы 1 фото",""),IF(AND(OR(C82="Квартира",C82="Апартаменты",C82="Дом",C82="Вилла",C82="Коммерческая"),J82=""),"Площадь",""),IF(AND(OR(C82="Квартира",C82="Апартаменты"),K82=""),"Жилая площадь",""),IF(AND(OR(C82="Дом",C82="Вилла",C82="Земля"),L82=""),"Площадь участка",""),IF(AND(OR(C82="Квартира",C82="Апартаменты"),M82=""),"Комнаты",""),IF(AND(OR(C82="Дом",C82="Вилла"),N82=""),"Спальни",""),IF(AND(OR(C82="Квартира",C82="Апартаменты",C82="Дом",C82="Вилла"),O82=""),"Ванные",""),IF(AND(OR(C82="Квартира",C82="Апартаменты"),P82=""),"Этаж",""),IF(AND(OR(OR(C82="Квартира",C82="Апартаменты"),OR(C82="Дом",C82="Вилла")),Q82=""),"Этажей",""),IF(AND(OR(OR(C82="Квартира",C82="Апартаменты"),OR(C82="Дом",C82="Вилла")),OR(R82="",R82>YEAR(TODAY()))),"Год постройки",""),IF(AND(P82<>"",Q82<>"",P82>Q82),"Этаж больше этажности",""),IF(AND(OR(C82="Квартира",C82="Апартаменты",C82="Дом",C82="Вилла"),S82=""),"Материал",""),IF(AND(OR(C82="Коммерческая"),U82=""),"Тип коммерции",""),IF(AND(OR(C82="Земля"),V82=""),"Назначение земли",""),IF(OR(X82="",X82<=0),"Минимальная цена продажи",""),IF(OR(Y82="",Y82<=0),"Стартовая ставка",""),IF(Z82="","Начало аукциона",""),IF(AA82="","Окончание аукциона",""),IF(AND(W82<>"",X82<>"",X82>W82),"Минимальная цена выше «Продать сейчас»",""),IF(AND(W82<>"",X82<>"",X82<=W82,X82>W82*0.9),"Минимальная цена выше 90% от «Продать сейчас»",""),IF(AND(W82<>"",Y82<>"",Y82>W82*0.3),"Стартовая ставка выше 30% от «Продать сейчас»",""),IF(AND(Z82<>"",AA82<>"",AA82<EDATE(Z82,3)+15),"Аукцион короче 3 месяцев и 15 дней",""),IF(AND(AB82="Да",OR(AC82="",AC82<=0)),"Цена тест-драйва за сутки",""),IF(OR(AJ82="",AJ82="Нет"),"Право собственности",""),IF(OR(AK82="",AK82="Нет"),"Справка об отсутствии обременений","")))) | AN82: =IF(NOT(COUNTA(A82:AL82)>0),"",IF(TEXTJOIN(", ",TRUE,IF(AH82="","Описание",""),IF(AND(AE82<>"",AE82>=1,AE82<5),"Фото меньше 5",""),IF(AG82="","Видео",""),IF(H82="","Кадастровый номер",""),IF(AF82="","Ссылка на фото",""))="","",TEXTJOIN(", ",TRUE,IF(AH82="","Описание",""),IF(AND(AE82<>"",AE82>=1,AE82<5),"Фото меньше 5",""),IF(AG82="","Видео",""),IF(H82="","Кадастровый номер",""),IF(AF82="","Ссылка на фото","")))) | AO82: =IF(NOT(COUNTA(A82:AL82)>0),"",IF(AM82="","Можно публиковать","Не хватает"))

Sheet Доли
A1: Сбор | B1: Объект | D1: Адрес | I1: Объект | J1: Параметры | W1: Доли | AA1: Подача | AF1: Документы | AI1: Проверка
A2: Источник | B2: Название | C2: Тип недвижимости | D2: Страна | E2: Город | F2: Улица | G2: Номер дома | H2: Кадастровый номер | I2: Валюта | J2: Площадь, м² | K2: Жилая, м² | L2: Участок, м² | M2: Комнаты | N2: Спальни | O2: Ванные | P2: Этаж | Q2: Этажей | R2: Год | S2: Материал | T2: Конструкция | U2: Тип коммерции | V2: Назначение земли | W2: Общая стоимость | X2: Количество долей | Y2: Цена одной доли | Z2: Купить целиком | AA2: Фото, шт. | AB2: Ссылка на фото | AC2: Ссылка на видео | AD2: Описание | AE2: Удобства | AF2: Право собственности | AG2: Нет обременений | AH2: Доп. документы | AI2: Не хватает для публикации | AJ2: Желательно добрать | AK2: Готовность
Y3: =IF(OR(W3="",X3="",X3<=0),"",W3/X3) | AI3: =IF(NOT(COUNTA(A3:AH3)>0),"",IF(TEXTJOIN(", ",TRUE,IF(B3="","Название",""),IF(C3="","Тип недвижимости",""),IF(D3="","Страна",""),IF(E3="","Город",""),IF(F3="","Улица",""),IF(I3="","Валюта",""),IF(OR(AA3="",AA3<1),"Хотя бы 1 фото",""),IF(AND(OR(C3="Квартира",C3="Апартаменты",C3="Дом",C3="Вилла",C3="Коммерческая"),J3=""),"Площадь",""),IF(AND(OR(C3="Квартира",C3="Апартаменты"),K3=""),"Жилая площадь",""),IF(AND(OR(C3="Дом",C3="Вилла",C3="Земля"),L3=""),"Площадь участка",""),IF(AND(OR(C3="Квартира",C3="Апартаменты"),M3=""),"Комнаты",""),IF(AND(OR(C3="Дом",C3="Вилла"),N3=""),"Спальни",""),IF(AND(OR(C3="Квартира",C3="Апартаменты",C3="Дом",C3="Вилла"),O3=""),"Ванные",""),IF(AND(OR(C3="Квартира",C3="Апартаменты"),P3=""),"Этаж",""),IF(AND(OR(OR(C3="Квартира",C3="Апартаменты"),OR(C3="Дом",C3="Вилла")),Q3=""),"Этажей",""),IF(AND(OR(OR(C3="Квартира",C3="Апартаменты"),OR(C3="Дом",C3="Вилла")),OR(R3="",R3>YEAR(TODAY()))),"Год постройки",""),IF(AND(P3<>"",Q3<>"",P3>Q3),"Этаж больше этажности",""),IF(AND(OR(C3="Квартира",C3="Апартаменты",C3="Дом",C3="Вилла"),S3=""),"Материал",""),IF(AND(OR(C3="Коммерческая"),U3=""),"Тип коммерции",""),IF(AND(OR(C3="Земля"),V3=""),"Назначение земли",""),IF(OR(AF3="",AF3="Нет"),"Право собственности",""),IF(OR(AG3="",AG3="Нет"),"Справка об отсутствии обременений",""),IF(OR(W3="",W3<=0),"Общая стоимость",""),IF(OR(X3="",X3<=0),"Количество долей",""),IF(AND(X3<>"",X3<>INT(X3)),"Количество долей должно быть целым",""))="","",TEXTJOIN(", ",TRUE,IF(B3="","Название",""),IF(C3="","Тип недвижимости",""),IF(D3="","Страна",""),IF(E3="","Город",""),IF(F3="","Улица",""),IF(I3="","Валюта",""),IF(OR(AA3="",AA3<1),"Хотя бы 1 фото",""),IF(AND(OR(C3="Квартира",C3="Апартаменты",C3="Дом",C3="Вилла",C3="Коммерческая"),J3=""),"Площадь",""),IF(AND(OR(C3="Квартира",C3="Апартаменты"),K3=""),"Жилая площадь",""),IF(AND(OR(C3="Дом",C3="Вилла",C3="Земля"),L3=""),"Площадь участка",""),IF(AND(OR(C3="Квартира",C3="Апартаменты"),M3=""),"Комнаты",""),IF(AND(OR(C3="Дом",C3="Вилла"),N3=""),"Спальни",""),IF(AND(OR(C3="Квартира",C3="Апартаменты",C3="Дом",C3="Вилла"),O3=""),"Ванные",""),IF(AND(OR(C3="Квартира",C3="Апартаменты"),P3=""),"Этаж",""),IF(AND(OR(OR(C3="Квартира",C3="Апартаменты"),OR(C3="Дом",C3="Вилла")),Q3=""),"Этажей",""),IF(AND(OR(OR(C3="Квартира",C3="Апартаменты"),OR(C3="Дом",C3="Вилла")),OR(R3="",R3>YEAR(TODAY()))),"Год постройки",""),IF(AND(P3<>"",Q3<>"",P3>Q3),"Этаж больше этажности",""),IF(AND(OR(C3="Квартира",C3="Апартаменты",C3="Дом",C3="Вилла"),S3=""),"Материал",""),IF(AND(OR(C3="Коммерческая"),U3=""),"Тип коммерции",""),IF(AND(OR(C3="Земля"),V3=""),"Назначение земли",""),IF(OR(AF3="",AF3="Нет"),"Право собственности",""),IF(OR(AG3="",AG3="Нет"),"Справка об отсутствии обременений",""),IF(OR(W3="",W3<=0),"Общая стоимость",""),IF(OR(X3="",X3<=0),"Количество долей",""),IF(AND(X3<>"",X3<>INT(X3)),"Количество долей должно быть целым","")))) | AJ3: =IF(NOT(COUNTA(A3:AH3)>0),"",IF(TEXTJOIN(", ",TRUE,IF(AD3="","Описание",""),IF(AND(AA3<>"",AA3>=1,AA3<5),"Фото меньше 5",""),IF(AC3="","Видео",""),IF(H3="","Кадастровый номер",""),IF(AB3="","Ссылка на фото",""))="","",TEXTJOIN(", ",TRUE,IF(AD3="","Описание",""),IF(AND(AA3<>"",AA3>=1,AA3<5),"Фото меньше 5",""),IF(AC3="","Видео",""),IF(H3="","Кадастровый номер",""),IF(AB3="","Ссылка на фото","")))) | AK3: =IF(NOT(COUNTA(A3:AH3)>0),"",IF(AI3="","Можно публиковать","Не хватает"))
Y4: =IF(OR(W4="",X4="",X4<=0),"",W4/X4) | AI4: =IF(NOT(COUNTA(A4:AH4)>0),"",IF(TEXTJOIN(", ",TRUE,IF(B4="","Название",""),IF(C4="","Тип недвижимости",""),IF(D4="","Страна",""),IF(E4="","Город",""),IF(F4="","Улица",""),IF(I4="","Валюта",""),IF(OR(AA4="",AA4<1),"Хотя бы 1 фото",""),IF(AND(OR(C4="Квартира",C4="Апартаменты",C4="Дом",C4="Вилла",C4="Коммерческая"),J4=""),"Площадь",""),IF(AND(OR(C4="Квартира",C4="Апартаменты"),K4=""),"Жилая площадь",""),IF(AND(OR(C4="Дом",C4="Вилла",C4="Земля"),L4=""),"Площадь участка",""),IF(AND(OR(C4="Квартира",C4="Апартаменты"),M4=""),"Комнаты",""),IF(AND(OR(C4="Дом",C4="Вилла"),N4=""),"Спальни",""),IF(AND(OR(C4="Квартира",C4="Апартаменты",C4="Дом",C4="Вилла"),O4=""),"Ванные",""),IF(AND(OR(C4="Квартира",C4="Апартаменты"),P4=""),"Этаж",""),IF(AND(OR(OR(C4="Квартира",C4="Апартаменты"),OR(C4="Дом",C4="Вилла")),Q4=""),"Этажей",""),IF(AND(OR(OR(C4="Квартира",C4="Апартаменты"),OR(C4="Дом",C4="Вилла")),OR(R4="",R4>YEAR(TODAY()))),"Год постройки",""),IF(AND(P4<>"",Q4<>"",P4>Q4),"Этаж больше этажности",""),IF(AND(OR(C4="Квартира",C4="Апартаменты",C4="Дом",C4="Вилла"),S4=""),"Материал",""),IF(AND(OR(C4="Коммерческая"),U4=""),"Тип коммерции",""),IF(AND(OR(C4="Земля"),V4=""),"Назначение земли",""),IF(OR(AF4="",AF4="Нет"),"Право собственности",""),IF(OR(AG4="",AG4="Нет"),"Справка об отсутствии обременений",""),IF(OR(W4="",W4<=0),"Общая стоимость",""),IF(OR(X4="",X4<=0),"Количество долей",""),IF(AND(X4<>"",X4<>INT(X4)),"Количество долей должно быть целым",""))="","",TEXTJOIN(", ",TRUE,IF(B4="","Название",""),IF(C4="","Тип недвижимости",""),IF(D4="","Страна",""),IF(E4="","Город",""),IF(F4="","Улица",""),IF(I4="","Валюта",""),IF(OR(AA4="",AA4<1),"Хотя бы 1 фото",""),IF(AND(OR(C4="Квартира",C4="Апартаменты",C4="Дом",C4="Вилла",C4="Коммерческая"),J4=""),"Площадь",""),IF(AND(OR(C4="Квартира",C4="Апартаменты"),K4=""),"Жилая площадь",""),IF(AND(OR(C4="Дом",C4="Вилла",C4="Земля"),L4=""),"Площадь участка",""),IF(AND(OR(C4="Квартира",C4="Апартаменты"),M4=""),"Комнаты",""),IF(AND(OR(C4="Дом",C4="Вилла"),N4=""),"Спальни",""),IF(AND(OR(C4="Квартира",C4="Апартаменты",C4="Дом",C4="Вилла"),O4=""),"Ванные",""),IF(AND(OR(C4="Квартира",C4="Апартаменты"),P4=""),"Этаж",""),IF(AND(OR(OR(C4="Квартира",C4="Апартаменты"),OR(C4="Дом",C4="Вилла")),Q4=""),"Этажей",""),IF(AND(OR(OR(C4="Квартира",C4="Апартаменты"),OR(C4="Дом",C4="Вилла")),OR(R4="",R4>YEAR(TODAY()))),"Год постройки",""),IF(AND(P4<>"",Q4<>"",P4>Q4),"Этаж больше этажности",""),IF(AND(OR(C4="Квартира",C4="Апартаменты",C4="Дом",C4="Вилла"),S4=""),"Материал",""),IF(AND(OR(C4="Коммерческая"),U4=""),"Тип коммерции",""),IF(AND(OR(C4="Земля"),V4=""),"Назначение земли",""),IF(OR(AF4="",AF4="Нет"),"Право собственности",""),IF(OR(AG4="",AG4="Нет"),"Справка об отсутствии обременений",""),IF(OR(W4="",W4<=0),"Общая стоимость",""),IF(OR(X4="",X4<=0),"Количество долей",""),IF(AND(X4<>"",X4<>INT(X4)),"Количество долей должно быть целым","")))) | AJ4: =IF(NOT(COUNTA(A4:AH4)>0),"",IF(TEXTJOIN(", ",TRUE,IF(AD4="","Описание",""),IF(AND(AA4<>"",AA4>=1,AA4<5),"Фото меньше 5",""),IF(AC4="","Видео",""),IF(H4="","Кадастровый номер",""),IF(AB4="","Ссылка на фото",""))="","",TEXTJOIN(", ",TRUE,IF(AD4="","Описание",""),IF(AND(AA4<>"",AA4>=1,AA4<5),"Фото меньше 5",""),IF(AC4="","Видео",""),IF(H4="","Кадастровый номер",""),IF(AB4="","Ссылка на фото","")))) | AK4: =IF(NOT(COUNTA(A4:AH4)>0),"",IF(AI4="","Можно публиковать","Не хватает"))
Y5: =IF(OR(W5="",X5="",X5<=0),"",W5/X5) | AI5: =IF(NOT(COUNTA(A5:AH5)>0),"",IF(TEXTJOIN(", ",TRUE,IF(B5="","Название",""),IF(C5="","Тип недвижимости",""),IF(D5="","Страна",""),IF(E5="","Город",""),IF(F5="","Улица",""),IF(I5="","Валюта",""),IF(OR(AA5="",AA5<1),"Хотя бы 1 фото",""),IF(AND(OR(C5="Квартира",C5="Апартаменты",C5="Дом",C5="Вилла",C5="Коммерческая"),J5=""),"Площадь",""),IF(AND(OR(C5="Квартира",C5="Апартаменты"),K5=""),"Жилая площадь",""),IF(AND(OR(C5="Дом",C5="Вилла",C5="Земля"),L5=""),"Площадь участка",""),IF(AND(OR(C5="Квартира",C5="Апартаменты"),M5=""),"Комнаты",""),IF(AND(OR(C5="Дом",C5="Вилла"),N5=""),"Спальни",""),IF(AND(OR(C5="Квартира",C5="Апартаменты",C5="Дом",C5="Вилла"),O5=""),"Ванные",""),IF(AND(OR(C5="Квартира",C5="Апартаменты"),P5=""),"Этаж",""),IF(AND(OR(OR(C5="Квартира",C5="Апартаменты"),OR(C5="Дом",C5="Вилла")),Q5=""),"Этажей",""),IF(AND(OR(OR(C5="Квартира",C5="Апартаменты"),OR(C5="Дом",C5="Вилла")),OR(R5="",R5>YEAR(TODAY()))),"Год постройки",""),IF(AND(P5<>"",Q5<>"",P5>Q5),"Этаж больше этажности",""),IF(AND(OR(C5="Квартира",C5="Апартаменты",C5="Дом",C5="Вилла"),S5=""),"Материал",""),IF(AND(OR(C5="Коммерческая"),U5=""),"Тип коммерции",""),IF(AND(OR(C5="Земля"),V5=""),"Назначение земли",""),IF(OR(AF5="",AF5="Нет"),"Право собственности",""),IF(OR(AG5="",AG5="Нет"),"Справка об отсутствии обременений",""),IF(OR(W5="",W5<=0),"Общая стоимость",""),IF(OR(X5="",X5<=0),"Количество долей",""),IF(AND(X5<>"",X5<>INT(X5)),"Количество долей должно быть целым",""))="","",TEXTJOIN(", ",TRUE,IF(B5="","Название",""),IF(C5="","Тип недвижимости",""),IF(D5="","Страна",""),IF(E5="","Город",""),IF(F5="","Улица",""),IF(I5="","Валюта",""),IF(OR(AA5="",AA5<1),"Хотя бы 1 фото",""),IF(AND(OR(C5="Квартира",C5="Апартаменты",C5="Дом",C5="Вилла",C5="Коммерческая"),J5=""),"Площадь",""),IF(AND(OR(C5="Квартира",C5="Апартаменты"),K5=""),"Жилая площадь",""),IF(AND(OR(C5="Дом",C5="Вилла",C5="Земля"),L5=""),"Площадь участка",""),IF(AND(OR(C5="Квартира",C5="Апартаменты"),M5=""),"Комнаты",""),IF(AND(OR(C5="Дом",C5="Вилла"),N5=""),"Спальни",""),IF(AND(OR(C5="Квартира",C5="Апартаменты",C5="Дом",C5="Вилла"),O5=""),"Ванные",""),IF(AND(OR(C5="Квартира",C5="Апартаменты"),P5=""),"Этаж",""),IF(AND(OR(OR(C5="Квартира",C5="Апартаменты"),OR(C5="Дом",C5="Вилла")),Q5=""),"Этажей",""),IF(AND(OR(OR(C5="Квартира",C5="Апартаменты"),OR(C5="Дом",C5="Вилла")),OR(R5="",R5>YEAR(TODAY()))),"Год постройки",""),IF(AND(P5<>"",Q5<>"",P5>Q5),"Этаж больше этажности",""),IF(AND(OR(C5="Квартира",C5="Апартаменты",C5="Дом",C5="Вилла"),S5=""),"Материал",""),IF(AND(OR(C5="Коммерческая"),U5=""),"Тип коммерции",""),IF(AND(OR(C5="Земля"),V5=""),"Назначение земли",""),IF(OR(AF5="",AF5="Нет"),"Право собственности",""),IF(OR(AG5="",AG5="Нет"),"Справка об отсутствии обременений",""),IF(OR(W5="",W5<=0),"Общая стоимость",""),IF(OR(X5="",X5<=0),"Количество долей",""),IF(AND(X5<>"",X5<>INT(X5)),"Количество долей должно быть целым","")))) | AJ5: =IF(NOT(COUNTA(A5:AH5)>0),"",IF(TEXTJOIN(", ",TRUE,IF(AD5="","Описание",""),IF(AND(AA5<>"",AA5>=1,AA5<5),"Фото меньше 5",""),IF(AC5="","Видео",""),IF(H5="","Кадастровый номер",""),IF(AB5="","Ссылка на фото",""))="","",TEXTJOIN(", ",TRUE,IF(AD5="","Описание",""),IF(AND(AA5<>"",AA5>=1,AA5<5),"Фото меньше 5",""),IF(AC5="","Видео",""),IF(H5="","Кадастровый номер",""),IF(AB5="","Ссылка на фото","")))) | AK5: =IF(NOT(COUNTA(A5:AH5)>0),"",IF(AI5="","Можно публиковать","Не хватает"))
Y6: =IF(OR(W6="",X6="",X6<=0),"",W6/X6) | AI6: =IF(NOT(COUNTA(A6:AH6)>0),"",IF(TEXTJOIN(", ",TRUE,IF(B6="","Название",""),IF(C6="","Тип недвижимости",""),IF(D6="","Страна",""),IF(E6="","Город",""),IF(F6="","Улица",""),IF(I6="","Валюта",""),IF(OR(AA6="",AA6<1),"Хотя бы 1 фото",""),IF(AND(OR(C6="Квартира",C6="Апартаменты",C6="Дом",C6="Вилла",C6="Коммерческая"),J6=""),"Площадь",""),IF(AND(OR(C6="Квартира",C6="Апартаменты"),K6=""),"Жилая площадь",""),IF(AND(OR(C6="Дом",C6="Вилла",C6="Земля"),L6=""),"Площадь участка",""),IF(AND(OR(C6="Квартира",C6="Апартаменты"),M6=""),"Комнаты",""),IF(AND(OR(C6="Дом",C6="Вилла"),N6=""),"Спальни",""),IF(AND(OR(C6="Квартира",C6="Апартаменты",C6="Дом",C6="Вилла"),O6=""),"Ванные",""),IF(AND(OR(C6="Квартира",C6="Апартаменты"),P6=""),"Этаж",""),IF(AND(OR(OR(C6="Квартира",C6="Апартаменты"),OR(C6="Дом",C6="Вилла")),Q6=""),"Этажей",""),IF(AND(OR(OR(C6="Квартира",C6="Апартаменты"),OR(C6="Дом",C6="Вилла")),OR(R6="",R6>YEAR(TODAY()))),"Год постройки",""),IF(AND(P6<>"",Q6<>"",P6>Q6),"Этаж больше этажности",""),IF(AND(OR(C6="Квартира",C6="Апартаменты",C6="Дом",C6="Вилла"),S6=""),"Материал",""),IF(AND(OR(C6="Коммерческая"),U6=""),"Тип коммерции",""),IF(AND(OR(C6="Земля"),V6=""),"Назначение земли",""),IF(OR(AF6="",AF6="Нет"),"Право собственности",""),IF(OR(AG6="",AG6="Нет"),"Справка об отсутствии обременений",""),IF(OR(W6="",W6<=0),"Общая стоимость",""),IF(OR(X6="",X6<=0),"Количество долей",""),IF(AND(X6<>"",X6<>INT(X6)),"Количество долей должно быть целым",""))="","",TEXTJOIN(", ",TRUE,IF(B6="","Название",""),IF(C6="","Тип недвижимости",""),IF(D6="","Страна",""),IF(E6="","Город",""),IF(F6="","Улица",""),IF(I6="","Валюта",""),IF(OR(AA6="",AA6<1),"Хотя бы 1 фото",""),IF(AND(OR(C6="Квартира",C6="Апартаменты",C6="Дом",C6="Вилла",C6="Коммерческая"),J6=""),"Площадь",""),IF(AND(OR(C6="Квартира",C6="Апартаменты"),K6=""),"Жилая площадь",""),IF(AND(OR(C6="Дом",C6="Вилла",C6="Земля"),L6=""),"Площадь участка",""),IF(AND(OR(C6="Квартира",C6="Апартаменты"),M6=""),"Комнаты",""),IF(AND(OR(C6="Дом",C6="Вилла"),N6=""),"Спальни",""),IF(AND(OR(C6="Квартира",C6="Апартаменты",C6="Дом",C6="Вилла"),O6=""),"Ванные",""),IF(AND(OR(C6="Квартира",C6="Апартаменты"),P6=""),"Этаж",""),IF(AND(OR(OR(C6="Квартира",C6="Апартаменты"),OR(C6="Дом",C6="Вилла")),Q6=""),"Этажей",""),IF(AND(OR(OR(C6="Квартира",C6="Апартаменты"),OR(C6="Дом",C6="Вилла")),OR(R6="",R6>YEAR(TODAY()))),"Год постройки",""),IF(AND(P6<>"",Q6<>"",P6>Q6),"Этаж больше этажности",""),IF(AND(OR(C6="Квартира",C6="Апартаменты",C6="Дом",C6="Вилла"),S6=""),"Материал",""),IF(AND(OR(C6="Коммерческая"),U6=""),"Тип коммерции",""),IF(AND(OR(C6="Земля"),V6=""),"Назначение земли",""),IF(OR(AF6="",AF6="Нет"),"Право собственности",""),IF(OR(AG6="",AG6="Нет"),"Справка об отсутствии обременений",""),IF(OR(W6="",W6<=0),"Общая стоимость",""),IF(OR(X6="",X6<=0),"Количество долей",""),IF(AND(X6<>"",X6<>INT(X6)),"Количество долей должно быть целым","")))) | AJ6: =IF(NOT(COUNTA(A6:AH6)>0),"",IF(TEXTJOIN(", ",TRUE,IF(AD6="","Описание",""),IF(AND(AA6<>"",AA6>=1,AA6<5),"Фото меньше 5",""),IF(AC6="","Видео",""),IF(H6="","Кадастровый номер",""),IF(AB6="","Ссылка на фото",""))="","",TEXTJOIN(", ",TRUE,IF(AD6="","Описание",""),IF(AND(AA6<>"",AA6>=1,AA6<5),"Фото меньше 5",""),IF(AC6="","Видео",""),IF(H6="","Кадастровый номер",""),IF(AB6="","Ссылка на фото","")))) | AK6: =IF(NOT(COUNTA(A6:AH6)>0),"",IF(AI6="","Можно публиковать","Не хватает"))
Y7: =IF(OR(W7="",X7="",X7<=0),"",W7/X7) | AI7: =IF(NOT(COUNTA(A7:AH7)>0),"",IF(TEXTJOIN(", ",TRUE,IF(B7="","Название",""),IF(C7="","Тип недвижимости",""),IF(D7="","Страна",""),IF(E7="","Город",""),IF(F7="","Улица",""),IF(I7="","Валюта",""),IF(OR(AA7="",AA7<1),"Хотя бы 1 фото",""),IF(AND(OR(C7="Квартира",C7="Апартаменты",C7="Дом",C7="Вилла",C7="Коммерческая"),J7=""),"Площадь",""),IF(AND(OR(C7="Квартира",C7="Апартаменты"),K7=""),"Жилая площадь",""),IF(AND(OR(C7="Дом",C7="Вилла",C7="Земля"),L7=""),"Площадь участка",""),IF(AND(OR(C7="Квартира",C7="Апартаменты"),M7=""),"Комнаты",""),IF(AND(OR(C7="Дом",C7="Вилла"),N7=""),"Спальни",""),IF(AND(OR(C7="Квартира",C7="Апартаменты",C7="Дом",C7="Вилла"),O7=""),"Ванные",""),IF(AND(OR(C7="Квартира",C7="Апартаменты"),P7=""),"Этаж",""),IF(AND(OR(OR(C7="Квартира",C7="Апартаменты"),OR(C7="Дом",C7="Вилла")),Q7=""),"Этажей",""),IF(AND(OR(OR(C7="Квартира",C7="Апартаменты"),OR(C7="Дом",C7="Вилла")),OR(R7="",R7>YEAR(TODAY()))),"Год постройки",""),IF(AND(P7<>"",Q7<>"",P7>Q7),"Этаж больше этажности",""),IF(AND(OR(C7="Квартира",C7="Апартаменты",C7="Дом",C7="Вилла"),S7=""),"Материал",""),IF(AND(OR(C7="Коммерческая"),U7=""),"Тип коммерции",""),IF(AND(OR(C7="Земля"),V7=""),"Назначение земли",""),IF(OR(AF7="",AF7="Нет"),"Право собственности",""),IF(OR(AG7="",AG7="Нет"),"Справка об отсутствии обременений",""),IF(OR(W7="",W7<=0),"Общая стоимость",""),IF(OR(X7="",X7<=0),"Количество долей",""),IF(AND(X7<>"",X7<>INT(X7)),"Количество долей должно быть целым",""))="","",TEXTJOIN(", ",TRUE,IF(B7="","Название",""),IF(C7="","Тип недвижимости",""),IF(D7="","Страна",""),IF(E7="","Город",""),IF(F7="","Улица",""),IF(I7="","Валюта",""),IF(OR(AA7="",AA7<1),"Хотя бы 1 фото",""),IF(AND(OR(C7="Квартира",C7="Апартаменты",C7="Дом",C7="Вилла",C7="Коммерческая"),J7=""),"Площадь",""),IF(AND(OR(C7="Квартира",C7="Апартаменты"),K7=""),"Жилая площадь",""),IF(AND(OR(C7="Дом",C7="Вилла",C7="Земля"),L7=""),"Площадь участка",""),IF(AND(OR(C7="Квартира",C7="Апартаменты"),M7=""),"Комнаты",""),IF(AND(OR(C7="Дом",C7="Вилла"),N7=""),"Спальни",""),IF(AND(OR(C7="Квартира",C7="Апартаменты",C7="Дом",C7="Вилла"),O7=""),"Ванные",""),IF(AND(OR(C7="Квартира",C7="Апартаменты"),P7=""),"Этаж",""),IF(AND(OR(OR(C7="Квартира",C7="Апартаменты"),OR(C7="Дом",C7="Вилла")),Q7=""),"Этажей",""),IF(AND(OR(OR(C7="Квартира",C7="Апартаменты"),OR(C7="Дом",C7="Вилла")),OR(R7="",R7>YEAR(TODAY()))),"Год постройки",""),IF(AND(P7<>"",Q7<>"",P7>Q7),"Этаж больше этажности",""),IF(AND(OR(C7="Квартира",C7="Апартаменты",C7="Дом",C7="Вилла"),S7=""),"Материал",""),IF(AND(OR(C7="Коммерческая"),U7=""),"Тип коммерции",""),IF(AND(OR(C7="Земля"),V7=""),"Назначение земли",""),IF(OR(AF7="",AF7="Нет"),"Право собственности",""),IF(OR(AG7="",AG7="Нет"),"Справка об отсутствии обременений",""),IF(OR(W7="",W7<=0),"Общая стоимость",""),IF(OR(X7="",X7<=0),"Количество долей",""),IF(AND(X7<>"",X7<>INT(X7)),"Количество долей должно быть целым","")))) | AJ7: =IF(NOT(COUNTA(A7:AH7)>0),"",IF(TEXTJOIN(", ",TRUE,IF(AD7="","Описание",""),IF(AND(AA7<>"",AA7>=1,AA7<5),"Фото меньше 5",""),IF(AC7="","Видео",""),IF(H7="","Кадастровый номер",""),IF(AB7="","Ссылка на фото",""))="","",TEXTJOIN(", ",TRUE,IF(AD7="","Описание",""),IF(AND(AA7<>"",AA7>=1,AA7<5),"Фото меньше 5",""),IF(AC7="","Видео",""),IF(H7="","Кадастровый номер",""),IF(AB7="","Ссылка на фото","")))) | AK7: =IF(NOT(COUNTA(A7:AH7)>0),"",IF(AI7="","Можно публиковать","Не хватает"))
Y8: =IF(OR(W8="",X8="",X8<=0),"",W8/X8) | AI8: =IF(NOT(COUNTA(A8:AH8)>0),"",IF(TEXTJOIN(", ",TRUE,IF(B8="","Название",""),IF(C8="","Тип недвижимости",""),IF(D8="","Страна",""),IF(E8="","Город",""),IF(F8="","Улица",""),IF(I8="","Валюта",""),IF(OR(AA8="",AA8<1),"Хотя бы 1 фото",""),IF(AND(OR(C8="Квартира",C8="Апартаменты",C8="Дом",C8="Вилла",C8="Коммерческая"),J8=""),"Площадь",""),IF(AND(OR(C8="Квартира",C8="Апартаменты"),K8=""),"Жилая площадь",""),IF(AND(OR(C8="Дом",C8="Вилла",C8="Земля"),L8=""),"Площадь участка",""),IF(AND(OR(C8="Квартира",C8="Апартаменты"),M8=""),"Комнаты",""),IF(AND(OR(C8="Дом",C8="Вилла"),N8=""),"Спальни",""),IF(AND(OR(C8="Квартира",C8="Апартаменты",C8="Дом",C8="Вилла"),O8=""),"Ванные",""),IF(AND(OR(C8="Квартира",C8="Апартаменты"),P8=""),"Этаж",""),IF(AND(OR(OR(C8="Квартира",C8="Апартаменты"),OR(C8="Дом",C8="Вилла")),Q8=""),"Этажей",""),IF(AND(OR(OR(C8="Квартира",C8="Апартаменты"),OR(C8="Дом",C8="Вилла")),OR(R8="",R8>YEAR(TODAY()))),"Год постройки",""),IF(AND(P8<>"",Q8<>"",P8>Q8),"Этаж больше этажности",""),IF(AND(OR(C8="Квартира",C8="Апартаменты",C8="Дом",C8="Вилла"),S8=""),"Материал",""),IF(AND(OR(C8="Коммерческая"),U8=""),"Тип коммерции",""),IF(AND(OR(C8="Земля"),V8=""),"Назначение земли",""),IF(OR(AF8="",AF8="Нет"),"Право собственности",""),IF(OR(AG8="",AG8="Нет"),"Справка об отсутствии обременений",""),IF(OR(W8="",W8<=0),"Общая стоимость",""),IF(OR(X8="",X8<=0),"Количество долей",""),IF(AND(X8<>"",X8<>INT(X8)),"Количество долей должно быть целым",""))="","",TEXTJOIN(", ",TRUE,IF(B8="","Название",""),IF(C8="","Тип недвижимости",""),IF(D8="","Страна",""),IF(E8="","Город",""),IF(F8="","Улица",""),IF(I8="","Валюта",""),IF(OR(AA8="",AA8<1),"Хотя бы 1 фото",""),IF(AND(OR(C8="Квартира",C8="Апартаменты",C8="Дом",C8="Вилла",C8="Коммерческая"),J8=""),"Площадь",""),IF(AND(OR(C8="Квартира",C8="Апартаменты"),K8=""),"Жилая площадь",""),IF(AND(OR(C8="Дом",C8="Вилла",C8="Земля"),L8=""),"Площадь участка",""),IF(AND(OR(C8="Квартира",C8="Апартаменты"),M8=""),"Комнаты",""),IF(AND(OR(C8="Дом",C8="Вилла"),N8=""),"Спальни",""),IF(AND(OR(C8="Квартира",C8="Апартаменты",C8="Дом",C8="Вилла"),O8=""),"Ванные",""),IF(AND(OR(C8="Квартира",C8="Апартаменты"),P8=""),"Этаж",""),IF(AND(OR(OR(C8="Квартира",C8="Апартаменты"),OR(C8="Дом",C8="Вилла")),Q8=""),"Этажей",""),IF(AND(OR(OR(C8="Квартира",C8="Апартаменты"),OR(C8="Дом",C8="Вилла")),OR(R8="",R8>YEAR(TODAY()))),"Год постройки",""),IF(AND(P8<>"",Q8<>"",P8>Q8),"Этаж больше этажности",""),IF(AND(OR(C8="Квартира",C8="Апартаменты",C8="Дом",C8="Вилла"),S8=""),"Материал",""),IF(AND(OR(C8="Коммерческая"),U8=""),"Тип коммерции",""),IF(AND(OR(C8="Земля"),V8=""),"Назначение земли",""),IF(OR(AF8="",AF8="Нет"),"Право собственности",""),IF(OR(AG8="",AG8="Нет"),"Справка об отсутствии обременений",""),IF(OR(W8="",W8<=0),"Общая стоимость",""),IF(OR(X8="",X8<=0),"Количество долей",""),IF(AND(X8<>"",X8<>INT(X8)),"Количество долей должно быть целым","")))) | AJ8: =IF(NOT(COUNTA(A8:AH8)>0),"",IF(TEXTJOIN(", ",TRUE,IF(AD8="","Описание",""),IF(AND(AA8<>"",AA8>=1,AA8<5),"Фото меньше 5",""),IF(AC8="","Видео",""),IF(H8="","Кадастровый номер",""),IF(AB8="","Ссылка на фото",""))="","",TEXTJOIN(", ",TRUE,IF(AD8="","Описание",""),IF(AND(AA8<>"",AA8>=1,AA8<5),"Фото меньше 5",""),IF(AC8="","Видео",""),IF(H8="","Кадастровый номер",""),IF(AB8="","Ссылка на фото","")))) | AK8: =IF(NOT(COUNTA(A8:AH8)>0),"",IF(AI8="","Можно публиковать","Не хватает"))
Y9: =IF(OR(W9="",X9="",X9<=0),"",W9/X9) | AI9: =IF(NOT(COUNTA(A9:AH9)>0),"",IF(TEXTJOIN(", ",TRUE,IF(B9="","Название",""),IF(C9="","Тип недвижимости",""),IF(D9="","Страна",""),IF(E9="","Город",""),IF(F9="","Улица",""),IF(I9="","Валюта",""),IF(OR(AA9="",AA9<1),"Хотя бы 1 фото",""),IF(AND(OR(C9="Квартира",C9="Апартаменты",C9="Дом",C9="Вилла",C9="Коммерческая"),J9=""),"Площадь",""),IF(AND(OR(C9="Квартира",C9="Апартаменты"),K9=""),"Жилая площадь",""),IF(AND(OR(C9="Дом",C9="Вилла",C9="Земля"),L9=""),"Площадь участка",""),IF(AND(OR(C9="Квартира",C9="Апартаменты"),M9=""),"Комнаты",""),IF(AND(OR(C9="Дом",C9="Вилла"),N9=""),"Спальни",""),IF(AND(OR(C9="Квартира",C9="Апартаменты",C9="Дом",C9="Вилла"),O9=""),"Ванные",""),IF(AND(OR(C9="Квартира",C9="Апартаменты"),P9=""),"Этаж",""),IF(AND(OR(OR(C9="Квартира",C9="Апартаменты"),OR(C9="Дом",C9="Вилла")),Q9=""),"Этажей",""),IF(AND(OR(OR(C9="Квартира",C9="Апартаменты"),OR(C9="Дом",C9="Вилла")),OR(R9="",R9>YEAR(TODAY()))),"Год постройки",""),IF(AND(P9<>"",Q9<>"",P9>Q9),"Этаж больше этажности",""),IF(AND(OR(C9="Квартира",C9="Апартаменты",C9="Дом",C9="Вилла"),S9=""),"Материал",""),IF(AND(OR(C9="Коммерческая"),U9=""),"Тип коммерции",""),IF(AND(OR(C9="Земля"),V9=""),"Назначение земли",""),IF(OR(AF9="",AF9="Нет"),"Право собственности",""),IF(OR(AG9="",AG9="Нет"),"Справка об отсутствии обременений",""),IF(OR(W9="",W9<=0),"Общая стоимость",""),IF(OR(X9="",X9<=0),"Количество долей",""),IF(AND(X9<>"",X9<>INT(X9)),"Количество долей должно быть целым",""))="","",TEXTJOIN(", ",TRUE,IF(B9="","Название",""),IF(C9="","Тип недвижимости",""),IF(D9="","Страна",""),IF(E9="","Город",""),IF(F9="","Улица",""),IF(I9="","Валюта",""),IF(OR(AA9="",AA9<1),"Хотя бы 1 фото",""),IF(AND(OR(C9="Квартира",C9="Апартаменты",C9="Дом",C9="Вилла",C9="Коммерческая"),J9=""),"Площадь",""),IF(AND(OR(C9="Квартира",C9="Апартаменты"),K9=""),"Жилая площадь",""),IF(AND(OR(C9="Дом",C9="Вилла",C9="Земля"),L9=""),"Площадь участка",""),IF(AND(OR(C9="Квартира",C9="Апартаменты"),M9=""),"Комнаты",""),IF(AND(OR(C9="Дом",C9="Вилла"),N9=""),"Спальни",""),IF(AND(OR(C9="Квартира",C9="Апартаменты",C9="Дом",C9="Вилла"),O9=""),"Ванные",""),IF(AND(OR(C9="Квартира",C9="Апартаменты"),P9=""),"Этаж",""),IF(AND(OR(OR(C9="Квартира",C9="Апартаменты"),OR(C9="Дом",C9="Вилла")),Q9=""),"Этажей",""),IF(AND(OR(OR(C9="Квартира",C9="Апартаменты"),OR(C9="Дом",C9="Вилла")),OR(R9="",R9>YEAR(TODAY()))),"Год постройки",""),IF(AND(P9<>"",Q9<>"",P9>Q9),"Этаж больше этажности",""),IF(AND(OR(C9="Квартира",C9="Апартаменты",C9="Дом",C9="Вилла"),S9=""),"Материал",""),IF(AND(OR(C9="Коммерческая"),U9=""),"Тип коммерции",""),IF(AND(OR(C9="Земля"),V9=""),"Назначение земли",""),IF(OR(AF9="",AF9="Нет"),"Право собственности",""),IF(OR(AG9="",AG9="Нет"),"Справка об отсутствии обременений",""),IF(OR(W9="",W9<=0),"Общая стоимость",""),IF(OR(X9="",X9<=0),"Количество долей",""),IF(AND(X9<>"",X9<>INT(X9)),"Количество долей должно быть целым","")))) | AJ9: =IF(NOT(COUNTA(A9:AH9)>0),"",IF(TEXTJOIN(", ",TRUE,IF(AD9="","Описание",""),IF(AND(AA9<>"",AA9>=1,AA9<5),"Фото меньше 5",""),IF(AC9="","Видео",""),IF(H9="","Кадастровый номер",""),IF(AB9="","Ссылка на фото",""))="","",TEXTJOIN(", ",TRUE,IF(AD9="","Описание",""),IF(AND(AA9<>"",AA9>=1,AA9<5),"Фото меньше 5",""),IF(AC9="","Видео",""),IF(H9="","Кадастровый номер",""),IF(AB9="","Ссылка на фото","")))) | AK9: =IF(NOT(COUNTA(A9:AH9)>0),"",IF(AI9="","Можно публиковать","Не хватает"))
Y10: =IF(OR(W10="",X10="",X10<=0),"",W10/X10) | AI10: =IF(NOT(COUNTA(A10:AH10)>0),"",IF(TEXTJOIN(", ",TRUE,IF(B10="","Название",""),IF(C10="","Тип недвижимости",""),IF(D10="","Страна",""),IF(E10="","Город",""),IF(F10="","Улица",""),IF(I10="","Валюта",""),IF(OR(AA10="",AA10<1),"Хотя бы 1 фото",""),IF(AND(OR(C10="Квартира",C10="Апартаменты",C10="Дом",C10="Вилла",C10="Коммерческая"),J10=""),"Площадь",""),IF(AND(OR(C10="Квартира",C10="Апартаменты"),K10=""),"Жилая площадь",""),IF(AND(OR(C10="Дом",C10="Вилла",C10="Земля"),L10=""),"Площадь участка",""),IF(AND(OR(C10="Квартира",C10="Апартаменты"),M10=""),"Комнаты",""),IF(AND(OR(C10="Дом",C10="Вилла"),N10=""),"Спальни",""),IF(AND(OR(C10="Квартира",C10="Апартаменты",C10="Дом",C10="Вилла"),O10=""),"Ванные",""),IF(AND(OR(C10="Квартира",C10="Апартаменты"),P10=""),"Этаж",""),IF(AND(OR(OR(C10="Квартира",C10="Апартаменты"),OR(C10="Дом",C10="Вилла")),Q10=""),"Этажей",""),IF(AND(OR(OR(C10="Квартира",C10="Апартаменты"),OR(C10="Дом",C10="Вилла")),OR(R10="",R10>YEAR(TODAY()))),"Год постройки",""),IF(AND(P10<>"",Q10<>"",P10>Q10),"Этаж больше этажности",""),IF(AND(OR(C10="Квартира",C10="Апартаменты",C10="Дом",C10="Вилла"),S10=""),"Материал",""),IF(AND(OR(C10="Коммерческая"),U10=""),"Тип коммерции",""),IF(AND(OR(C10="Земля"),V10=""),"Назначение земли",""),IF(OR(AF10="",AF10="Нет"),"Право собственности",""),IF(OR(AG10="",AG10="Нет"),"Справка об отсутствии обременений",""),IF(OR(W10="",W10<=0),"Общая стоимость",""),IF(OR(X10="",X10<=0),"Количество долей",""),IF(AND(X10<>"",X10<>INT(X10)),"Количество долей должно быть целым",""))="","",TEXTJOIN(", ",TRUE,IF(B10="","Название",""),IF(C10="","Тип недвижимости",""),IF(D10="","Страна",""),IF(E10="","Город",""),IF(F10="","Улица",""),IF(I10="","Валюта",""),IF(OR(AA10="",AA10<1),"Хотя бы 1 фото",""),IF(AND(OR(C10="Квартира",C10="Апартаменты",C10="Дом",C10="Вилла",C10="Коммерческая"),J10=""),"Площадь",""),IF(AND(OR(C10="Квартира",C10="Апартаменты"),K10=""),"Жилая площадь",""),IF(AND(OR(C10="Дом",C10="Вилла",C10="Земля"),L10=""),"Площадь участка",""),IF(AND(OR(C10="Квартира",C10="Апартаменты"),M10=""),"Комнаты",""),IF(AND(OR(C10="Дом",C10="Вилла"),N10=""),"Спальни",""),IF(AND(OR(C10="Квартира",C10="Апартаменты",C10="Дом",C10="Вилла"),O10=""),"Ванные",""),IF(AND(OR(C10="Квартира",C10="Апартаменты"),P10=""),"Этаж",""),IF(AND(OR(OR(C10="Квартира",C10="Апартаменты"),OR(C10="Дом",C10="Вилла")),Q10=""),"Этажей",""),IF(AND(OR(OR(C10="Квартира",C10="Апартаменты"),OR(C10="Дом",C10="Вилла")),OR(R10="",R10>YEAR(TODAY()))),"Год постройки",""),IF(AND(P10<>"",Q10<>"",P10>Q10),"Этаж больше этажности",""),IF(AND(OR(C10="Квартира",C10="Апартаменты",C10="Дом",C10="Вилла"),S10=""),"Материал",""),IF(AND(OR(C10="Коммерческая"),U10=""),"Тип коммерции",""),IF(AND(OR(C10="Земля"),V10=""),"Назначение земли",""),IF(OR(AF10="",AF10="Нет"),"Право собственности",""),IF(OR(AG10="",AG10="Нет"),"Справка об отсутствии обременений",""),IF(OR(W10="",W10<=0),"Общая стоимость",""),IF(OR(X10="",X10<=0),"Количество долей",""),IF(AND(X10<>"",X10<>INT(X10)),"Количество долей должно быть целым","")))) | AJ10: =IF(NOT(COUNTA(A10:AH10)>0),"",IF(TEXTJOIN(", ",TRUE,IF(AD10="","Описание",""),IF(AND(AA10<>"",AA10>=1,AA10<5),"Фото меньше 5",""),IF(AC10="","Видео",""),IF(H10="","Кадастровый номер",""),IF(AB10="","Ссылка на фото",""))="","",TEXTJOIN(", ",TRUE,IF(AD10="","Описание",""),IF(AND(AA10<>"",AA10>=1,AA10<5),"Фото меньше 5",""),IF(AC10="","Видео",""),IF(H10="","Кадастровый номер",""),IF(AB10="","Ссылка на фото","")))) | AK10: =IF(NOT(COUNTA(A10:AH10)>0),"",IF(AI10="","Можно публиковать","Не хватает"))
Y11: =IF(OR(W11="",X11="",X11<=0),"",W11/X11) | AI11: =IF(NOT(COUNTA(A11:AH11)>0),"",IF(TEXTJOIN(", ",TRUE,IF(B11="","Название",""),IF(C11="","Тип недвижимости",""),IF(D11="","Страна",""),IF(E11="","Город",""),IF(F11="","Улица",""),IF(I11="","Валюта",""),IF(OR(AA11="",AA11<1),"Хотя бы 1 фото",""),IF(AND(OR(C11="Квартира",C11="Апартаменты",C11="Дом",C11="Вилла",C11="Коммерческая"),J11=""),"Площадь",""),IF(AND(OR(C11="Квартира",C11="Апартаменты"),K11=""),"Жилая площадь",""),IF(AND(OR(C11="Дом",C11="Вилла",C11="Земля"),L11=""),"Площадь участка",""),IF(AND(OR(C11="Квартира",C11="Апартаменты"),M11=""),"Комнаты",""),IF(AND(OR(C11="Дом",C11="Вилла"),N11=""),"Спальни",""),IF(AND(OR(C11="Квартира",C11="Апартаменты",C11="Дом",C11="Вилла"),O11=""),"Ванные",""),IF(AND(OR(C11="Квартира",C11="Апартаменты"),P11=""),"Этаж",""),IF(AND(OR(OR(C11="Квартира",C11="Апартаменты"),OR(C11="Дом",C11="Вилла")),Q11=""),"Этажей",""),IF(AND(OR(OR(C11="Квартира",C11="Апартаменты"),OR(C11="Дом",C11="Вилла")),OR(R11="",R11>YEAR(TODAY()))),"Год постройки",""),IF(AND(P11<>"",Q11<>"",P11>Q11),"Этаж больше этажности",""),IF(AND(OR(C11="Квартира",C11="Апартаменты",C11="Дом",C11="Вилла"),S11=""),"Материал",""),IF(AND(OR(C11="Коммерческая"),U11=""),"Тип коммерции",""),IF(AND(OR(C11="Земля"),V11=""),"Назначение земли",""),IF(OR(AF11="",AF11="Нет"),"Право собственности",""),IF(OR(AG11="",AG11="Нет"),"Справка об отсутствии обременений",""),IF(OR(W11="",W11<=0),"Общая стоимость",""),IF(OR(X11="",X11<=0),"Количество долей",""),IF(AND(X11<>"",X11<>INT(X11)),"Количество долей должно быть целым",""))="","",TEXTJOIN(", ",TRUE,IF(B11="","Название",""),IF(C11="","Тип недвижимости",""),IF(D11="","Страна",""),IF(E11="","Город",""),IF(F11="","Улица",""),IF(I11="","Валюта",""),IF(OR(AA11="",AA11<1),"Хотя бы 1 фото",""),IF(AND(OR(C11="Квартира",C11="Апартаменты",C11="Дом",C11="Вилла",C11="Коммерческая"),J11=""),"Площадь",""),IF(AND(OR(C11="Квартира",C11="Апартаменты"),K11=""),"Жилая площадь",""),IF(AND(OR(C11="Дом",C11="Вилла",C11="Земля"),L11=""),"Площадь участка",""),IF(AND(OR(C11="Квартира",C11="Апартаменты"),M11=""),"Комнаты",""),IF(AND(OR(C11="Дом",C11="Вилла"),N11=""),"Спальни",""),IF(AND(OR(C11="Квартира",C11="Апартаменты",C11="Дом",C11="Вилла"),O11=""),"Ванные",""),IF(AND(OR(C11="Квартира",C11="Апартаменты"),P11=""),"Этаж",""),IF(AND(OR(OR(C11="Квартира",C11="Апартаменты"),OR(C11="Дом",C11="Вилла")),Q11=""),"Этажей",""),IF(AND(OR(OR(C11="Квартира",C11="Апартаменты"),OR(C11="Дом",C11="Вилла")),OR(R11="",R11>YEAR(TODAY()))),"Год постройки",""),IF(AND(P11<>"",Q11<>"",P11>Q11),"Этаж больше этажности",""),IF(AND(OR(C11="Квартира",C11="Апартаменты",C11="Дом",C11="Вилла"),S11=""),"Материал",""),IF(AND(OR(C11="Коммерческая"),U11=""),"Тип коммерции",""),IF(AND(OR(C11="Земля"),V11=""),"Назначение земли",""),IF(OR(AF11="",AF11="Нет"),"Право собственности",""),IF(OR(AG11="",AG11="Нет"),"Справка об отсутствии обременений",""),IF(OR(W11="",W11<=0),"Общая стоимость",""),IF(OR(X11="",X11<=0),"Количество долей",""),IF(AND(X11<>"",X11<>INT(X11)),"Количество долей должно быть целым","")))) | AJ11: =IF(NOT(COUNTA(A11:AH11)>0),"",IF(TEXTJOIN(", ",TRUE,IF(AD11="","Описание",""),IF(AND(AA11<>"",AA11>=1,AA11<5),"Фото меньше 5",""),IF(AC11="","Видео",""),IF(H11="","Кадастровый номер",""),IF(AB11="","Ссылка на фото",""))="","",TEXTJOIN(", ",TRUE,IF(AD11="","Описание",""),IF(AND(AA11<>"",AA11>=1,AA11<5),"Фото меньше 5",""),IF(AC11="","Видео",""),IF(H11="","Кадастровый номер",""),IF(AB11="","Ссылка на фото","")))) | AK11: =IF(NOT(COUNTA(A11:AH11)>0),"",IF(AI11="","Можно публиковать","Не хватает"))
Y12: =IF(OR(W12="",X12="",X12<=0),"",W12/X12) | AI12: =IF(NOT(COUNTA(A12:AH12)>0),"",IF(TEXTJOIN(", ",TRUE,IF(B12="","Название",""),IF(C12="","Тип недвижимости",""),IF(D12="","Страна",""),IF(E12="","Город",""),IF(F12="","Улица",""),IF(I12="","Валюта",""),IF(OR(AA12="",AA12<1),"Хотя бы 1 фото",""),IF(AND(OR(C12="Квартира",C12="Апартаменты",C12="Дом",C12="Вилла",C12="Коммерческая"),J12=""),"Площадь",""),IF(AND(OR(C12="Квартира",C12="Апартаменты"),K12=""),"Жилая площадь",""),IF(AND(OR(C12="Дом",C12="Вилла",C12="Земля"),L12=""),"Площадь участка",""),IF(AND(OR(C12="Квартира",C12="Апартаменты"),M12=""),"Комнаты",""),IF(AND(OR(C12="Дом",C12="Вилла"),N12=""),"Спальни",""),IF(AND(OR(C12="Квартира",C12="Апартаменты",C12="Дом",C12="Вилла"),O12=""),"Ванные",""),IF(AND(OR(C12="Квартира",C12="Апартаменты"),P12=""),"Этаж",""),IF(AND(OR(OR(C12="Квартира",C12="Апартаменты"),OR(C12="Дом",C12="Вилла")),Q12=""),"Этажей",""),IF(AND(OR(OR(C12="Квартира",C12="Апартаменты"),OR(C12="Дом",C12="Вилла")),OR(R12="",R12>YEAR(TODAY()))),"Год постройки",""),IF(AND(P12<>"",Q12<>"",P12>Q12),"Этаж больше этажности",""),IF(AND(OR(C12="Квартира",C12="Апартаменты",C12="Дом",C12="Вилла"),S12=""),"Материал",""),IF(AND(OR(C12="Коммерческая"),U12=""),"Тип коммерции",""),IF(AND(OR(C12="Земля"),V12=""),"Назначение земли",""),IF(OR(AF12="",AF12="Нет"),"Право собственности",""),IF(OR(AG12="",AG12="Нет"),"Справка об отсутствии обременений",""),IF(OR(W12="",W12<=0),"Общая стоимость",""),IF(OR(X12="",X12<=0),"Количество долей",""),IF(AND(X12<>"",X12<>INT(X12)),"Количество долей должно быть целым",""))="","",TEXTJOIN(", ",TRUE,IF(B12="","Название",""),IF(C12="","Тип недвижимости",""),IF(D12="","Страна",""),IF(E12="","Город",""),IF(F12="","Улица",""),IF(I12="","Валюта",""),IF(OR(AA12="",AA12<1),"Хотя бы 1 фото",""),IF(AND(OR(C12="Квартира",C12="Апартаменты",C12="Дом",C12="Вилла",C12="Коммерческая"),J12=""),"Площадь",""),IF(AND(OR(C12="Квартира",C12="Апартаменты"),K12=""),"Жилая площадь",""),IF(AND(OR(C12="Дом",C12="Вилла",C12="Земля"),L12=""),"Площадь участка",""),IF(AND(OR(C12="Квартира",C12="Апартаменты"),M12=""),"Комнаты",""),IF(AND(OR(C12="Дом",C12="Вилла"),N12=""),"Спальни",""),IF(AND(OR(C12="Квартира",C12="Апартаменты",C12="Дом",C12="Вилла"),O12=""),"Ванные",""),IF(AND(OR(C12="Квартира",C12="Апартаменты"),P12=""),"Этаж",""),IF(AND(OR(OR(C12="Квартира",C12="Апартаменты"),OR(C12="Дом",C12="Вилла")),Q12=""),"Этажей",""),IF(AND(OR(OR(C12="Квартира",C12="Апартаменты"),OR(C12="Дом",C12="Вилла")),OR(R12="",R12>YEAR(TODAY()))),"Год постройки",""),IF(AND(P12<>"",Q12<>"",P12>Q12),"Этаж больше этажности",""),IF(AND(OR(C12="Квартира",C12="Апартаменты",C12="Дом",C12="Вилла"),S12=""),"Материал",""),IF(AND(OR(C12="Коммерческая"),U12=""),"Тип коммерции",""),IF(AND(OR(C12="Земля"),V12=""),"Назначение земли",""),IF(OR(AF12="",AF12="Нет"),"Право собственности",""),IF(OR(AG12="",AG12="Нет"),"Справка об отсутствии обременений",""),IF(OR(W12="",W12<=0),"Общая стоимость",""),IF(OR(X12="",X12<=0),"Количество долей",""),IF(AND(X12<>"",X12<>INT(X12)),"Количество долей должно быть целым","")))) | AJ12: =IF(NOT(COUNTA(A12:AH12)>0),"",IF(TEXTJOIN(", ",TRUE,IF(AD12="","Описание",""),IF(AND(AA12<>"",AA12>=1,AA12<5),"Фото меньше 5",""),IF(AC12="","Видео",""),IF(H12="","Кадастровый номер",""),IF(AB12="","Ссылка на фото",""))="","",TEXTJOIN(", ",TRUE,IF(AD12="","Описание",""),IF(AND(AA12<>"",AA12>=1,AA12<5),"Фото меньше 5",""),IF(AC12="","Видео",""),IF(H12="","Кадастровый номер",""),IF(AB12="","Ссылка на фото","")))) | AK12: =IF(NOT(COUNTA(A12:AH12)>0),"",IF(AI12="","Можно публиковать","Не хватает"))
Y13: =IF(OR(W13="",X13="",X13<=0),"",W13/X13) | AI13: =IF(NOT(COUNTA(A13:AH13)>0),"",IF(TEXTJOIN(", ",TRUE,IF(B13="","Название",""),IF(C13="","Тип недвижимости",""),IF(D13="","Страна",""),IF(E13="","Город",""),IF(F13="","Улица",""),IF(I13="","Валюта",""),IF(OR(AA13="",AA13<1),"Хотя бы 1 фото",""),IF(AND(OR(C13="Квартира",C13="Апартаменты",C13="Дом",C13="Вилла",C13="Коммерческая"),J13=""),"Площадь",""),IF(AND(OR(C13="Квартира",C13="Апартаменты"),K13=""),"Жилая площадь",""),IF(AND(OR(C13="Дом",C13="Вилла",C13="Земля"),L13=""),"Площадь участка",""),IF(AND(OR(C13="Квартира",C13="Апартаменты"),M13=""),"Комнаты",""),IF(AND(OR(C13="Дом",C13="Вилла"),N13=""),"Спальни",""),IF(AND(OR(C13="Квартира",C13="Апартаменты",C13="Дом",C13="Вилла"),O13=""),"Ванные",""),IF(AND(OR(C13="Квартира",C13="Апартаменты"),P13=""),"Этаж",""),IF(AND(OR(OR(C13="Квартира",C13="Апартаменты"),OR(C13="Дом",C13="Вилла")),Q13=""),"Этажей",""),IF(AND(OR(OR(C13="Квартира",C13="Апартаменты"),OR(C13="Дом",C13="Вилла")),OR(R13="",R13>YEAR(TODAY()))),"Год постройки",""),IF(AND(P13<>"",Q13<>"",P13>Q13),"Этаж больше этажности",""),IF(AND(OR(C13="Квартира",C13="Апартаменты",C13="Дом",C13="Вилла"),S13=""),"Материал",""),IF(AND(OR(C13="Коммерческая"),U13=""),"Тип коммерции",""),IF(AND(OR(C13="Земля"),V13=""),"Назначение земли",""),IF(OR(AF13="",AF13="Нет"),"Право собственности",""),IF(OR(AG13="",AG13="Нет"),"Справка об отсутствии обременений",""),IF(OR(W13="",W13<=0),"Общая стоимость",""),IF(OR(X13="",X13<=0),"Количество долей",""),IF(AND(X13<>"",X13<>INT(X13)),"Количество долей должно быть целым",""))="","",TEXTJOIN(", ",TRUE,IF(B13="","Название",""),IF(C13="","Тип недвижимости",""),IF(D13="","Страна",""),IF(E13="","Город",""),IF(F13="","Улица",""),IF(I13="","Валюта",""),IF(OR(AA13="",AA13<1),"Хотя бы 1 фото",""),IF(AND(OR(C13="Квартира",C13="Апартаменты",C13="Дом",C13="Вилла",C13="Коммерческая"),J13=""),"Площадь",""),IF(AND(OR(C13="Квартира",C13="Апартаменты"),K13=""),"Жилая площадь",""),IF(AND(OR(C13="Дом",C13="Вилла",C13="Земля"),L13=""),"Площадь участка",""),IF(AND(OR(C13="Квартира",C13="Апартаменты"),M13=""),"Комнаты",""),IF(AND(OR(C13="Дом",C13="Вилла"),N13=""),"Спальни",""),IF(AND(OR(C13="Квартира",C13="Апартаменты",C13="Дом",C13="Вилла"),O13=""),"Ванные",""),IF(AND(OR(C13="Квартира",C13="Апартаменты"),P13=""),"Этаж",""),IF(AND(OR(OR(C13="Квартира",C13="Апартаменты"),OR(C13="Дом",C13="Вилла")),Q13=""),"Этажей",""),IF(AND(OR(OR(C13="Квартира",C13="Апартаменты"),OR(C13="Дом",C13="Вилла")),OR(R13="",R13>YEAR(TODAY()))),"Год постройки",""),IF(AND(P13<>"",Q13<>"",P13>Q13),"Этаж больше этажности",""),IF(AND(OR(C13="Квартира",C13="Апартаменты",C13="Дом",C13="Вилла"),S13=""),"Материал",""),IF(AND(OR(C13="Коммерческая"),U13=""),"Тип коммерции",""),IF(AND(OR(C13="Земля"),V13=""),"Назначение земли",""),IF(OR(AF13="",AF13="Нет"),"Право собственности",""),IF(OR(AG13="",AG13="Нет"),"Справка об отсутствии обременений",""),IF(OR(W13="",W13<=0),"Общая стоимость",""),IF(OR(X13="",X13<=0),"Количество долей",""),IF(AND(X13<>"",X13<>INT(X13)),"Количество долей должно быть целым","")))) | AJ13: =IF(NOT(COUNTA(A13:AH13)>0),"",IF(TEXTJOIN(", ",TRUE,IF(AD13="","Описание",""),IF(AND(AA13<>"",AA13>=1,AA13<5),"Фото меньше 5",""),IF(AC13="","Видео",""),IF(H13="","Кадастровый номер",""),IF(AB13="","Ссылка на фото",""))="","",TEXTJOIN(", ",TRUE,IF(AD13="","Описание",""),IF(AND(AA13<>"",AA13>=1,AA13<5),"Фото меньше 5",""),IF(AC13="","Видео",""),IF(H13="","Кадастровый номер",""),IF(AB13="","Ссылка на фото","")))) | AK13: =IF(NOT(COUNTA(A13:AH13)>0),"",IF(AI13="","Можно публиковать","Не хватает"))
Y14: =IF(OR(W14="",X14="",X14<=0),"",W14/X14) | AI14: =IF(NOT(COUNTA(A14:AH14)>0),"",IF(TEXTJOIN(", ",TRUE,IF(B14="","Название",""),IF(C14="","Тип недвижимости",""),IF(D14="","Страна",""),IF(E14="","Город",""),IF(F14="","Улица",""),IF(I14="","Валюта",""),IF(OR(AA14="",AA14<1),"Хотя бы 1 фото",""),IF(AND(OR(C14="Квартира",C14="Апартаменты",C14="Дом",C14="Вилла",C14="Коммерческая"),J14=""),"Площадь",""),IF(AND(OR(C14="Квартира",C14="Апартаменты"),K14=""),"Жилая площадь",""),IF(AND(OR(C14="Дом",C14="Вилла",C14="Земля"),L14=""),"Площадь участка",""),IF(AND(OR(C14="Квартира",C14="Апартаменты"),M14=""),"Комнаты",""),IF(AND(OR(C14="Дом",C14="Вилла"),N14=""),"Спальни",""),IF(AND(OR(C14="Квартира",C14="Апартаменты",C14="Дом",C14="Вилла"),O14=""),"Ванные",""),IF(AND(OR(C14="Квартира",C14="Апартаменты"),P14=""),"Этаж",""),IF(AND(OR(OR(C14="Квартира",C14="Апартаменты"),OR(C14="Дом",C14="Вилла")),Q14=""),"Этажей",""),IF(AND(OR(OR(C14="Квартира",C14="Апартаменты"),OR(C14="Дом",C14="Вилла")),OR(R14="",R14>YEAR(TODAY()))),"Год постройки",""),IF(AND(P14<>"",Q14<>"",P14>Q14),"Этаж больше этажности",""),IF(AND(OR(C14="Квартира",C14="Апартаменты",C14="Дом",C14="Вилла"),S14=""),"Материал",""),IF(AND(OR(C14="Коммерческая"),U14=""),"Тип коммерции",""),IF(AND(OR(C14="Земля"),V14=""),"Назначение земли",""),IF(OR(AF14="",AF14="Нет"),"Право собственности",""),IF(OR(AG14="",AG14="Нет"),"Справка об отсутствии обременений",""),IF(OR(W14="",W14<=0),"Общая стоимость",""),IF(OR(X14="",X14<=0),"Количество долей",""),IF(AND(X14<>"",X14<>INT(X14)),"Количество долей должно быть целым",""))="","",TEXTJOIN(", ",TRUE,IF(B14="","Название",""),IF(C14="","Тип недвижимости",""),IF(D14="","Страна",""),IF(E14="","Город",""),IF(F14="","Улица",""),IF(I14="","Валюта",""),IF(OR(AA14="",AA14<1),"Хотя бы 1 фото",""),IF(AND(OR(C14="Квартира",C14="Апартаменты",C14="Дом",C14="Вилла",C14="Коммерческая"),J14=""),"Площадь",""),IF(AND(OR(C14="Квартира",C14="Апартаменты"),K14=""),"Жилая площадь",""),IF(AND(OR(C14="Дом",C14="Вилла",C14="Земля"),L14=""),"Площадь участка",""),IF(AND(OR(C14="Квартира",C14="Апартаменты"),M14=""),"Комнаты",""),IF(AND(OR(C14="Дом",C14="Вилла"),N14=""),"Спальни",""),IF(AND(OR(C14="Квартира",C14="Апартаменты",C14="Дом",C14="Вилла"),O14=""),"Ванные",""),IF(AND(OR(C14="Квартира",C14="Апартаменты"),P14=""),"Этаж",""),IF(AND(OR(OR(C14="Квартира",C14="Апартаменты"),OR(C14="Дом",C14="Вилла")),Q14=""),"Этажей",""),IF(AND(OR(OR(C14="Квартира",C14="Апартаменты"),OR(C14="Дом",C14="Вилла")),OR(R14="",R14>YEAR(TODAY()))),"Год постройки",""),IF(AND(P14<>"",Q14<>"",P14>Q14),"Этаж больше этажности",""),IF(AND(OR(C14="Квартира",C14="Апартаменты",C14="Дом",C14="Вилла"),S14=""),"Материал",""),IF(AND(OR(C14="Коммерческая"),U14=""),"Тип коммерции",""),IF(AND(OR(C14="Земля"),V14=""),"Назначение земли",""),IF(OR(AF14="",AF14="Нет"),"Право собственности",""),IF(OR(AG14="",AG14="Нет"),"Справка об отсутствии обременений",""),IF(OR(W14="",W14<=0),"Общая стоимость",""),IF(OR(X14="",X14<=0),"Количество долей",""),IF(AND(X14<>"",X14<>INT(X14)),"Количество долей должно быть целым","")))) | AJ14: =IF(NOT(COUNTA(A14:AH14)>0),"",IF(TEXTJOIN(", ",TRUE,IF(AD14="","Описание",""),IF(AND(AA14<>"",AA14>=1,AA14<5),"Фото меньше 5",""),IF(AC14="","Видео",""),IF(H14="","Кадастровый номер",""),IF(AB14="","Ссылка на фото",""))="","",TEXTJOIN(", ",TRUE,IF(AD14="","Описание",""),IF(AND(AA14<>"",AA14>=1,AA14<5),"Фото меньше 5",""),IF(AC14="","Видео",""),IF(H14="","Кадастровый номер",""),IF(AB14="","Ссылка на фото","")))) | AK14: =IF(NOT(COUNTA(A14:AH14)>0),"",IF(AI14="","Можно публиковать","Не хватает"))
... Y82: =IF(OR(W82="",X82="",X82<=0),"",W82/X82) | AI82: =IF(NOT(COUNTA(A82:AH82)>0),"",IF(TEXTJOIN(", ",TRUE,IF(B82="","Название",""),IF(C82="","Тип недвижимости",""),IF(D82="","Страна",""),IF(E82="","Город",""),IF(F82="","Улица",""),IF(I82="","Валюта",""),IF(OR(AA82="",AA82<1),"Хотя бы 1 фото",""),IF(AND(OR(C82="Квартира",C82="Апартаменты",C82="Дом",C82="Вилла",C82="Коммерческая"),J82=""),"Площадь",""),IF(AND(OR(C82="Квартира",C82="Апартаменты"),K82=""),"Жилая площадь",""),IF(AND(OR(C82="Дом",C82="Вилла",C82="Земля"),L82=""),"Площадь участка",""),IF(AND(OR(C82="Квартира",C82="Апартаменты"),M82=""),"Комнаты",""),IF(AND(OR(C82="Дом",C82="Вилла"),N82=""),"Спальни",""),IF(AND(OR(C82="Квартира",C82="Апартаменты",C82="Дом",C82="Вилла"),O82=""),"Ванные",""),IF(AND(OR(C82="Квартира",C82="Апартаменты"),P82=""),"Этаж",""),IF(AND(OR(OR(C82="Квартира",C82="Апартаменты"),OR(C82="Дом",C82="Вилла")),Q82=""),"Этажей",""),IF(AND(OR(OR(C82="Квартира",C82="Апартаменты"),OR(C82="Дом",C82="Вилла")),OR(R82="",R82>YEAR(TODAY()))),"Год постройки",""),IF(AND(P82<>"",Q82<>"",P82>Q82),"Этаж больше этажности",""),IF(AND(OR(C82="Квартира",C82="Апартаменты",C82="Дом",C82="Вилла"),S82=""),"Материал",""),IF(AND(OR(C82="Коммерческая"),U82=""),"Тип коммерции",""),IF(AND(OR(C82="Земля"),V82=""),"Назначение земли",""),IF(OR(AF82="",AF82="Нет"),"Право собственности",""),IF(OR(AG82="",AG82="Нет"),"Справка об отсутствии обременений",""),IF(OR(W82="",W82<=0),"Общая стоимость",""),IF(OR(X82="",X82<=0),"Количество долей",""),IF(AND(X82<>"",X82<>INT(X82)),"Количество долей должно быть целым",""))="","",TEXTJOIN(", ",TRUE,IF(B82="","Название",""),IF(C82="","Тип недвижимости",""),IF(D82="","Страна",""),IF(E82="","Город",""),IF(F82="","Улица",""),IF(I82="","Валюта",""),IF(OR(AA82="",AA82<1),"Хотя бы 1 фото",""),IF(AND(OR(C82="Квартира",C82="Апартаменты",C82="Дом",C82="Вилла",C82="Коммерческая"),J82=""),"Площадь",""),IF(AND(OR(C82="Квартира",C82="Апартаменты"),K82=""),"Жилая площадь",""),IF(AND(OR(C82="Дом",C82="Вилла",C82="Земля"),L82=""),"Площадь участка",""),IF(AND(OR(C82="Квартира",C82="Апартаменты"),M82=""),"Комнаты",""),IF(AND(OR(C82="Дом",C82="Вилла"),N82=""),"Спальни",""),IF(AND(OR(C82="Квартира",C82="Апартаменты",C82="Дом",C82="Вилла"),O82=""),"Ванные",""),IF(AND(OR(C82="Квартира",C82="Апартаменты"),P82=""),"Этаж",""),IF(AND(OR(OR(C82="Квартира",C82="Апартаменты"),OR(C82="Дом",C82="Вилла")),Q82=""),"Этажей",""),IF(AND(OR(OR(C82="Квартира",C82="Апартаменты"),OR(C82="Дом",C82="Вилла")),OR(R82="",R82>YEAR(TODAY()))),"Год постройки",""),IF(AND(P82<>"",Q82<>"",P82>Q82),"Этаж больше этажности",""),IF(AND(OR(C82="Квартира",C82="Апартаменты",C82="Дом",C82="Вилла"),S82=""),"Материал",""),IF(AND(OR(C82="Коммерческая"),U82=""),"Тип коммерции",""),IF(AND(OR(C82="Земля"),V82=""),"Назначение земли",""),IF(OR(AF82="",AF82="Нет"),"Право собственности",""),IF(OR(AG82="",AG82="Нет"),"Справка об отсутствии обременений",""),IF(OR(W82="",W82<=0),"Общая стоимость",""),IF(OR(X82="",X82<=0),"Количество долей",""),IF(AND(X82<>"",X82<>INT(X82)),"Количество долей должно быть целым","")))) | AJ82: =IF(NOT(COUNTA(A82:AH82)>0),"",IF(TEXTJOIN(", ",TRUE,IF(AD82="","Описание",""),IF(AND(AA82<>"",AA82>=1,AA82<5),"Фото меньше 5",""),IF(AC82="","Видео",""),IF(H82="","Кадастровый номер",""),IF(AB82="","Ссылка на фото",""))="","",TEXTJOIN(", ",TRUE,IF(AD82="","Описание",""),IF(AND(AA82<>"",AA82>=1,AA82<5),"Фото меньше 5",""),IF(AC82="","Видео",""),IF(H82="","Кадастровый номер",""),IF(AB82="","Ссылка на фото","")))) | AK82: =IF(NOT(COUNTA(A82:AH82)>0),"",IF(AI82="","Можно публиковать","Не хватает"))

Sheet Долги
A1: Сбор | B1: Объект | D1: Адрес | I1: Объект | J1: Параметры | W1: Долг | Y1: Аукцион долга | AD1: Пакет долга | AI1: Подача | AN1: Пакет долга | AO1: Проверка
A2: Источник | B2: Название | C2: Тип недвижимости | D2: Страна | E2: Город | F2: Улица | G2: Номер дома | H2: Кадастровый номер | I2: Валюта | J2: Площадь, м² | K2: Жилая, м² | L2: Участок, м² | M2: Комнаты | N2: Спальни | O2: Ванные | P2: Этаж | Q2: Этажей | R2: Год | S2: Материал | T2: Конструкция | U2: Тип коммерции | V2: Назначение земли | W2: Формат долга | X2: Сумма долга | Y2: Продать сейчас | Z2: Минимальная цена | AA2: Стартовая ставка | AB2: Начало аукциона | AC2: Окончание аукциона | AD2: Кредитный договор | AE2: Закладная | AF2: Выписка реестра | AG2: Оценка | AH2: Статус в суде | AI2: Фото, шт. | AJ2: Ссылка на фото | AK2: Ссылка на видео | AL2: Описание | AM2: Удобства | AN2: Ссылки на документы | AO2: Не хватает для публикации | AP2: Желательно добрать | AQ2: Готовность
AO3: =IF(NOT(COUNTA(A3:AN3)>0),"",IF(TEXTJOIN(", ",TRUE,IF(B3="","Название",""),IF(C3="","Тип недвижимости",""),IF(D3="","Страна",""),IF(E3="","Город",""),IF(F3="","Улица",""),IF(I3="","Валюта",""),IF(OR(AI3="",AI3<1),"Хотя бы 1 фото",""),IF(AND(OR(C3="Квартира",C3="Апартаменты",C3="Дом",C3="Вилла",C3="Коммерческая"),J3=""),"Площадь",""),IF(AND(OR(C3="Квартира",C3="Апартаменты"),K3=""),"Жилая площадь",""),IF(AND(OR(C3="Дом",C3="Вилла",C3="Земля"),L3=""),"Площадь участка",""),IF(AND(OR(C3="Квартира",C3="Апартаменты"),M3=""),"Комнаты",""),IF(AND(OR(C3="Дом",C3="Вилла"),N3=""),"Спальни",""),IF(AND(OR(C3="Квартира",C3="Апартаменты",C3="Дом",C3="Вилла"),O3=""),"Ванные",""),IF(AND(OR(C3="Квартира",C3="Апартаменты"),P3=""),"Этаж",""),IF(AND(OR(OR(C3="Квартира",C3="Апартаменты"),OR(C3="Дом",C3="Вилла")),Q3=""),"Этажей",""),IF(AND(OR(OR(C3="Квартира",C3="Апартаменты"),OR(C3="Дом",C3="Вилла")),OR(R3="",R3>YEAR(TODAY()))),"Год постройки",""),IF(AND(P3<>"",Q3<>"",P3>Q3),"Этаж больше этажности",""),IF(AND(OR(C3="Квартира",C3="Апартаменты",C3="Дом",C3="Вилла"),S3=""),"Материал",""),IF(AND(OR(C3="Коммерческая"),U3=""),"Тип коммерции",""),IF(AND(OR(C3="Земля"),V3=""),"Назначение земли",""),IF(W3="","Формат долга",""),IF(OR(X3="",X3<=0),"Сумма долга",""),IF(AND(W3="Долги + Аукцион",OR(Y3="",Y3<=0)),"Продать сейчас",""),IF(AND(W3="Долги + Аукцион",OR(Z3="",Z3<=0)),"Минимальная цена продажи",""),IF(AND(W3="Долги + Аукцион",OR(AA3="",AA3<=0)),"Стартовая ставка",""),IF(AND(W3="Долги + Аукцион",AB3=""),"Начало аукциона",""),IF(AND(W3="Долги + Аукцион",AC3=""),"Окончание аукциона",""),IF(AND(W3="Долги + Аукцион",AND(Y3<>"",Z3<>"",Z3>Y3)),"Минимальная цена выше «Продать сейчас»",""),IF(AND(W3="Долги + Аукцион",AND(Y3<>"",Z3<>"",Z3<=Y3,Z3>Y3*0.9)),"Минимальная цена выше 90% от «Продать сейчас»",""),IF(AND(W3="Долги + Аукцион",AND(Y3<>"",AA3<>"",AA3>Y3*0.3)),"Стартовая ставка выше 30% от «Продать сейчас»",""),IF(AND(W3="Долги + Аукцион",AND(AB3<>"",AC3<>"",AC3<EDATE(AB3,3)+15)),"Аукцион короче 3 месяцев и 15 дней",""))="","",TEXTJOIN(", ",TRUE,IF(B3="","Название",""),IF(C3="","Тип недвижимости",""),IF(D3="","Страна",""),IF(E3="","Город",""),IF(F3="","Улица",""),IF(I3="","Валюта",""),IF(OR(AI3="",AI3<1),"Хотя бы 1 фото",""),IF(AND(OR(C3="Квартира",C3="Апартаменты",C3="Дом",C3="Вилла",C3="Коммерческая"),J3=""),"Площадь",""),IF(AND(OR(C3="Квартира",C3="Апартаменты"),K3=""),"Жилая площадь",""),IF(AND(OR(C3="Дом",C3="Вилла",C3="Земля"),L3=""),"Площадь участка",""),IF(AND(OR(C3="Квартира",C3="Апартаменты"),M3=""),"Комнаты",""),IF(AND(OR(C3="Дом",C3="Вилла"),N3=""),"Спальни",""),IF(AND(OR(C3="Квартира",C3="Апартаменты",C3="Дом",C3="Вилла"),O3=""),"Ванные",""),IF(AND(OR(C3="Квартира",C3="Апартаменты"),P3=""),"Этаж",""),IF(AND(OR(OR(C3="Квартира",C3="Апартаменты"),OR(C3="Дом",C3="Вилла")),Q3=""),"Этажей",""),IF(AND(OR(OR(C3="Квартира",C3="Апартаменты"),OR(C3="Дом",C3="Вилла")),OR(R3="",R3>YEAR(TODAY()))),"Год постройки",""),IF(AND(P3<>"",Q3<>"",P3>Q3),"Этаж больше этажности",""),IF(AND(OR(C3="Квартира",C3="Апартаменты",C3="Дом",C3="Вилла"),S3=""),"Материал",""),IF(AND(OR(C3="Коммерческая"),U3=""),"Тип коммерции",""),IF(AND(OR(C3="Земля"),V3=""),"Назначение земли",""),IF(W3="","Формат долга",""),IF(OR(X3="",X3<=0),"Сумма долга",""),IF(AND(W3="Долги + Аукцион",OR(Y3="",Y3<=0)),"Продать сейчас",""),IF(AND(W3="Долги + Аукцион",OR(Z3="",Z3<=0)),"Минимальная цена продажи",""),IF(AND(W3="Долги + Аукцион",OR(AA3="",AA3<=0)),"Стартовая ставка",""),IF(AND(W3="Долги + Аукцион",AB3=""),"Начало аукциона",""),IF(AND(W3="Долги + Аукцион",AC3=""),"Окончание аукциона",""),IF(AND(W3="Долги + Аукцион",AND(Y3<>"",Z3<>"",Z3>Y3)),"Минимальная цена выше «Продать сейчас»",""),IF(AND(W3="Долги + Аукцион",AND(Y3<>"",Z3<>"",Z3<=Y3,Z3>Y3*0.9)),"Минимальная цена выше 90% от «Продать сейчас»",""),IF(AND(W3="Долги + Аукцион",AND(Y3<>"",AA3<>"",AA3>Y3*0.3)),"Стартовая ставка выше 30% от «Продать сейчас»",""),IF(AND(W3="Долги + Аукцион",AND(AB3<>"",AC3<>"",AC3<EDATE(AB3,3)+15)),"Аукцион короче 3 месяцев и 15 дней","")))) | AP3: =IF(NOT(COUNTA(A3:AN3)>0),"",IF(TEXTJOIN(", ",TRUE,IF(AL3="","Описание",""),IF(AND(AI3<>"",AI3>=1,AI3<5),"Фото меньше 5",""),IF(AK3="","Видео",""),IF(H3="","Кадастровый номер",""),IF(AJ3="","Ссылка на фото",""),IF(OR(AD3="",AD3="Нет"),"Кредитный договор",""),IF(OR(AE3="",AE3="Нет"),"Нотариальная закладная",""),IF(OR(AF3="",AF3="Нет"),"Выписка из реестра",""),IF(OR(AG3="",AG3="Нет"),"Оценка объекта",""),IF(AH3="","Статус в суде",""))="","",TEXTJOIN(", ",TRUE,IF(AL3="","Описание",""),IF(AND(AI3<>"",AI3>=1,AI3<5),"Фото меньше 5",""),IF(AK3="","Видео",""),IF(H3="","Кадастровый номер",""),IF(AJ3="","Ссылка на фото",""),IF(OR(AD3="",AD3="Нет"),"Кредитный договор",""),IF(OR(AE3="",AE3="Нет"),"Нотариальная закладная",""),IF(OR(AF3="",AF3="Нет"),"Выписка из реестра",""),IF(OR(AG3="",AG3="Нет"),"Оценка объекта",""),IF(AH3="","Статус в суде","")))) | AQ3: =IF(NOT(COUNTA(A3:AN3)>0),"",IF(AO3="","Можно публиковать","Не хватает"))
AO4: =IF(NOT(COUNTA(A4:AN4)>0),"",IF(TEXTJOIN(", ",TRUE,IF(B4="","Название",""),IF(C4="","Тип недвижимости",""),IF(D4="","Страна",""),IF(E4="","Город",""),IF(F4="","Улица",""),IF(I4="","Валюта",""),IF(OR(AI4="",AI4<1),"Хотя бы 1 фото",""),IF(AND(OR(C4="Квартира",C4="Апартаменты",C4="Дом",C4="Вилла",C4="Коммерческая"),J4=""),"Площадь",""),IF(AND(OR(C4="Квартира",C4="Апартаменты"),K4=""),"Жилая площадь",""),IF(AND(OR(C4="Дом",C4="Вилла",C4="Земля"),L4=""),"Площадь участка",""),IF(AND(OR(C4="Квартира",C4="Апартаменты"),M4=""),"Комнаты",""),IF(AND(OR(C4="Дом",C4="Вилла"),N4=""),"Спальни",""),IF(AND(OR(C4="Квартира",C4="Апартаменты",C4="Дом",C4="Вилла"),O4=""),"Ванные",""),IF(AND(OR(C4="Квартира",C4="Апартаменты"),P4=""),"Этаж",""),IF(AND(OR(OR(C4="Квартира",C4="Апартаменты"),OR(C4="Дом",C4="Вилла")),Q4=""),"Этажей",""),IF(AND(OR(OR(C4="Квартира",C4="Апартаменты"),OR(C4="Дом",C4="Вилла")),OR(R4="",R4>YEAR(TODAY()))),"Год постройки",""),IF(AND(P4<>"",Q4<>"",P4>Q4),"Этаж больше этажности",""),IF(AND(OR(C4="Квартира",C4="Апартаменты",C4="Дом",C4="Вилла"),S4=""),"Материал",""),IF(AND(OR(C4="Коммерческая"),U4=""),"Тип коммерции",""),IF(AND(OR(C4="Земля"),V4=""),"Назначение земли",""),IF(W4="","Формат долга",""),IF(OR(X4="",X4<=0),"Сумма долга",""),IF(AND(W4="Долги + Аукцион",OR(Y4="",Y4<=0)),"Продать сейчас",""),IF(AND(W4="Долги + Аукцион",OR(Z4="",Z4<=0)),"Минимальная цена продажи",""),IF(AND(W4="Долги + Аукцион",OR(AA4="",AA4<=0)),"Стартовая ставка",""),IF(AND(W4="Долги + Аукцион",AB4=""),"Начало аукциона",""),IF(AND(W4="Долги + Аукцион",AC4=""),"Окончание аукциона",""),IF(AND(W4="Долги + Аукцион",AND(Y4<>"",Z4<>"",Z4>Y4)),"Минимальная цена выше «Продать сейчас»",""),IF(AND(W4="Долги + Аукцион",AND(Y4<>"",Z4<>"",Z4<=Y4,Z4>Y4*0.9)),"Минимальная цена выше 90% от «Продать сейчас»",""),IF(AND(W4="Долги + Аукцион",AND(Y4<>"",AA4<>"",AA4>Y4*0.3)),"Стартовая ставка выше 30% от «Продать сейчас»",""),IF(AND(W4="Долги + Аукцион",AND(AB4<>"",AC4<>"",AC4<EDATE(AB4,3)+15)),"Аукцион короче 3 месяцев и 15 дней",""))="","",TEXTJOIN(", ",TRUE,IF(B4="","Название",""),IF(C4="","Тип недвижимости",""),IF(D4="","Страна",""),IF(E4="","Город",""),IF(F4="","Улица",""),IF(I4="","Валюта",""),IF(OR(AI4="",AI4<1),"Хотя бы 1 фото",""),IF(AND(OR(C4="Квартира",C4="Апартаменты",C4="Дом",C4="Вилла",C4="Коммерческая"),J4=""),"Площадь",""),IF(AND(OR(C4="Квартира",C4="Апартаменты"),K4=""),"Жилая площадь",""),IF(AND(OR(C4="Дом",C4="Вилла",C4="Земля"),L4=""),"Площадь участка",""),IF(AND(OR(C4="Квартира",C4="Апартаменты"),M4=""),"Комнаты",""),IF(AND(OR(C4="Дом",C4="Вилла"),N4=""),"Спальни",""),IF(AND(OR(C4="Квартира",C4="Апартаменты",C4="Дом",C4="Вилла"),O4=""),"Ванные",""),IF(AND(OR(C4="Квартира",C4="Апартаменты"),P4=""),"Этаж",""),IF(AND(OR(OR(C4="Квартира",C4="Апартаменты"),OR(C4="Дом",C4="Вилла")),Q4=""),"Этажей",""),IF(AND(OR(OR(C4="Квартира",C4="Апартаменты"),OR(C4="Дом",C4="Вилла")),OR(R4="",R4>YEAR(TODAY()))),"Год постройки",""),IF(AND(P4<>"",Q4<>"",P4>Q4),"Этаж больше этажности",""),IF(AND(OR(C4="Квартира",C4="Апартаменты",C4="Дом",C4="Вилла"),S4=""),"Материал",""),IF(AND(OR(C4="Коммерческая"),U4=""),"Тип коммерции",""),IF(AND(OR(C4="Земля"),V4=""),"Назначение земли",""),IF(W4="","Формат долга",""),IF(OR(X4="",X4<=0),"Сумма долга",""),IF(AND(W4="Долги + Аукцион",OR(Y4="",Y4<=0)),"Продать сейчас",""),IF(AND(W4="Долги + Аукцион",OR(Z4="",Z4<=0)),"Минимальная цена продажи",""),IF(AND(W4="Долги + Аукцион",OR(AA4="",AA4<=0)),"Стартовая ставка",""),IF(AND(W4="Долги + Аукцион",AB4=""),"Начало аукциона",""),IF(AND(W4="Долги + Аукцион",AC4=""),"Окончание аукциона",""),IF(AND(W4="Долги + Аукцион",AND(Y4<>"",Z4<>"",Z4>Y4)),"Минимальная цена выше «Продать сейчас»",""),IF(AND(W4="Долги + Аукцион",AND(Y4<>"",Z4<>"",Z4<=Y4,Z4>Y4*0.9)),"Минимальная цена выше 90% от «Продать сейчас»",""),IF(AND(W4="Долги + Аукцион",AND(Y4<>"",AA4<>"",AA4>Y4*0.3)),"Стартовая ставка выше 30% от «Продать сейчас»",""),IF(AND(W4="Долги + Аукцион",AND(AB4<>"",AC4<>"",AC4<EDATE(AB4,3)+15)),"Аукцион короче 3 месяцев и 15 дней","")))) | AP4: =IF(NOT(COUNTA(A4:AN4)>0),"",IF(TEXTJOIN(", ",TRUE,IF(AL4="","Описание",""),IF(AND(AI4<>"",AI4>=1,AI4<5),"Фото меньше 5",""),IF(AK4="","Видео",""),IF(H4="","Кадастровый номер",""),IF(AJ4="","Ссылка на фото",""),IF(OR(AD4="",AD4="Нет"),"Кредитный договор",""),IF(OR(AE4="",AE4="Нет"),"Нотариальная закладная",""),IF(OR(AF4="",AF4="Нет"),"Выписка из реестра",""),IF(OR(AG4="",AG4="Нет"),"Оценка объекта",""),IF(AH4="","Статус в суде",""))="","",TEXTJOIN(", ",TRUE,IF(AL4="","Описание",""),IF(AND(AI4<>"",AI4>=1,AI4<5),"Фото меньше 5",""),IF(AK4="","Видео",""),IF(H4="","Кадастровый номер",""),IF(AJ4="","Ссылка на фото",""),IF(OR(AD4="",AD4="Нет"),"Кредитный договор",""),IF(OR(AE4="",AE4="Нет"),"Нотариальная закладная",""),IF(OR(AF4="",AF4="Нет"),"Выписка из реестра",""),IF(OR(AG4="",AG4="Нет"),"Оценка объекта",""),IF(AH4="","Статус в суде","")))) | AQ4: =IF(NOT(COUNTA(A4:AN4)>0),"",IF(AO4="","Можно публиковать","Не хватает"))
AO5: =IF(NOT(COUNTA(A5:AN5)>0),"",IF(TEXTJOIN(", ",TRUE,IF(B5="","Название",""),IF(C5="","Тип недвижимости",""),IF(D5="","Страна",""),IF(E5="","Город",""),IF(F5="","Улица",""),IF(I5="","Валюта",""),IF(OR(AI5="",AI5<1),"Хотя бы 1 фото",""),IF(AND(OR(C5="Квартира",C5="Апартаменты",C5="Дом",C5="Вилла",C5="Коммерческая"),J5=""),"Площадь",""),IF(AND(OR(C5="Квартира",C5="Апартаменты"),K5=""),"Жилая площадь",""),IF(AND(OR(C5="Дом",C5="Вилла",C5="Земля"),L5=""),"Площадь участка",""),IF(AND(OR(C5="Квартира",C5="Апартаменты"),M5=""),"Комнаты",""),IF(AND(OR(C5="Дом",C5="Вилла"),N5=""),"Спальни",""),IF(AND(OR(C5="Квартира",C5="Апартаменты",C5="Дом",C5="Вилла"),O5=""),"Ванные",""),IF(AND(OR(C5="Квартира",C5="Апартаменты"),P5=""),"Этаж",""),IF(AND(OR(OR(C5="Квартира",C5="Апартаменты"),OR(C5="Дом",C5="Вилла")),Q5=""),"Этажей",""),IF(AND(OR(OR(C5="Квартира",C5="Апартаменты"),OR(C5="Дом",C5="Вилла")),OR(R5="",R5>YEAR(TODAY()))),"Год постройки",""),IF(AND(P5<>"",Q5<>"",P5>Q5),"Этаж больше этажности",""),IF(AND(OR(C5="Квартира",C5="Апартаменты",C5="Дом",C5="Вилла"),S5=""),"Материал",""),IF(AND(OR(C5="Коммерческая"),U5=""),"Тип коммерции",""),IF(AND(OR(C5="Земля"),V5=""),"Назначение земли",""),IF(W5="","Формат долга",""),IF(OR(X5="",X5<=0),"Сумма долга",""),IF(AND(W5="Долги + Аукцион",OR(Y5="",Y5<=0)),"Продать сейчас",""),IF(AND(W5="Долги + Аукцион",OR(Z5="",Z5<=0)),"Минимальная цена продажи",""),IF(AND(W5="Долги + Аукцион",OR(AA5="",AA5<=0)),"Стартовая ставка",""),IF(AND(W5="Долги + Аукцион",AB5=""),"Начало аукциона",""),IF(AND(W5="Долги + Аукцион",AC5=""),"Окончание аукциона",""),IF(AND(W5="Долги + Аукцион",AND(Y5<>"",Z5<>"",Z5>Y5)),"Минимальная цена выше «Продать сейчас»",""),IF(AND(W5="Долги + Аукцион",AND(Y5<>"",Z5<>"",Z5<=Y5,Z5>Y5*0.9)),"Минимальная цена выше 90% от «Продать сейчас»",""),IF(AND(W5="Долги + Аукцион",AND(Y5<>"",AA5<>"",AA5>Y5*0.3)),"Стартовая ставка выше 30% от «Продать сейчас»",""),IF(AND(W5="Долги + Аукцион",AND(AB5<>"",AC5<>"",AC5<EDATE(AB5,3)+15)),"Аукцион короче 3 месяцев и 15 дней",""))="","",TEXTJOIN(", ",TRUE,IF(B5="","Название",""),IF(C5="","Тип недвижимости",""),IF(D5="","Страна",""),IF(E5="","Город",""),IF(F5="","Улица",""),IF(I5="","Валюта",""),IF(OR(AI5="",AI5<1),"Хотя бы 1 фото",""),IF(AND(OR(C5="Квартира",C5="Апартаменты",C5="Дом",C5="Вилла",C5="Коммерческая"),J5=""),"Площадь",""),IF(AND(OR(C5="Квартира",C5="Апартаменты"),K5=""),"Жилая площадь",""),IF(AND(OR(C5="Дом",C5="Вилла",C5="Земля"),L5=""),"Площадь участка",""),IF(AND(OR(C5="Квартира",C5="Апартаменты"),M5=""),"Комнаты",""),IF(AND(OR(C5="Дом",C5="Вилла"),N5=""),"Спальни",""),IF(AND(OR(C5="Квартира",C5="Апартаменты",C5="Дом",C5="Вилла"),O5=""),"Ванные",""),IF(AND(OR(C5="Квартира",C5="Апартаменты"),P5=""),"Этаж",""),IF(AND(OR(OR(C5="Квартира",C5="Апартаменты"),OR(C5="Дом",C5="Вилла")),Q5=""),"Этажей",""),IF(AND(OR(OR(C5="Квартира",C5="Апартаменты"),OR(C5="Дом",C5="Вилла")),OR(R5="",R5>YEAR(TODAY()))),"Год постройки",""),IF(AND(P5<>"",Q5<>"",P5>Q5),"Этаж больше этажности",""),IF(AND(OR(C5="Квартира",C5="Апартаменты",C5="Дом",C5="Вилла"),S5=""),"Материал",""),IF(AND(OR(C5="Коммерческая"),U5=""),"Тип коммерции",""),IF(AND(OR(C5="Земля"),V5=""),"Назначение земли",""),IF(W5="","Формат долга",""),IF(OR(X5="",X5<=0),"Сумма долга",""),IF(AND(W5="Долги + Аукцион",OR(Y5="",Y5<=0)),"Продать сейчас",""),IF(AND(W5="Долги + Аукцион",OR(Z5="",Z5<=0)),"Минимальная цена продажи",""),IF(AND(W5="Долги + Аукцион",OR(AA5="",AA5<=0)),"Стартовая ставка",""),IF(AND(W5="Долги + Аукцион",AB5=""),"Начало аукциона",""),IF(AND(W5="Долги + Аукцион",AC5=""),"Окончание аукциона",""),IF(AND(W5="Долги + Аукцион",AND(Y5<>"",Z5<>"",Z5>Y5)),"Минимальная цена выше «Продать сейчас»",""),IF(AND(W5="Долги + Аукцион",AND(Y5<>"",Z5<>"",Z5<=Y5,Z5>Y5*0.9)),"Минимальная цена выше 90% от «Продать сейчас»",""),IF(AND(W5="Долги + Аукцион",AND(Y5<>"",AA5<>"",AA5>Y5*0.3)),"Стартовая ставка выше 30% от «Продать сейчас»",""),IF(AND(W5="Долги + Аукцион",AND(AB5<>"",AC5<>"",AC5<EDATE(AB5,3)+15)),"Аукцион короче 3 месяцев и 15 дней","")))) | AP5: =IF(NOT(COUNTA(A5:AN5)>0),"",IF(TEXTJOIN(", ",TRUE,IF(AL5="","Описание",""),IF(AND(AI5<>"",AI5>=1,AI5<5),"Фото меньше 5",""),IF(AK5="","Видео",""),IF(H5="","Кадастровый номер",""),IF(AJ5="","Ссылка на фото",""),IF(OR(AD5="",AD5="Нет"),"Кредитный договор",""),IF(OR(AE5="",AE5="Нет"),"Нотариальная закладная",""),IF(OR(AF5="",AF5="Нет"),"Выписка из реестра",""),IF(OR(AG5="",AG5="Нет"),"Оценка объекта",""),IF(AH5="","Статус в суде",""))="","",TEXTJOIN(", ",TRUE,IF(AL5="","Описание",""),IF(AND(AI5<>"",AI5>=1,AI5<5),"Фото меньше 5",""),IF(AK5="","Видео",""),IF(H5="","Кадастровый номер",""),IF(AJ5="","Ссылка на фото",""),IF(OR(AD5="",AD5="Нет"),"Кредитный договор",""),IF(OR(AE5="",AE5="Нет"),"Нотариальная закладная",""),IF(OR(AF5="",AF5="Нет"),"Выписка из реестра",""),IF(OR(AG5="",AG5="Нет"),"Оценка объекта",""),IF(AH5="","Статус в суде","")))) | AQ5: =IF(NOT(COUNTA(A5:AN5)>0),"",IF(AO5="","Можно публиковать","Не хватает"))
AO6: =IF(NOT(COUNTA(A6:AN6)>0),"",IF(TEXTJOIN(", ",TRUE,IF(B6="","Название",""),IF(C6="","Тип недвижимости",""),IF(D6="","Страна",""),IF(E6="","Город",""),IF(F6="","Улица",""),IF(I6="","Валюта",""),IF(OR(AI6="",AI6<1),"Хотя бы 1 фото",""),IF(AND(OR(C6="Квартира",C6="Апартаменты",C6="Дом",C6="Вилла",C6="Коммерческая"),J6=""),"Площадь",""),IF(AND(OR(C6="Квартира",C6="Апартаменты"),K6=""),"Жилая площадь",""),IF(AND(OR(C6="Дом",C6="Вилла",C6="Земля"),L6=""),"Площадь участка",""),IF(AND(OR(C6="Квартира",C6="Апартаменты"),M6=""),"Комнаты",""),IF(AND(OR(C6="Дом",C6="Вилла"),N6=""),"Спальни",""),IF(AND(OR(C6="Квартира",C6="Апартаменты",C6="Дом",C6="Вилла"),O6=""),"Ванные",""),IF(AND(OR(C6="Квартира",C6="Апартаменты"),P6=""),"Этаж",""),IF(AND(OR(OR(C6="Квартира",C6="Апартаменты"),OR(C6="Дом",C6="Вилла")),Q6=""),"Этажей",""),IF(AND(OR(OR(C6="Квартира",C6="Апартаменты"),OR(C6="Дом",C6="Вилла")),OR(R6="",R6>YEAR(TODAY()))),"Год постройки",""),IF(AND(P6<>"",Q6<>"",P6>Q6),"Этаж больше этажности",""),IF(AND(OR(C6="Квартира",C6="Апартаменты",C6="Дом",C6="Вилла"),S6=""),"Материал",""),IF(AND(OR(C6="Коммерческая"),U6=""),"Тип коммерции",""),IF(AND(OR(C6="Земля"),V6=""),"Назначение земли",""),IF(W6="","Формат долга",""),IF(OR(X6="",X6<=0),"Сумма долга",""),IF(AND(W6="Долги + Аукцион",OR(Y6="",Y6<=0)),"Продать сейчас",""),IF(AND(W6="Долги + Аукцион",OR(Z6="",Z6<=0)),"Минимальная цена продажи",""),IF(AND(W6="Долги + Аукцион",OR(AA6="",AA6<=0)),"Стартовая ставка",""),IF(AND(W6="Долги + Аукцион",AB6=""),"Начало аукциона",""),IF(AND(W6="Долги + Аукцион",AC6=""),"Окончание аукциона",""),IF(AND(W6="Долги + Аукцион",AND(Y6<>"",Z6<>"",Z6>Y6)),"Минимальная цена выше «Продать сейчас»",""),IF(AND(W6="Долги + Аукцион",AND(Y6<>"",Z6<>"",Z6<=Y6,Z6>Y6*0.9)),"Минимальная цена выше 90% от «Продать сейчас»",""),IF(AND(W6="Долги + Аукцион",AND(Y6<>"",AA6<>"",AA6>Y6*0.3)),"Стартовая ставка выше 30% от «Продать сейчас»",""),IF(AND(W6="Долги + Аукцион",AND(AB6<>"",AC6<>"",AC6<EDATE(AB6,3)+15)),"Аукцион короче 3 месяцев и 15 дней",""))="","",TEXTJOIN(", ",TRUE,IF(B6="","Название",""),IF(C6="","Тип недвижимости",""),IF(D6="","Страна",""),IF(E6="","Город",""),IF(F6="","Улица",""),IF(I6="","Валюта",""),IF(OR(AI6="",AI6<1),"Хотя бы 1 фото",""),IF(AND(OR(C6="Квартира",C6="Апартаменты",C6="Дом",C6="Вилла",C6="Коммерческая"),J6=""),"Площадь",""),IF(AND(OR(C6="Квартира",C6="Апартаменты"),K6=""),"Жилая площадь",""),IF(AND(OR(C6="Дом",C6="Вилла",C6="Земля"),L6=""),"Площадь участка",""),IF(AND(OR(C6="Квартира",C6="Апартаменты"),M6=""),"Комнаты",""),IF(AND(OR(C6="Дом",C6="Вилла"),N6=""),"Спальни",""),IF(AND(OR(C6="Квартира",C6="Апартаменты",C6="Дом",C6="Вилла"),O6=""),"Ванные",""),IF(AND(OR(C6="Квартира",C6="Апартаменты"),P6=""),"Этаж",""),IF(AND(OR(OR(C6="Квартира",C6="Апартаменты"),OR(C6="Дом",C6="Вилла")),Q6=""),"Этажей",""),IF(AND(OR(OR(C6="Квартира",C6="Апартаменты"),OR(C6="Дом",C6="Вилла")),OR(R6="",R6>YEAR(TODAY()))),"Год постройки",""),IF(AND(P6<>"",Q6<>"",P6>Q6),"Этаж больше этажности",""),IF(AND(OR(C6="Квартира",C6="Апартаменты",C6="Дом",C6="Вилла"),S6=""),"Материал",""),IF(AND(OR(C6="Коммерческая"),U6=""),"Тип коммерции",""),IF(AND(OR(C6="Земля"),V6=""),"Назначение земли",""),IF(W6="","Формат долга",""),IF(OR(X6="",X6<=0),"Сумма долга",""),IF(AND(W6="Долги + Аукцион",OR(Y6="",Y6<=0)),"Продать сейчас",""),IF(AND(W6="Долги + Аукцион",OR(Z6="",Z6<=0)),"Минимальная цена продажи",""),IF(AND(W6="Долги + Аукцион",OR(AA6="",AA6<=0)),"Стартовая ставка",""),IF(AND(W6="Долги + Аукцион",AB6=""),"Начало аукциона",""),IF(AND(W6="Долги + Аукцион",AC6=""),"Окончание аукциона",""),IF(AND(W6="Долги + Аукцион",AND(Y6<>"",Z6<>"",Z6>Y6)),"Минимальная цена выше «Продать сейчас»",""),IF(AND(W6="Долги + Аукцион",AND(Y6<>"",Z6<>"",Z6<=Y6,Z6>Y6*0.9)),"Минимальная цена выше 90% от «Продать сейчас»",""),IF(AND(W6="Долги + Аукцион",AND(Y6<>"",AA6<>"",AA6>Y6*0.3)),"Стартовая ставка выше 30% от «Продать сейчас»",""),IF(AND(W6="Долги + Аукцион",AND(AB6<>"",AC6<>"",AC6<EDATE(AB6,3)+15)),"Аукцион короче 3 месяцев и 15 дней","")))) | AP6: =IF(NOT(COUNTA(A6:AN6)>0),"",IF(TEXTJOIN(", ",TRUE,IF(AL6="","Описание",""),IF(AND(AI6<>"",AI6>=1,AI6<5),"Фото меньше 5",""),IF(AK6="","Видео",""),IF(H6="","Кадастровый номер",""),IF(AJ6="","Ссылка на фото",""),IF(OR(AD6="",AD6="Нет"),"Кредитный договор",""),IF(OR(AE6="",AE6="Нет"),"Нотариальная закладная",""),IF(OR(AF6="",AF6="Нет"),"Выписка из реестра",""),IF(OR(AG6="",AG6="Нет"),"Оценка объекта",""),IF(AH6="","Статус в суде",""))="","",TEXTJOIN(", ",TRUE,IF(AL6="","Описание",""),IF(AND(AI6<>"",AI6>=1,AI6<5),"Фото меньше 5",""),IF(AK6="","Видео",""),IF(H6="","Кадастровый номер",""),IF(AJ6="","Ссылка на фото",""),IF(OR(AD6="",AD6="Нет"),"Кредитный договор",""),IF(OR(AE6="",AE6="Нет"),"Нотариальная закладная",""),IF(OR(AF6="",AF6="Нет"),"Выписка из реестра",""),IF(OR(AG6="",AG6="Нет"),"Оценка объекта",""),IF(AH6="","Статус в суде","")))) | AQ6: =IF(NOT(COUNTA(A6:AN6)>0),"",IF(AO6="","Можно публиковать","Не хватает"))
AO7: =IF(NOT(COUNTA(A7:AN7)>0),"",IF(TEXTJOIN(", ",TRUE,IF(B7="","Название",""),IF(C7="","Тип недвижимости",""),IF(D7="","Страна",""),IF(E7="","Город",""),IF(F7="","Улица",""),IF(I7="","Валюта",""),IF(OR(AI7="",AI7<1),"Хотя бы 1 фото",""),IF(AND(OR(C7="Квартира",C7="Апартаменты",C7="Дом",C7="Вилла",C7="Коммерческая"),J7=""),"Площадь",""),IF(AND(OR(C7="Квартира",C7="Апартаменты"),K7=""),"Жилая площадь",""),IF(AND(OR(C7="Дом",C7="Вилла",C7="Земля"),L7=""),"Площадь участка",""),IF(AND(OR(C7="Квартира",C7="Апартаменты"),M7=""),"Комнаты",""),IF(AND(OR(C7="Дом",C7="Вилла"),N7=""),"Спальни",""),IF(AND(OR(C7="Квартира",C7="Апартаменты",C7="Дом",C7="Вилла"),O7=""),"Ванные",""),IF(AND(OR(C7="Квартира",C7="Апартаменты"),P7=""),"Этаж",""),IF(AND(OR(OR(C7="Квартира",C7="Апартаменты"),OR(C7="Дом",C7="Вилла")),Q7=""),"Этажей",""),IF(AND(OR(OR(C7="Квартира",C7="Апартаменты"),OR(C7="Дом",C7="Вилла")),OR(R7="",R7>YEAR(TODAY()))),"Год постройки",""),IF(AND(P7<>"",Q7<>"",P7>Q7),"Этаж больше этажности",""),IF(AND(OR(C7="Квартира",C7="Апартаменты",C7="Дом",C7="Вилла"),S7=""),"Материал",""),IF(AND(OR(C7="Коммерческая"),U7=""),"Тип коммерции",""),IF(AND(OR(C7="Земля"),V7=""),"Назначение земли",""),IF(W7="","Формат долга",""),IF(OR(X7="",X7<=0),"Сумма долга",""),IF(AND(W7="Долги + Аукцион",OR(Y7="",Y7<=0)),"Продать сейчас",""),IF(AND(W7="Долги + Аукцион",OR(Z7="",Z7<=0)),"Минимальная цена продажи",""),IF(AND(W7="Долги + Аукцион",OR(AA7="",AA7<=0)),"Стартовая ставка",""),IF(AND(W7="Долги + Аукцион",AB7=""),"Начало аукциона",""),IF(AND(W7="Долги + Аукцион",AC7=""),"Окончание аукциона",""),IF(AND(W7="Долги + Аукцион",AND(Y7<>"",Z7<>"",Z7>Y7)),"Минимальная цена выше «Продать сейчас»",""),IF(AND(W7="Долги + Аукцион",AND(Y7<>"",Z7<>"",Z7<=Y7,Z7>Y7*0.9)),"Минимальная цена выше 90% от «Продать сейчас»",""),IF(AND(W7="Долги + Аукцион",AND(Y7<>"",AA7<>"",AA7>Y7*0.3)),"Стартовая ставка выше 30% от «Продать сейчас»",""),IF(AND(W7="Долги + Аукцион",AND(AB7<>"",AC7<>"",AC7<EDATE(AB7,3)+15)),"Аукцион короче 3 месяцев и 15 дней",""))="","",TEXTJOIN(", ",TRUE,IF(B7="","Название",""),IF(C7="","Тип недвижимости",""),IF(D7="","Страна",""),IF(E7="","Город",""),IF(F7="","Улица",""),IF(I7="","Валюта",""),IF(OR(AI7="",AI7<1),"Хотя бы 1 фото",""),IF(AND(OR(C7="Квартира",C7="Апартаменты",C7="Дом",C7="Вилла",C7="Коммерческая"),J7=""),"Площадь",""),IF(AND(OR(C7="Квартира",C7="Апартаменты"),K7=""),"Жилая площадь",""),IF(AND(OR(C7="Дом",C7="Вилла",C7="Земля"),L7=""),"Площадь участка",""),IF(AND(OR(C7="Квартира",C7="Апартаменты"),M7=""),"Комнаты",""),IF(AND(OR(C7="Дом",C7="Вилла"),N7=""),"Спальни",""),IF(AND(OR(C7="Квартира",C7="Апартаменты",C7="Дом",C7="Вилла"),O7=""),"Ванные",""),IF(AND(OR(C7="Квартира",C7="Апартаменты"),P7=""),"Этаж",""),IF(AND(OR(OR(C7="Квартира",C7="Апартаменты"),OR(C7="Дом",C7="Вилла")),Q7=""),"Этажей",""),IF(AND(OR(OR(C7="Квартира",C7="Апартаменты"),OR(C7="Дом",C7="Вилла")),OR(R7="",R7>YEAR(TODAY()))),"Год постройки",""),IF(AND(P7<>"",Q7<>"",P7>Q7),"Этаж больше этажности",""),IF(AND(OR(C7="Квартира",C7="Апартаменты",C7="Дом",C7="Вилла"),S7=""),"Материал",""),IF(AND(OR(C7="Коммерческая"),U7=""),"Тип коммерции",""),IF(AND(OR(C7="Земля"),V7=""),"Назначение земли",""),IF(W7="","Формат долга",""),IF(OR(X7="",X7<=0),"Сумма долга",""),IF(AND(W7="Долги + Аукцион",OR(Y7="",Y7<=0)),"Продать сейчас",""),IF(AND(W7="Долги + Аукцион",OR(Z7="",Z7<=0)),"Минимальная цена продажи",""),IF(AND(W7="Долги + Аукцион",OR(AA7="",AA7<=0)),"Стартовая ставка",""),IF(AND(W7="Долги + Аукцион",AB7=""),"Начало аукциона",""),IF(AND(W7="Долги + Аукцион",AC7=""),"Окончание аукциона",""),IF(AND(W7="Долги + Аукцион",AND(Y7<>"",Z7<>"",Z7>Y7)),"Минимальная цена выше «Продать сейчас»",""),IF(AND(W7="Долги + Аукцион",AND(Y7<>"",Z7<>"",Z7<=Y7,Z7>Y7*0.9)),"Минимальная цена выше 90% от «Продать сейчас»",""),IF(AND(W7="Долги + Аукцион",AND(Y7<>"",AA7<>"",AA7>Y7*0.3)),"Стартовая ставка выше 30% от «Продать сейчас»",""),IF(AND(W7="Долги + Аукцион",AND(AB7<>"",AC7<>"",AC7<EDATE(AB7,3)+15)),"Аукцион короче 3 месяцев и 15 дней","")))) | AP7: =IF(NOT(COUNTA(A7:AN7)>0),"",IF(TEXTJOIN(", ",TRUE,IF(AL7="","Описание",""),IF(AND(AI7<>"",AI7>=1,AI7<5),"Фото меньше 5",""),IF(AK7="","Видео",""),IF(H7="","Кадастровый номер",""),IF(AJ7="","Ссылка на фото",""),IF(OR(AD7="",AD7="Нет"),"Кредитный договор",""),IF(OR(AE7="",AE7="Нет"),"Нотариальная закладная",""),IF(OR(AF7="",AF7="Нет"),"Выписка из реестра",""),IF(OR(AG7="",AG7="Нет"),"Оценка объекта",""),IF(AH7="","Статус в суде",""))="","",TEXTJOIN(", ",TRUE,IF(AL7="","Описание",""),IF(AND(AI7<>"",AI7>=1,AI7<5),"Фото меньше 5",""),IF(AK7="","Видео",""),IF(H7="","Кадастровый номер",""),IF(AJ7="","Ссылка на фото",""),IF(OR(AD7="",AD7="Нет"),"Кредитный договор",""),IF(OR(AE7="",AE7="Нет"),"Нотариальная закладная",""),IF(OR(AF7="",AF7="Нет"),"Выписка из реестра",""),IF(OR(AG7="",AG7="Нет"),"Оценка объекта",""),IF(AH7="","Статус в суде","")))) | AQ7: =IF(NOT(COUNTA(A7:AN7)>0),"",IF(AO7="","Можно публиковать","Не хватает"))
AO8: =IF(NOT(COUNTA(A8:AN8)>0),"",IF(TEXTJOIN(", ",TRUE,IF(B8="","Название",""),IF(C8="","Тип недвижимости",""),IF(D8="","Страна",""),IF(E8="","Город",""),IF(F8="","Улица",""),IF(I8="","Валюта",""),IF(OR(AI8="",AI8<1),"Хотя бы 1 фото",""),IF(AND(OR(C8="Квартира",C8="Апартаменты",C8="Дом",C8="Вилла",C8="Коммерческая"),J8=""),"Площадь",""),IF(AND(OR(C8="Квартира",C8="Апартаменты"),K8=""),"Жилая площадь",""),IF(AND(OR(C8="Дом",C8="Вилла",C8="Земля"),L8=""),"Площадь участка",""),IF(AND(OR(C8="Квартира",C8="Апартаменты"),M8=""),"Комнаты",""),IF(AND(OR(C8="Дом",C8="Вилла"),N8=""),"Спальни",""),IF(AND(OR(C8="Квартира",C8="Апартаменты",C8="Дом",C8="Вилла"),O8=""),"Ванные",""),IF(AND(OR(C8="Квартира",C8="Апартаменты"),P8=""),"Этаж",""),IF(AND(OR(OR(C8="Квартира",C8="Апартаменты"),OR(C8="Дом",C8="Вилла")),Q8=""),"Этажей",""),IF(AND(OR(OR(C8="Квартира",C8="Апартаменты"),OR(C8="Дом",C8="Вилла")),OR(R8="",R8>YEAR(TODAY()))),"Год постройки",""),IF(AND(P8<>"",Q8<>"",P8>Q8),"Этаж больше этажности",""),IF(AND(OR(C8="Квартира",C8="Апартаменты",C8="Дом",C8="Вилла"),S8=""),"Материал",""),IF(AND(OR(C8="Коммерческая"),U8=""),"Тип коммерции",""),IF(AND(OR(C8="Земля"),V8=""),"Назначение земли",""),IF(W8="","Формат долга",""),IF(OR(X8="",X8<=0),"Сумма долга",""),IF(AND(W8="Долги + Аукцион",OR(Y8="",Y8<=0)),"Продать сейчас",""),IF(AND(W8="Долги + Аукцион",OR(Z8="",Z8<=0)),"Минимальная цена продажи",""),IF(AND(W8="Долги + Аукцион",OR(AA8="",AA8<=0)),"Стартовая ставка",""),IF(AND(W8="Долги + Аукцион",AB8=""),"Начало аукциона",""),IF(AND(W8="Долги + Аукцион",AC8=""),"Окончание аукциона",""),IF(AND(W8="Долги + Аукцион",AND(Y8<>"",Z8<>"",Z8>Y8)),"Минимальная цена выше «Продать сейчас»",""),IF(AND(W8="Долги + Аукцион",AND(Y8<>"",Z8<>"",Z8<=Y8,Z8>Y8*0.9)),"Минимальная цена выше 90% от «Продать сейчас»",""),IF(AND(W8="Долги + Аукцион",AND(Y8<>"",AA8<>"",AA8>Y8*0.3)),"Стартовая ставка выше 30% от «Продать сейчас»",""),IF(AND(W8="Долги + Аукцион",AND(AB8<>"",AC8<>"",AC8<EDATE(AB8,3)+15)),"Аукцион короче 3 месяцев и 15 дней",""))="","",TEXTJOIN(", ",TRUE,IF(B8="","Название",""),IF(C8="","Тип недвижимости",""),IF(D8="","Страна",""),IF(E8="","Город",""),IF(F8="","Улица",""),IF(I8="","Валюта",""),IF(OR(AI8="",AI8<1),"Хотя бы 1 фото",""),IF(AND(OR(C8="Квартира",C8="Апартаменты",C8="Дом",C8="Вилла",C8="Коммерческая"),J8=""),"Площадь",""),IF(AND(OR(C8="Квартира",C8="Апартаменты"),K8=""),"Жилая площадь",""),IF(AND(OR(C8="Дом",C8="Вилла",C8="Земля"),L8=""),"Площадь участка",""),IF(AND(OR(C8="Квартира",C8="Апартаменты"),M8=""),"Комнаты",""),IF(AND(OR(C8="Дом",C8="Вилла"),N8=""),"Спальни",""),IF(AND(OR(C8="Квартира",C8="Апартаменты",C8="Дом",C8="Вилла"),O8=""),"Ванные",""),IF(AND(OR(C8="Квартира",C8="Апартаменты"),P8=""),"Этаж",""),IF(AND(OR(OR(C8="Квартира",C8="Апартаменты"),OR(C8="Дом",C8="Вилла")),Q8=""),"Этажей",""),IF(AND(OR(OR(C8="Квартира",C8="Апартаменты"),OR(C8="Дом",C8="Вилла")),OR(R8="",R8>YEAR(TODAY()))),"Год постройки",""),IF(AND(P8<>"",Q8<>"",P8>Q8),"Этаж больше этажности",""),IF(AND(OR(C8="Квартира",C8="Апартаменты",C8="Дом",C8="Вилла"),S8=""),"Материал",""),IF(AND(OR(C8="Коммерческая"),U8=""),"Тип коммерции",""),IF(AND(OR(C8="Земля"),V8=""),"Назначение земли",""),IF(W8="","Формат долга",""),IF(OR(X8="",X8<=0),"Сумма долга",""),IF(AND(W8="Долги + Аукцион",OR(Y8="",Y8<=0)),"Продать сейчас",""),IF(AND(W8="Долги + Аукцион",OR(Z8="",Z8<=0)),"Минимальная цена продажи",""),IF(AND(W8="Долги + Аукцион",OR(AA8="",AA8<=0)),"Стартовая ставка",""),IF(AND(W8="Долги + Аукцион",AB8=""),"Начало аукциона",""),IF(AND(W8="Долги + Аукцион",AC8=""),"Окончание аукциона",""),IF(AND(W8="Долги + Аукцион",AND(Y8<>"",Z8<>"",Z8>Y8)),"Минимальная цена выше «Продать сейчас»",""),IF(AND(W8="Долги + Аукцион",AND(Y8<>"",Z8<>"",Z8<=Y8,Z8>Y8*0.9)),"Минимальная цена выше 90% от «Продать сейчас»",""),IF(AND(W8="Долги + Аукцион",AND(Y8<>"",AA8<>"",AA8>Y8*0.3)),"Стартовая ставка выше 30% от «Продать сейчас»",""),IF(AND(W8="Долги + Аукцион",AND(AB8<>"",AC8<>"",AC8<EDATE(AB8,3)+15)),"Аукцион короче 3 месяцев и 15 дней","")))) | AP8: =IF(NOT(COUNTA(A8:AN8)>0),"",IF(TEXTJOIN(", ",TRUE,IF(AL8="","Описание",""),IF(AND(AI8<>"",AI8>=1,AI8<5),"Фото меньше 5",""),IF(AK8="","Видео",""),IF(H8="","Кадастровый номер",""),IF(AJ8="","Ссылка на фото",""),IF(OR(AD8="",AD8="Нет"),"Кредитный договор",""),IF(OR(AE8="",AE8="Нет"),"Нотариальная закладная",""),IF(OR(AF8="",AF8="Нет"),"Выписка из реестра",""),IF(OR(AG8="",AG8="Нет"),"Оценка объекта",""),IF(AH8="","Статус в суде",""))="","",TEXTJOIN(", ",TRUE,IF(AL8="","Описание",""),IF(AND(AI8<>"",AI8>=1,AI8<5),"Фото меньше 5",""),IF(AK8="","Видео",""),IF(H8="","Кадастровый номер",""),IF(AJ8="","Ссылка на фото",""),IF(OR(AD8="",AD8="Нет"),"Кредитный договор",""),IF(OR(AE8="",AE8="Нет"),"Нотариальная закладная",""),IF(OR(AF8="",AF8="Нет"),"Выписка из реестра",""),IF(OR(AG8="",AG8="Нет"),"Оценка объекта",""),IF(AH8="","Статус в суде","")))) | AQ8: =IF(NOT(COUNTA(A8:AN8)>0),"",IF(AO8="","Можно публиковать","Не хватает"))
AO9: =IF(NOT(COUNTA(A9:AN9)>0),"",IF(TEXTJOIN(", ",TRUE,IF(B9="","Название",""),IF(C9="","Тип недвижимости",""),IF(D9="","Страна",""),IF(E9="","Город",""),IF(F9="","Улица",""),IF(I9="","Валюта",""),IF(OR(AI9="",AI9<1),"Хотя бы 1 фото",""),IF(AND(OR(C9="Квартира",C9="Апартаменты",C9="Дом",C9="Вилла",C9="Коммерческая"),J9=""),"Площадь",""),IF(AND(OR(C9="Квартира",C9="Апартаменты"),K9=""),"Жилая площадь",""),IF(AND(OR(C9="Дом",C9="Вилла",C9="Земля"),L9=""),"Площадь участка",""),IF(AND(OR(C9="Квартира",C9="Апартаменты"),M9=""),"Комнаты",""),IF(AND(OR(C9="Дом",C9="Вилла"),N9=""),"Спальни",""),IF(AND(OR(C9="Квартира",C9="Апартаменты",C9="Дом",C9="Вилла"),O9=""),"Ванные",""),IF(AND(OR(C9="Квартира",C9="Апартаменты"),P9=""),"Этаж",""),IF(AND(OR(OR(C9="Квартира",C9="Апартаменты"),OR(C9="Дом",C9="Вилла")),Q9=""),"Этажей",""),IF(AND(OR(OR(C9="Квартира",C9="Апартаменты"),OR(C9="Дом",C9="Вилла")),OR(R9="",R9>YEAR(TODAY()))),"Год постройки",""),IF(AND(P9<>"",Q9<>"",P9>Q9),"Этаж больше этажности",""),IF(AND(OR(C9="Квартира",C9="Апартаменты",C9="Дом",C9="Вилла"),S9=""),"Материал",""),IF(AND(OR(C9="Коммерческая"),U9=""),"Тип коммерции",""),IF(AND(OR(C9="Земля"),V9=""),"Назначение земли",""),IF(W9="","Формат долга",""),IF(OR(X9="",X9<=0),"Сумма долга",""),IF(AND(W9="Долги + Аукцион",OR(Y9="",Y9<=0)),"Продать сейчас",""),IF(AND(W9="Долги + Аукцион",OR(Z9="",Z9<=0)),"Минимальная цена продажи",""),IF(AND(W9="Долги + Аукцион",OR(AA9="",AA9<=0)),"Стартовая ставка",""),IF(AND(W9="Долги + Аукцион",AB9=""),"Начало аукциона",""),IF(AND(W9="Долги + Аукцион",AC9=""),"Окончание аукциона",""),IF(AND(W9="Долги + Аукцион",AND(Y9<>"",Z9<>"",Z9>Y9)),"Минимальная цена выше «Продать сейчас»",""),IF(AND(W9="Долги + Аукцион",AND(Y9<>"",Z9<>"",Z9<=Y9,Z9>Y9*0.9)),"Минимальная цена выше 90% от «Продать сейчас»",""),IF(AND(W9="Долги + Аукцион",AND(Y9<>"",AA9<>"",AA9>Y9*0.3)),"Стартовая ставка выше 30% от «Продать сейчас»",""),IF(AND(W9="Долги + Аукцион",AND(AB9<>"",AC9<>"",AC9<EDATE(AB9,3)+15)),"Аукцион короче 3 месяцев и 15 дней",""))="","",TEXTJOIN(", ",TRUE,IF(B9="","Название",""),IF(C9="","Тип недвижимости",""),IF(D9="","Страна",""),IF(E9="","Город",""),IF(F9="","Улица",""),IF(I9="","Валюта",""),IF(OR(AI9="",AI9<1),"Хотя бы 1 фото",""),IF(AND(OR(C9="Квартира",C9="Апартаменты",C9="Дом",C9="Вилла",C9="Коммерческая"),J9=""),"Площадь",""),IF(AND(OR(C9="Квартира",C9="Апартаменты"),K9=""),"Жилая площадь",""),IF(AND(OR(C9="Дом",C9="Вилла",C9="Земля"),L9=""),"Площадь участка",""),IF(AND(OR(C9="Квартира",C9="Апартаменты"),M9=""),"Комнаты",""),IF(AND(OR(C9="Дом",C9="Вилла"),N9=""),"Спальни",""),IF(AND(OR(C9="Квартира",C9="Апартаменты",C9="Дом",C9="Вилла"),O9=""),"Ванные",""),IF(AND(OR(C9="Квартира",C9="Апартаменты"),P9=""),"Этаж",""),IF(AND(OR(OR(C9="Квартира",C9="Апартаменты"),OR(C9="Дом",C9="Вилла")),Q9=""),"Этажей",""),IF(AND(OR(OR(C9="Квартира",C9="Апартаменты"),OR(C9="Дом",C9="Вилла")),OR(R9="",R9>YEAR(TODAY()))),"Год постройки",""),IF(AND(P9<>"",Q9<>"",P9>Q9),"Этаж больше этажности",""),IF(AND(OR(C9="Квартира",C9="Апартаменты",C9="Дом",C9="Вилла"),S9=""),"Материал",""),IF(AND(OR(C9="Коммерческая"),U9=""),"Тип коммерции",""),IF(AND(OR(C9="Земля"),V9=""),"Назначение земли",""),IF(W9="","Формат долга",""),IF(OR(X9="",X9<=0),"Сумма долга",""),IF(AND(W9="Долги + Аукцион",OR(Y9="",Y9<=0)),"Продать сейчас",""),IF(AND(W9="Долги + Аукцион",OR(Z9="",Z9<=0)),"Минимальная цена продажи",""),IF(AND(W9="Долги + Аукцион",OR(AA9="",AA9<=0)),"Стартовая ставка",""),IF(AND(W9="Долги + Аукцион",AB9=""),"Начало аукциона",""),IF(AND(W9="Долги + Аукцион",AC9=""),"Окончание аукциона",""),IF(AND(W9="Долги + Аукцион",AND(Y9<>"",Z9<>"",Z9>Y9)),"Минимальная цена выше «Продать сейчас»",""),IF(AND(W9="Долги + Аукцион",AND(Y9<>"",Z9<>"",Z9<=Y9,Z9>Y9*0.9)),"Минимальная цена выше 90% от «Продать сейчас»",""),IF(AND(W9="Долги + Аукцион",AND(Y9<>"",AA9<>"",AA9>Y9*0.3)),"Стартовая ставка выше 30% от «Продать сейчас»",""),IF(AND(W9="Долги + Аукцион",AND(AB9<>"",AC9<>"",AC9<EDATE(AB9,3)+15)),"Аукцион короче 3 месяцев и 15 дней","")))) | AP9: =IF(NOT(COUNTA(A9:AN9)>0),"",IF(TEXTJOIN(", ",TRUE,IF(AL9="","Описание",""),IF(AND(AI9<>"",AI9>=1,AI9<5),"Фото меньше 5",""),IF(AK9="","Видео",""),IF(H9="","Кадастровый номер",""),IF(AJ9="","Ссылка на фото",""),IF(OR(AD9="",AD9="Нет"),"Кредитный договор",""),IF(OR(AE9="",AE9="Нет"),"Нотариальная закладная",""),IF(OR(AF9="",AF9="Нет"),"Выписка из реестра",""),IF(OR(AG9="",AG9="Нет"),"Оценка объекта",""),IF(AH9="","Статус в суде",""))="","",TEXTJOIN(", ",TRUE,IF(AL9="","Описание",""),IF(AND(AI9<>"",AI9>=1,AI9<5),"Фото меньше 5",""),IF(AK9="","Видео",""),IF(H9="","Кадастровый номер",""),IF(AJ9="","Ссылка на фото",""),IF(OR(AD9="",AD9="Нет"),"Кредитный договор",""),IF(OR(AE9="",AE9="Нет"),"Нотариальная закладная",""),IF(OR(AF9="",AF9="Нет"),"Выписка из реестра",""),IF(OR(AG9="",AG9="Нет"),"Оценка объекта",""),IF(AH9="","Статус в суде","")))) | AQ9: =IF(NOT(COUNTA(A9:AN9)>0),"",IF(AO9="","Можно публиковать","Не хватает"))
